Workbook

Sheet Resumen
A1: Green Alliance — tablero de avances
A2: Actualizado: 2026-10-23. Lo mantiene el agente ga-supervisor-avances a partir de docs/avances/plan.json.
B4: Parámetros
B5: Bloques por semana | C5: 10 | D5: 1 bloque = 1 punto de peso ≈ media jornada de trabajo. Se puede cambiar en la hoja Resumen.
B6: HOY (bloque donde termina lo hecho) | C6: 134 | D6: Calculado por el optimizador.
B8: Indicadores
B9: Actividades en el plan | C9: =COUNTA(Plan!$A$5:$A$129)
B10: Hechas | C10: =COUNTIF(Plan!$O$5:$O$129,"Hecho")
B11: En curso | C11: =COUNTIF(Plan!$O$5:$O$129,"En curso")
B12: Pendientes | C12: =COUNTIF(Plan!$O$5:$O$129,"Pendiente")
B13: Bloqueadas (esperan a la cooperativa) | C13: =COUNTIF(Plan!$O$5:$O$129,"Bloqueado")
B14: Peso total (puntos) | C14: =SUM(Plan!$D$5:$D$129)
B15: Peso hecho (puntos) | C15: =SUMIF(Plan!$O$5:$O$129,"Hecho",Plan!$D$5:$D$129)
B16: Avance ponderado por peso | C16: =IF(C14=0,0,C15/C14)
B17: Duración total optimizada (bloques) | C17: =MAX(Plan!$L$5:$L$129)
B18: Duración total optimizada (semanas) | C18: =C17/C5
B19: Si se hiciera en una sola fila (bloques) | C19: =C14
B20: Si se hiciera en una sola fila (semanas) | C20: =C19/C5
B21: Tiempo ahorrado con 2 filas | C21: =IF(C19=0,0,1-C17/C19)
B22: Falta desde HOY (semanas) | C22: =(C17-C6)/C5
B23: Uso de la Fila A | C23: =IF(C17=0,0,(SUMIF(Plan!$I$5:$I$129,"A",Plan!$E$5:$E$129)+SUMIF(Plan!$I$5:$I$129,"A+B",Plan!$E$5:$E$129))/C17)
B24: Uso de la Fila B | C24: =IF(C17=0,0,(SUMIF(Plan!$I$5:$I$129,"B",Plan!$E$5:$E$129)+SUMIF(Plan!$I$5:$I$129,"A+B",Plan!$E$5:$E$129))/C17)
B25: Plazo de la propuesta (semanas) | C25: =MAX('Propuesta original'!E5:E10)
B27: Avance por fase
B28: Fase | C28: Peso total | D28: Peso hecho | E28: Avance | F28: Termina (bloque) | G28: Termina (semana) | H28: Propuesta (semanas)
B29: 1. Diseño y arquitectura | C29: =SUMIF(Plan!$B$5:$B$129,"1. Diseño y arquitectura",Plan!$D$5:$D$129) | D29: =SUMIFS(Plan!$D$5:$D$129,Plan!$B$5:$B$129,"1. Diseño y arquitectura",Plan!$O$5:$O$129,"Hecho") | E29: =IF(C29=0,0,D29/C29) | F29: =SUMPRODUCT(MAX((Plan!$B$5:$B$129="1. Diseño y arquitectura")*Plan!$L$5:$L$129)) | G29: ="S"&ROUNDUP(F29/$C$5,0) | H29: ='Propuesta original'!E5
B30: 2. Landing y autenticación | C30: =SUMIF(Plan!$B$5:$B$129,"2. Landing y autenticación",Plan!$D$5:$D$129) | D30: =SUMIFS(Plan!$D$5:$D$129,Plan!$B$5:$B$129,"2. Landing y autenticación",Plan!$O$5:$O$129,"Hecho") | E30: =IF(C30=0,0,D30/C30) | F30: =SUMPRODUCT(MAX((Plan!$B$5:$B$129="2. Landing y autenticación")*Plan!$L$5:$L$129)) | G30: ="S"&ROUNDUP(F30/$C$5,0) | H30: ='Propuesta original'!E6
B31: 3. Flujo de solicitud de crédito | C31: =SUMIF(Plan!$B$5:$B$129,"3. Flujo de solicitud de crédito",Plan!$D$5:$D$129) | D31: =SUMIFS(Plan!$D$5:$D$129,Plan!$B$5:$B$129,"3. Flujo de solicitud de crédito",Plan!$O$5:$O$129,"Hecho") | E31: =IF(C31=0,0,D31/C31) | F31: =SUMPRODUCT(MAX((Plan!$B$5:$B$129="3. Flujo de solicitud de crédito")*Plan!$L$5:$L$129)) | G31: ="S"&ROUNDUP(F31/$C$5,0) | H31: ='Propuesta original'!E7
B32: 4. Panel de administración | C32: =SUMIF(Plan!$B$5:$B$129,"4. Panel de administración",Plan!$D$5:$D$129) | D32: =SUMIFS(Plan!$D$5:$D$129,Plan!$B$5:$B$129,"4. Panel de administración",Plan!$O$5:$O$129,"Hecho") | E32: =IF(C32=0,0,D32/C32) | F32: =SUMPRODUCT(MAX((Plan!$B$5:$B$129="4. Panel de administración")*Plan!$L$5:$L$129)) | G32: ="S"&ROUNDUP(F32/$C$5,0) | H32: ='Propuesta original'!E8
B33: 5. Convenios y pulido | C33: =SUMIF(Plan!$B$5:$B$129,"5. Convenios y pulido",Plan!$D$5:$D$129) | D33: =SUMIFS(Plan!$D$5:$D$129,Plan!$B$5:$B$129,"5. Convenios y pulido",Plan!$O$5:$O$129,"Hecho") | E33: =IF(C33=0,0,D33/C33) | F33: =SUMPRODUCT(MAX((Plan!$B$5:$B$129="5. Convenios y pulido")*Plan!$L$5:$L$129)) | G33: ="S"&ROUNDUP(F33/$C$5,0) | H33: ='Propuesta original'!E9
B34: 6. Pruebas y lanzamiento | C34: =SUMIF(Plan!$B$5:$B$129,"6. Pruebas y lanzamiento",Plan!$D$5:$D$129) | D34: =SUMIFS(Plan!$D$5:$D$129,Plan!$B$5:$B$129,"6. Pruebas y lanzamiento",Plan!$O$5:$O$129,"Hecho") | E34: =IF(C34=0,0,D34/C34) | F34: =SUMPRODUCT(MAX((Plan!$B$5:$B$129="6. Pruebas y lanzamiento")*Plan!$L$5:$L$129)) | G34: ="S"&ROUNDUP(F34/$C$5,0) | H34: ='Propuesta original'!E10
B36: Hitos de pago (propuesta)
B37: Pago | C37: Valor (COP) | D37: Fase | E37: Se libera en | F37: Bloque | G37: Semana | H37: Estado del hito
B38: Adelanto | C38: 500000 | D38: 1 | E38: Al iniciar el proyecto (Fase 1) | F38: 0 | G38: S1 | H38: ="Cumplido (inicio)"
B39: Pago 2 | C39: 800000 | D39: 3 | E39: Login y flujo de solicitud de crédito funcionando (fin Fase 3) | F39: =F31 | G39: =G31 | H39: =IF(E31=1,"Cumplido","Falta "&TEXT(1-E31,"0%"))
B40: Pago 3 | C40: 800000 | D40: 4 | E40: Panel de administración funcionando (fin Fase 4) | F40: =F32 | G40: =G32 | H40: =IF(E32=1,"Cumplido","Falta "&TEXT(1-E32,"0%"))
B41: Pago final | C41: 900000 | D41: 6 | E41: Entrega en producción (fin Fase 6) | F41: =F34 | G41: =G34 | H41: =IF(E34=1,"Cumplido","Falta "&TEXT(1-E34,"0%"))
B42: Total | C42: =SUM(C38:C41)
B44: Pendientes por categoría (hoja Pendientes)
B45: Categoría | C45: Hecho | D45: En curso | E45: Pendiente | F45: Bloqueado | G45: Total
B46: Decisión | C46: =COUNTIFS(Pendientes!$B$5:$B$149,$B46,Pendientes!$G$5:$G$149,"Hecho") | D46: =COUNTIFS(Pendientes!$B$5:$B$149,$B46,Pendientes!$G$5:$G$149,"En curso") | E46: =COUNTIFS(Pendientes!$B$5:$B$149,$B46,Pendientes!$G$5:$G$149,"Pendiente") | F46: =COUNTIFS(Pendientes!$B$5:$B$149,$B46,Pendientes!$G$5:$G$149,"Bloqueado") | G46: =SUM(C46:F46)
B47: Dato de la cooperativa | C47: =COUNTIFS(Pendientes!$B$5:$B$149,$B47,Pendientes!$G$5:$G$149,"Hecho") | D47: =COUNTIFS(Pendientes!$B$5:$B$149,$B47,Pendientes!$G$5:$G$149,"En curso") | E47: =COUNTIFS(Pendientes!$B$5:$B$149,$B47,Pendientes!$G$5:$G$149,"Pendiente") | F47: =COUNTIFS(Pendientes!$B$5:$B$149,$B47,Pendientes!$G$5:$G$149,"Bloqueado") | G47: =SUM(C47:F47)
B48: Configuración | C48: =COUNTIFS(Pendientes!$B$5:$B$149,$B48,Pendientes!$G$5:$G$149,"Hecho") | D48: =COUNTIFS(Pendientes!$B$5:$B$149,$B48,Pendientes!$G$5:$G$149,"En curso") | E48: =COUNTIFS(Pendientes!$B$5:$B$149,$B48,Pendientes!$G$5:$G$149,"Pendiente") | F48: =COUNTIFS(Pendientes!$B$5:$B$149,$B48,Pendientes!$G$5:$G$149,"Bloqueado") | G48: =SUM(C48:F48)
B49: Funcionalidad | C49: =COUNTIFS(Pendientes!$B$5:$B$149,$B49,Pendientes!$G$5:$G$149,"Hecho") | D49: =COUNTIFS(Pendientes!$B$5:$B$149,$B49,Pendientes!$G$5:$G$149,"En curso") | E49: =COUNTIFS(Pendientes!$B$5:$B$149,$B49,Pendientes!$G$5:$G$149,"Pendiente") | F49: =COUNTIFS(Pendientes!$B$5:$B$149,$B49,Pendientes!$G$5:$G$149,"Bloqueado") | G49: =SUM(C49:F49)
B50: Verificación y cierre | C50: =COUNTIFS(Pendientes!$B$5:$B$149,$B50,Pendientes!$G$5:$G$149,"Hecho") | D50: =COUNTIFS(Pendientes!$B$5:$B$149,$B50,Pendientes!$G$5:$G$149,"En curso") | E50: =COUNTIFS(Pendientes!$B$5:$B$149,$B50,Pendientes!$G$5:$G$149,"Pendiente") | F50: =COUNTIFS(Pendientes!$B$5:$B$149,$B50,Pendientes!$G$5:$G$149,"Bloqueado") | G50: =SUM(C50:F50)
B51: Seguridad | C51: =COUNTIFS(Pendientes!$B$5:$B$149,$B51,Pendientes!$G$5:$G$149,"Hecho") | D51: =COUNTIFS(Pendientes!$B$5:$B$149,$B51,Pendientes!$G$5:$G$149,"En curso") | E51: =COUNTIFS(Pendientes!$B$5:$B$149,$B51,Pendientes!$G$5:$G$149,"Pendiente") | F51: =COUNTIFS(Pendientes!$B$5:$B$149,$B51,Pendientes!$G$5:$G$149,"Bloqueado") | G51: =SUM(C51:F51)
B52: Código | C52: =COUNTIFS(Pendientes!$B$5:$B$149,$B52,Pendientes!$G$5:$G$149,"Hecho") | D52: =COUNTIFS(Pendientes!$B$5:$B$149,$B52,Pendientes!$G$5:$G$149,"En curso") | E52: =COUNTIFS(Pendientes!$B$5:$B$149,$B52,Pendientes!$G$5:$G$149,"Pendiente") | F52: =COUNTIFS(Pendientes!$B$5:$B$149,$B52,Pendientes!$G$5:$G$149,"Bloqueado") | G52: =SUM(C52:F52)
B53: Base de datos | C53: =COUNTIFS(Pendientes!$B$5:$B$149,$B53,Pendientes!$G$5:$G$149,"Hecho") | D53: =COUNTIFS(Pendientes!$B$5:$B$149,$B53,Pendientes!$G$5:$G$149,"En curso") | E53: =COUNTIFS(Pendientes!$B$5:$B$149,$B53,Pendientes!$G$5:$G$149,"Pendiente") | F53: =COUNTIFS(Pendientes!$B$5:$B$149,$B53,Pendientes!$G$5:$G$149,"Bloqueado") | G53: =SUM(C53:F53)

Sheet Pendientes
A1: Pendientes organizados
A2: Ordenados por categoría, estado y prioridad. «Actividad del plan» enlaza con la hoja Plan / Gantt.
A4: ID | B4: Categoría | C4: Área / pantalla | D4: Tarea | E4: Responsable | F4: Prioridad | G4: Estado | H4: Actividad del plan | I4: Fase de la actividad | J4: Nota
A5: P-145 | B5: Configuración | C5: Base de datos | D5: Correr pgTAP 35 y 36 cuando tenga Docker (las migraciones 20261022000000 y 20261023000000 ya están aplicadas; hoy el PC no tiene la virtualización activa) | E5: Sebas | F5: Alta | G5: Pendiente | H5: 6.44 | I5: =IFERROR(INDEX(Plan!$B$5:$B$129,MATCH(H5,Plan!$A$5:$A$129,0)),"—") | J5: 23-oct: migraciones aplicadas y verificadas con migration list --linked; queda solo pgTAP.
A6: P-105 | B6: Configuración | C6: Vercel/Resend | D6: CRON_SECRET de 32+ caracteres, publicar plantilla ga-aviso-institucional y crear RESEND_TEMPLATE_AVISO_INSTITUCIONAL | E6: Sebas | F6: Alta | G6: Hecho | H6: 6.22 | I6: =IFERROR(INDEX(Plan!$B$5:$B$129,MATCH(H6,Plan!$A$5:$A$129,0)),"—") | J6: 30-sep: Sebas lo hizo en producción.
A7: P-110 | B7: Configuración | C7: Base de datos | D7: Aplicar la migración 20261001000000 antes de desplegar (sin ella falla el insert de afiliación por la columna version_politica_datos) | E7: Sebas | F7: Alta | G7: Hecho | H7: 6.23 | I7: =IFERROR(INDEX(Plan!$B$5:$B$129,MATCH(H7,Plan!$A$5:$A$129,0)),"—") | J7: 30-sep: reportado por ga-auditor-supabase y ga-funcionalidad-botones. 01-oct: aplicada en producción.
A8: P-113 | B8: Configuración | C8: Base de datos | D8: Docker: db reset + test db local y aplicar la migración 20261001100000 en producción | E8: Sebas | F8: Alta | G8: Hecho | H8: 6.24 | I8: =IFERROR(INDEX(Plan!$B$5:$B$129,MATCH(H8,Plan!$A$5:$A$129,0)),"—") | J8: 01-oct: Docker Desktop no arranca («unable to start»). 01-oct: Docker de vuelta; db test local en verde (22 archivos, 497 pruebas). Falta solo db push --linked de 20261001000000 y 20261001100000 y fusionar develop→main. 01-oct: 20261001000000 y 20261001100000 aplicadas en producción.
A9: P-114 | B9: Configuración | C9: Base de datos | D9: Aplicar la migración 20261002000000 en producción y fusionar develop→main (commit e2523de) | E9: Sebas | F9: Alta | G9: Hecho | H9: 6.25 | I9: =IFERROR(INDEX(Plan!$B$5:$B$129,MATCH(H9,Plan!$A$5:$A$129,0)),"—") | J9: 01-oct: sin ella /admin/convenios y la lectura de convenios por visible/orden fallan en producción (el loader tiene respaldo en CONVENIOS). Probar subida de logo con un admin real. 02-oct: cerrada; la fusión develop→main sigue en P-116 (6.27).
A10: P-116 | B10: Configuración | C10: Base de datos | D10: Aplicar con respaldo previo 20261002500000, 20261002600000, 20261003000000, 20261003100000 y 20261003200000 y 20261003300000 y fusionar develop→main | E10: Sebas | F10: Alta | G10: Hecho | H10: 6.27 | I10: =IFERROR(INDEX(Plan!$B$5:$B$129,MATCH(H10,Plan!$A$5:$A$129,0)),"—") | J10: 02-oct: 20261003000000 quita la FK perfiles.id → auth.users (cascada por trigger). 09-oct: Hecho por Sebas.
A11: P-117 | B11: Configuración | C11: Correos | D11: Plantilla del sorteo en Vercel/Resend (variables NOMBRE, NUMERO_BOLETA, MES) y {{{COMPROBANTE}}} en la plantilla de desembolso | E11: Sebas | F11: Alta | G11: Hecho | H11: 6.28 | I11: =IFERROR(INDEX(Plan!$B$5:$B$129,MATCH(H11,Plan!$A$5:$A$129,0)),"—") | J11: 02-oct: sin la plantilla, el correo del sorteo cae a texto plano (docs/resend-plantillas.md). 09-oct: Hecho por Sebas.
A12: P-135 | B12: Configuración | C12: Base de datos | D12: Aplicar la migración 20261008000000 (Patrullero de Policía) con respaldo previo | E12: Sebas | F12: Alta | G12: Hecho | H12: 6.36 | I12: =IFERROR(INDEX(Plan!$B$5:$B$129,MATCH(H12,Plan!$A$5:$A$129,0)),"—") | J12: 08-oct: db push, verificando antes migration list --linked. 09-oct: Hecho por Sebas.
A13: P-138 | B13: Configuración | C13: Base de datos | D13: Aplicar con respaldo previo la migración 20261009000000 (hallazgos de seguridad del 8-oct), verificando antes migration list --linked | E13: Sebas | F13: Alta | G13: Hecho | H13: 6.39 | I13: =IFERROR(INDEX(Plan!$B$5:$B$129,MATCH(H13,Plan!$A$5:$A$129,0)),"—") | J13: 09-oct: incluye la RPC fotos_carne_huerfanas. Sin ella el código nuevo no funciona. 09-oct: Hecho por Sebas.
A14: P-139 | B14: Configuración | C14: Despliegue | D14: Desplegar el código nuevo de inmediato junto con la migración 20261009000000 | E14: Sebas | F14: Alta | G14: Hecho | H14: 6.40 | I14: =IFERROR(INDEX(Plan!$B$5:$B$129,MATCH(H14,Plan!$A$5:$A$129,0)),"—") | J14: 09-oct: código y migración van juntos. Desactivar a un admin ya no se puede desde la app; si la cooperativa lo necesita, hace falta otra migración. 09-oct: Hecho por Sebas.
A15: P-141 | B15: Configuración | C15: Base de datos | D15: Aplicar la migración 20261014000000 (afiliación sin repetidos) con db push y correr pgTAP con Docker | E15: Sebas | F15: Alta | G15: Hecho | H15: 6.41 | I15: =IFERROR(INDEX(Plan!$B$5:$B$129,MATCH(H15,Plan!$A$5:$A$129,0)),"—") | J15: 18-oct: aplicada por Sebas; pgTAP en verde.
A16: P-142 | B16: Configuración | C16: Base de datos | D16: Aplicar la migración 20261018000000 (pausa de cuenta y avisos) con db push y correr pgTAP 33 con Docker | E16: Sebas | F16: Alta | G16: Hecho | H16: 6.41 | I16: =IFERROR(INDEX(Plan!$B$5:$B$129,MATCH(H16,Plan!$A$5:$A$129,0)),"—") | J16: 18-oct: aplicada por Sebas; pgTAP 33 en verde. La prueba de selfie en celular real pasó a P-143.
... A35: P-56 | B35: Funcionalidad | C35: /cuenta/solicitar | D35: Revisar el diseño de /cuenta/solicitar (sin maqueta; selector 50/100 como radios) | E35: ga-diseno-a-codigo | F35: Media | G35: Pendiente | H35: 5.6 | I35: =IFERROR(INDEX(Plan!$B$5:$B$129,MATCH(H35,Plan!$A$5:$A$129,0)),"—") | J35: Pedido por ga-funcionalidad-botones el 23-sep.
A36: P-22 | B36: Funcionalidad | C36: /ingresar | D36: Server Action: correo_por_cedula(), signInWithOtp, cookie firmada, ir a /ingresar/codigo | E36: ga-funcionalidad-botones | F36: Alta | G36: Hecho | H36: 2.5 | I36: =IFERROR(INDEX(Plan!$B$5:$B$129,MATCH(H36,Plan!$A$5:$A$129,0)),"—")
A37: P-24 | B37: Funcionalidad | C37: /ingresar/codigo | D37: Leer la cookie del paso 1; sin cookie, volver a /ingresar | E37: ga-funcionalidad-botones | F37: Alta | G37: Hecho | H37: 2.6 | I37: =IFERROR(INDEX(Plan!$B$5:$B$129,MATCH(H37,Plan!$A$5:$A$129,0)),"—")
A38: P-25 | B38: Funcionalidad | C38: /ingresar/codigo | D38: verifyOtp y entrar a /cuenta | E38: ga-funcionalidad-botones | F38: Alta | G38: Hecho | H38: 2.6 | I38: =IFERROR(INDEX(Plan!$B$5:$B$129,MATCH(H38,Plan!$A$5:$A$129,0)),"—")
A39: P-28 | B39: Funcionalidad | C39: /afiliacion | D39: Server Action: zod, límites por IP y cédula, guardar | E39: ga-funcionalidad-botones | F39: Alta | G39: Hecho | H39: 2.9 | I39: =IFERROR(INDEX(Plan!$B$5:$B$129,MATCH(H39,Plan!$A$5:$A$129,0)),"—") | J39: 23-sep: se quitaron los correos al equipo y al solicitante (decisión de Sebas). El equipo revisa las afiliaciones en Supabase hasta que exista el panel /admin; el correo «Ingreso aceptado» sale al aprobar (P-51).
A40: P-31 | B40: Funcionalidad | C40: /cuenta | D40: Proteger con proxy.ts y «Salir» con signOut | E40: ga-funcionalidad-botones | F40: Alta | G40: Hecho | H40: 2.7 | I40: =IFERROR(INDEX(Plan!$B$5:$B$129,MATCH(H40,Plan!$A$5:$A$129,0)),"—")
A41: P-32 | B41: Funcionalidad | C41: /cuenta | D41: Cargar perfil, última solicitud (con tasa), tope y convenios | E41: ga-funcionalidad-botones | F41: Alta | G41: Hecho | H41: 3.5 | I41: =IFERROR(INDEX(Plan!$B$5:$B$129,MATCH(H41,Plan!$A$5:$A$129,0)),"—")
A42: P-35 | B42: Funcionalidad | C42: Crédito | D42: Conectar el formulario de crédito a /cuenta | E42: ga-funcionalidad-botones | F42: Alta | G42: Hecho | H42: 3.7 | I42: =IFERROR(INDEX(Plan!$B$5:$B$129,MATCH(H42,Plan!$A$5:$A$129,0)),"—") | J42: 23-sep: el formulario vive en /cuenta/solicitar (protegida por proxy.ts, encabezado compartido EncabezadoCuenta); «Nueva solicitud» lleva ahí.
A43: P-36 | B43: Funcionalidad | C43: Admin | D43: Panel /admin: listado, aprobar y rechazar con motivo | E43: ga-funcionalidad-botones | F43: Alta | G43: Hecho | H43: 4.1 | I43: =IFERROR(INDEX(Plan!$B$5:$B$129,MATCH(H43,Plan!$A$5:$A$129,0)),"—") | J43: 24-sep: implementado y probado en local (commits 235ffbe, a13c2de). Un admin no puede resolver su propia solicitud.
A44: P-37 | B44: Funcionalidad | C44: Correos | D44: Correo «Resultado del crédito» (aprobado / no aprobado) al asociado al resolver una solicitud | E44: ga-funcionalidad-botones | F44: Alta | G44: Hecho | H44: 4.3 | I44: =IFERROR(INDEX(Plan!$B$5:$B$129,MATCH(H44,Plan!$A$5:$A$129,0)),"—") | J44: 24-sep: enviarResultadoCredito ya está conectado al aprobar/rechazar en /admin (probado en local); falta que Sebas configure el SMTP/Resend de producción (2.4) para que salga de verdad.
A45: P-38 | B45: Funcionalidad | C45: Asociados | D45: Importación de asociados desde Excel | E45: ga-funcionalidad-botones | F45: Alta | G45: Hecho | H45: 4.4 | I45: =IFERROR(INDEX(Plan!$B$5:$B$129,MATCH(H45,Plan!$A$5:$A$129,0)),"—") | J45: Ya no aplica: decisión de la cooperativa 2026-09-24, no habrá importación de Excel.
A46: P-51 | B46: Funcionalidad | C46: Correos | D46: Correo «Ingreso aceptado» (plantilla ga-ingreso-aceptado): acción del admin que aprueba la afiliación, crea el usuario y envía el correo | E46: ga-funcionalidad-botones | F46: Alta | G46: Hecho | H46: 4.5 | I46: =IFERROR(INDEX(Plan!$B$5:$B$129,MATCH(H46,Plan!$A$5:$A$129,0)),"—") | J46: 01-oct: verificado en el código: aprobarAfiliacion (app/admin/afiliaciones/actions.ts) crea el usuario y envía enviarIngresoAceptado (lib/correo/ingreso.ts).
A47: P-66 | B47: Funcionalidad | C47: Admin | D47: Dashboard de clientes en /admin: métricas (asociados por grado/institución, afiliaciones y créditos pendientes, montos del mes, inscritos al sorteo), lista con buscador/filtros, detalle de cliente y reasignar asesor | E47: Carlos Pardo | F47: Alta | G47: Hecho | H47: 4.7 | I47: =IFERROR(INDEX(Plan!$B$5:$B$129,MATCH(H47,Plan!$A$5:$A$129,0)),"—") | J47: Encargo externo (500.000 COP) por PR a develop. Ver P-73. 30-sep: Carlos salió; pasa a ga-funcionalidad-botones. 01-oct: verificado en el código y cerrado con 4.7 (ResumenAdmin, /admin/asociados con buscador y detalle, asignarAsesor). «Inscritos al sorteo» sigue en P-111.
A48: P-67 | B48: Funcionalidad | C48: Asesor | D48: Dashboard del asesor en /asesor: métricas de sus clientes y detalle de cliente sin celular, correo, Nequi ni fotos | E48: Carlos Pardo | F48: Alta | G48: Hecho | H48: 4.8 | I48: =IFERROR(INDEX(Plan!$B$5:$B$129,MATCH(H48,Plan!$A$5:$A$129,0)),"—") | J48: Encargo externo (500.000 COP) por PR a develop. Ver P-73. 30-sep: Carlos salió; pasa a ga-funcionalidad-botones. 01-oct: verificado en el código y cerrado con 4.8 (/asesor con métricas; el loader no selecciona celular, correo, Nequi ni fotos).
A49: P-69 | B49: Funcionalidad | C49: Legal | D49: Ley 1581: borrado automático de fotos de afiliaciones rechazadas tras X días y motivo de rechazo en /admin | E49: Carlos Pardo | F49: Alta | G49: Hecho | H49: 5.10 | I49: =IFERROR(INDEX(Plan!$B$5:$B$129,MATCH(H49,Plan!$A$5:$A$129,0)),"—") | J49: Encargo externo (500.000 COP) por PR a develop. Falta que la cooperativa dé el X de días (ver P-63). Ver P-73. 29-sep: primera entrega (ZIP, base main anterior al rediseño C+) NO fusionable — reintroduce F2-03, pierde el revoke en resumen_clientes_asesor, columna de motivo de rechazo inexistente sin migración, purga con columnas/bucket equivocados y cron abierto sin CRON_SECRET, claves en .env.example, console.log, config de túnel, sin pruebas. Se le envió la lista de correcciones para rehacer sobre rediseno-c-plus, un PR por tarea. 30-sep: hecho por agentes (cron cada hora + RPC fotos_huerfanas_afiliacion).
A50: P-85 | B50: Funcionalidad | C50: /afiliacion | D50: Correo de afiliación acepta cualquier dominio (ya no exige @policia.gov.co / @ejercito.mil.co) | E50: sesión principal | F50: Alta | G50: Hecho | H50: 2.12 | I50: =IFERROR(INDEX(Plan!$B$5:$B$129,MATCH(H50,Plan!$A$5:$A$129,0)),"—") | J50: 25-sep: esquema zod, campo del formulario y pruebas (unitarias, e2e, pgTAP) actualizados; migración 20260925194922_correo_afiliacion_cualquier_dominio aplicada en producción (base de datos) y el archivo local renombrado a esa versión para que el historial coincida. F-01 revisado: la máscara del correo ahora oculta también el dominio («ju•••@•••»). 25-sep: desplegado con el PR #2 (merge 2c19d02); confirmado en vivo que /afiliacion ya no exige correo institucional.
A51: P-112 | B51: Funcionalidad | C51: Pruebas | D51: Agregar admin_metricas_dashboard y asesor_metricas_dashboard a las listas blancas de security definer (pgTAP 00 #14 y 15 #24) | E51: ga-escritor-tests | F51: Media | G51: Hecho | H51: 6.21 | I51: =IFERROR(INDEX(Plan!$B$5:$B$129,MATCH(H51,Plan!$A$5:$A$129,0)),"—") | J51: 30-sep: reportado por ga-auditor-supabase. 01-oct: listas blancas de 00 y 15 actualizadas por ga-auditor-supabase (falta correrlas: Docker).
A52: P-23 | B52: Funcionalidad | C52: /ingresar | D52: Estado «Enviando…» (prop cargando) y errores (prop error) | E52: ga-funcionalidad-botones | F52: Media | G52: Hecho | H52: 2.5 | I52: =IFERROR(INDEX(Plan!$B$5:$B$129,MATCH(H52,Plan!$A$5:$A$129,0)),"—")
A53: P-26 | B53: Funcionalidad | C53: /ingresar/codigo | D53: Casillas OTP: avance automático, Backspace, pegar; «Entrar» con 6 dígitos | E53: ga-funcionalidad-botones | F53: Media | G53: Hecho | H53: 2.6 | I53: =IFERROR(INDEX(Plan!$B$5:$B$129,MATCH(H53,Plan!$A$5:$A$129,0)),"—")
A54: P-27 | B54: Funcionalidad | C54: /ingresar/codigo | D54: «Reenviar código» con contador de 45 s; «Cambiar cédula» limpia la cookie | E54: ga-funcionalidad-botones | F54: Media | G54: Hecho | H54: 2.6 | I54: =IFERROR(INDEX(Plan!$B$5:$B$129,MATCH(H54,Plan!$A$5:$A$129,0)),"—")
A55: P-29 | B55: Funcionalidad | C55: /afiliacion | D55: Grados desde grados_credito, honeypot, errores y estado de carga | E55: ga-funcionalidad-botones | F55: Media | G55: Hecho | H55: 2.9 | I55: =IFERROR(INDEX(Plan!$B$5:$B$129,MATCH(H55,Plan!$A$5:$A$129,0)),"—")
A56: P-33 | B56: Funcionalidad | C56: /cuenta | D56: «Mis datos»: actualizar solo perfiles.telefono | E56: ga-funcionalidad-botones | F56: Media | G56: Hecho | H56: 3.6 | I56: =IFERROR(INDEX(Plan!$B$5:$B$129,MATCH(H56,Plan!$A$5:$A$129,0)),"—") | J56: Con error, alinear «Guardar» con el campo desde 640 px.
A57: P-48 | B57: Funcionalidad | C57: /afiliacion | D57: F-01: el select «Grado» se vacía tras un error de validación | E57: ga-funcionalidad-botones | F57: Media | G57: Hecho | H57: 2.11 | I57: =IFERROR(INDEX(Plan!$B$5:$B$129,MATCH(H57,Plan!$A$5:$A$129,0)),"—") | J57: Falla media de la verificación QA 1 (docs/verificaciones/2026-09-23-verificacion-1.md). 01-oct: corregido (formulario se rehace con key; conserva Institución/Grado).
A58: P-57 | B58: Funcionalidad | C58: /asesor | D58: Agregar /asesor al matcher de proxy.ts y redirigir por rol tras el login | E58: ga-funcionalidad-botones | F58: Media | G58: Hecho | H58: 4.6 | I58: =IFERROR(INDEX(Plan!$B$5:$B$129,MATCH(H58,Plan!$A$5:$A$129,0)),"—") | J58: 01-oct: verificado en el código: /asesor en el matcher de proxy.ts y redirección por rol en app/ingresar/actions.ts.
A59: P-68 | B59: Funcionalidad | C59: Convenios | D59: Convenios administrables desde /admin (crear, editar, ocultar, ordenar, logo en Storage); landing y /cuenta leen de la tabla convenios | E59: Carlos Pardo | F59: Media | G59: Hecho | H59: 5.9 | I59: =IFERROR(INDEX(Plan!$B$5:$B$129,MATCH(H59,Plan!$A$5:$A$129,0)),"—") | J59: Encargo externo (500.000 COP) por PR a develop. Ver P-73. 30-sep: Carlos salió; pasa a ga-funcionalidad-botones. 01-oct: hecho por agentes (5.9); falta aplicar 20261002000000 (P-114).
A60: P-74 | B60: Funcionalidad | C60: /afiliacion | D60: Bug: esquemaAfiliacion no valida el cruce institución↔correo institucional si falla cualquier otro campo del formulario | E60: ga-funcionalidad-botones | F60: Media | G60: Hecho | H60: 2.13 | I60: =IFERROR(INDEX(Plan!$B$5:$B$129,MATCH(H60,Plan!$A$5:$A$129,0)),"—") | J60: Reportado por ga-escritor-tests el 24-sep; reproducido en tests/unit/validaciones.test.ts y en tests/e2e/d-afiliacion.spec.ts (D4, casos bug: true). Falta correr npm run test:db (pgTAP), bloqueado por el permiso de la sandbox. Corregido por la sesión principal el 2026-09-24 (commit fedf620): superRefine con `when`; 308 unitarias, 96 e2e de afiliación y 222 pgTAP en verde.
A61: P-89 | B61: Funcionalidad | C61: Admin | D61: Cuenta de demostración para administradores en /admin/demo (pestaña «Demostración») | E61: sesión principal | F61: Media | G61: Hecho | H61: 4.9 | I61: =IFERROR(INDEX(Plan!$B$5:$B$129,MATCH(H61,Plan!$A$5:$A$129,0)),"—") | J61: 25-sep: reutiliza la cuenta fantasma de /asesor/demo; lectura de grados compartida en lib/asesor/cargarPaquetesDemo.ts; un asesor no puede entrar. 25-sep: desplegado con el PR #2 (merge 2c19d02); confirmado por HTTP que /admin/demo redirige a /ingresar sin sesión. Falta que Sebas la confirme a ojo con su propia sesión.
A62: P-108 | B62: Funcionalidad | C62: Asesor | D62: Backlog: premio al primer asesor | E62: ga-funcionalidad-botones | F62: Baja | G62: Hecho | H62: 5.11 | I62: =IFERROR(INDEX(Plan!$B$5:$B$129,MATCH(H62,Plan!$A$5:$A$129,0)),"—") | J62: Spec §12.12
A63: P-109 | B63: Funcionalidad | C63: /cuenta | D63: Backlog: carné virtual del asociado | E63: ga-diseno-a-codigo | F63: Baja | G63: Hecho | H63: 5.12 | I63: =IFERROR(INDEX(Plan!$B$5:$B$129,MATCH(H63,Plan!$A$5:$A$129,0)),"—") | J63: Spec §12.12 01-oct: carné virtual en /cuenta (5.12).
A64: P-30 | B64: Funcionalidad | C64: /afiliacion/enviada | D64: Mostrar el correo real; si se entra directo, redirigir | E64: ga-funcionalidad-botones | F64: Baja | G64: Hecho | H64: 2.10 | I64: =IFERROR(INDEX(Plan!$B$5:$B$129,MATCH(H64,Plan!$A$5:$A$129,0)),"—")
A65: P-34 | B65: Funcionalidad | C65: Landing | D65: «Mi cuenta», «Ingresar», «Solicitar crédito», «Ver beneficios» → /cuenta con sesión | E65: ga-funcionalidad-botones | F65: Baja | G65: Hecho | H65: 2.8 | I65: =IFERROR(INDEX(Plan!$B$5:$B$129,MATCH(H65,Plan!$A$5:$A$129,0)),"—") | J65: Convenios fijos en la landing por ahora.
A66: P-124 | B66: Dato de la cooperativa | C66: Landing | D66: Fotos de las sedes | E66: Cooperativa | F66: Baja | G66: Pendiente | H66: 5.3 | I66: =IFERROR(INDEX(Plan!$B$5:$B$129,MATCH(H66,Plan!$A$5:$A$129,0)),"—")
A67: P-16 | B67: Dato de la cooperativa | C67: Landing | D67: Fotos reales, cifras y testimonios | E67: Cooperativa | F67: Baja | G67: Pendiente | H67: 5.3 | I67: =IFERROR(INDEX(Plan!$B$5:$B$129,MATCH(H67,Plan!$A$5:$A$129,0)),"—") | J67: 23-sep: los espacios de foto de la landing ya tienen diseño de marca (EspacioFoto). Para poner la foto real se cambia `null` por { src, alt }. Faltan las fotos de la cooperativa.
A68: P-14 | B68: Dato de la cooperativa | C68: Legal | D68: Texto de la política de datos | E68: Cooperativa | F68: Alta | G68: Hecho | H68: 5.4 | I68: =IFERROR(INDEX(Plan!$B$5:$B$129,MATCH(H68,Plan!$A$5:$A$129,0)),"—") | J68: Ruta /politica-de-datos ya existe. 24-sep: borrador completo con 10 secciones (Ley 1581, Decreto 1377) y la autorización de datos sensibles para fotos y selfie; los datos que faltan quedan resaltados en la página con <Pendiente>. Faltan de la cooperativa: NIT/dirección/ciudad (P-75), fecha de vigencia (P-76), país o región de los servidores -Supabase, Vercel, Resend- (P-77), alternativa de verificación sin selfie (P-78), plazos de conservación de fotos y demás datos (P-79, ligado a P-63) y si reportan a centrales de riesgo Ley 1266 (P-80); y falta revisión de un abogado (P-81). Bloquea el despliegue.
A69: P-18 | B69: Dato de la cooperativa | C69: Asociados | D69: Correos reales de los asociados (Excel de importación) | E69: Cooperativa | F69: Alta | G69: Hecho | H69: 4.4 | I69: =IFERROR(INDEX(Plan!$B$5:$B$129,MATCH(H69,Plan!$A$5:$A$129,0)),"—") | J69: Ya no aplica: decisión de la cooperativa 2026-09-24, no habrá importación de Excel. El ingreso ahora se resuelve con la afiliación v2 (correo institucional propio) más aprobación en /admin.
A70: P-75 | B70: Dato de la cooperativa | C70: Legal | D70: NIT, dirección y ciudad de la cooperativa para la política de datos | E70: Cooperativa | F70: Alta | G70: Hecho | H70: 5.4 | I70: =IFERROR(INDEX(Plan!$B$5:$B$129,MATCH(H70,Plan!$A$5:$A$129,0)),"—") | J70: 24-sep: reportado por la sesión principal, necesario para publicar /politica-de-datos. 30-sep: NIT 902.103.335-7, Cr 78 No. 16 D 71, Bogotá (Cámara de Comercio).
A71: P-76 | B71: Dato de la cooperativa | C71: Legal | D71: Fecha de vigencia de la política de datos | E71: Cooperativa | F71: Alta | G71: Hecho | H71: 5.4 | I71: =IFERROR(INDEX(Plan!$B$5:$B$129,MATCH(H71,Plan!$A$5:$A$129,0)),"—") | J71: 24-sep: reportado por la sesión principal.
A72: P-77 | B72: Dato de la cooperativa | C72: Legal | D72: País o región de los servidores (Supabase, Vercel, Resend) | E72: Cooperativa | F72: Alta | G72: Hecho | H72: 5.4 | I72: =IFERROR(INDEX(Plan!$B$5:$B$129,MATCH(H72,Plan!$A$5:$A$129,0)),"—") | J72: 24-sep: reportado por la sesión principal, dato exigido por la Ley 1581 para informar transferencia internacional de datos.
A73: P-78 | B73: Dato de la cooperativa | C73: Legal | D73: Alternativa de verificación para quien no quiera subir la selfie | E73: Cooperativa | F73: Alta | G73: Hecho | H73: 5.4 | I73: =IFERROR(INDEX(Plan!$B$5:$B$129,MATCH(H73,Plan!$A$5:$A$129,0)),"—") | J73: 24-sep: reportado por la sesión principal.
A74: P-79 | B74: Dato de la cooperativa | C74: Legal | D74: Plazos de conservación de los datos (fotos de rechazados y de asociados, y demás datos) | E74: Cooperativa | F74: Alta | G74: Hecho | H74: 5.4 | I74: =IFERROR(INDEX(Plan!$B$5:$B$129,MATCH(H74,Plan!$A$5:$A$129,0)),"—") | J74: 24-sep: reportado por la sesión principal; el plazo de las fotos es el mismo que decida P-63 (borrado automático de fotos rechazadas, 5.10).
A75: P-10 | B75: Dato de la cooperativa | C75: Configuración | D75: Número de WhatsApp (NEXT_PUBLIC_WHATSAPP) | E75: Cooperativa | F75: Media | G75: Hecho | H75: 5.3 | I75: =IFERROR(INDEX(Plan!$B$5:$B$129,MATCH(H75,Plan!$A$5:$A$129,0)),"—") | J75: 24-sep: 311 724 1942.
A76: P-11 | B76: Dato de la cooperativa | C76: Configuración | D76: Días hábiles de respuesta (DIAS_RESPUESTA) | E76: Cooperativa | F76: Media | G76: Hecho | H76: 5.3 | I76: =IFERROR(INDEX(Plan!$B$5:$B$129,MATCH(H76,Plan!$A$5:$A$129,0)),"—") | J76: 24-sep: la cooperativa dio el tiempo de respuesta como «4 horas o menos» (ver P-17); se usa ese dato en vez de días hábiles.
A77: P-12 | B77: Dato de la cooperativa | C77: Configuración | D77: Correo de contacto (CORREO_CONTACTO) | E77: Cooperativa | F77: Media | G77: Hecho | H77: 5.3 | I77: =IFERROR(INDEX(Plan!$B$5:$B$129,MATCH(H77,Plan!$A$5:$A$129,0)),"—") | J77: 24-sep: soporte@greenallianceco.com.
A78: P-13 | B78: Dato de la cooperativa | C78: Configuración | D78: Texto de vigilancia de Supersolidaria (TEXTO_VIGILANCIA) | E78: Cooperativa | F78: Media | G78: Hecho | H78: 5.3 | I78: =IFERROR(INDEX(Plan!$B$5:$B$129,MATCH(H78,Plan!$A$5:$A$129,0)),"—") | J78: 25-sep: Sebas confirmó que la cooperativa está vigilada por la Supersolidaria; TEXTO_VIGILANCIA pasa a «Vigilada por Supersolidaria» en local (falta desplegar).
... A93: P-41 | B93: Verificación y cierre | C93: Git | D93: Commit de las pantallas nuevas | E93: Yo | F93: Alta | G93: Hecho | H93: — | I93: =IFERROR(INDEX(Plan!$B$5:$B$129,MATCH(H93,Plan!$A$5:$A$129,0)),"—") | J93: Commit d86db86 en develop.
A94: P-42 | B94: Verificación y cierre | C94: Despliegue | D94: Subir a GitHub y desplegar en Vercel | E94: Yo | F94: Alta | G94: Hecho | H94: 6.5 | I94: =IFERROR(INDEX(Plan!$B$5:$B$129,MATCH(H94,Plan!$A$5:$A$129,0)),"—")
A95: P-58 | B95: Verificación y cierre | C95: Pruebas | D95: Actualizar tests/e2e a la afiliación v2 y a la nueva máscara de correo | E95: ga-escritor-tests | F95: Alta | G95: Hecho | H95: 6.1 | I95: =IFERROR(INDEX(Plan!$B$5:$B$129,MATCH(H95,Plan!$A$5:$A$129,0)),"—") | J95: d-afiliacion.spec.ts usa el formulario viejo (nombres y apellidos, unidad) y hace falta reescribirlo entero para institución/Nequi/asesor/fotos (k-roles.spec.ts ya cubre un caso feliz v2 pero no reemplaza la cobertura de D). 24-sep: ga-escritor-tests lo reescribió entero (48 pruebas × 2 proyectos); 92/96 pasan, 4 fallan por un bug real de la app (ver P-74), no de la prueba. b-ingreso.spec.ts, i-despliegue.spec.ts y j-produccion.spec.ts siguen con el formato viejo de máscara de correo y dominios (formato nuevo xx•••@yy•••.co); ese trabajo pasa a Carlos Pardo (ver P-71, 6.15). Falta correr npm run test:db (pgTAP), bloqueado por el permiso de la sandbox. Actualización: el bug de P-74 ya está corregido y d-afiliacion pasa 96/96; pgTAP 222/222 corrido por la sesión principal.
A96: P-64 | B96: Verificación y cierre | C96: Git | D96: Abrir el PR de develop a main | E96: Sebas | F96: Alta | G96: Hecho | H96: 6.5 | I96: =IFERROR(INDEX(Plan!$B$5:$B$129,MATCH(H96,Plan!$A$5:$A$129,0)),"—") | J96: 25-sep: Sebas abrió y fusionó el PR #1 develop → main (merge 5a39d34); Vercel desplegó fase 2 en producción.
A97: P-82 | B97: Verificación y cierre | C97: Despliegue | D97: Probar en producción con sesión real de los 3 administradores (ingreso con código OTP y logo del correo) | E97: Sebas | F97: Alta | G97: Hecho | H97: 6.5 | I97: =IFERROR(INDEX(Plan!$B$5:$B$129,MATCH(H97,Plan!$A$5:$A$129,0)),"—") | J97: 25-sep: Sebas entró con su cédula y le apareció el panel de administrador (falta confirmar Ricardo y abogadosprieto). 25-sep: reportado por la sesión principal tras el despliegue de fase 2; falta esta prueba manual antes de cerrar 6.5.
A98: P-86 | B98: Verificación y cierre | C98: /afiliacion | D98: A-01: la ayuda del dominio de correo institucional no se actualiza en vivo al elegir Policía/Ejército | E98: ga-funcionalidad-botones | F98: Alta | G98: Hecho | H98: 6.3 | I98: =IFERROR(INDEX(Plan!$B$5:$B$129,MATCH(H98,Plan!$A$5:$A$129,0)),"—") | J98: 25-sep: Sebas confirmó el correo de cualquier dominio (P-85); la ayuda por institución ya no existe. 25-sep: hallazgo de ga-verificador-qa. Condicionado a P-85: si se despliega el cambio a «correo de cualquier dominio» queda superado (ya no habría ayuda de dominio que actualizar); si Sebas decide mantener el chequeo institucional, hay que corregir el texto en vivo. Pendiente de esa decisión.
A99: P-40 | B99: Verificación y cierre | C99: Código | D99: Borrar /login y /dashboard cuando /ingresar y /cuenta funcionen | E99: Yo | F99: Media | G99: Hecho | H99: 5.5 | I99: =IFERROR(INDEX(Plan!$B$5:$B$129,MATCH(H99,Plan!$A$5:$A$129,0)),"—") | J99: Borradas el 23-sep (incluida /dashboard/solicitar, su parte del proxy y los colores heredados de tailwind.config.ts).
A100: P-49 | B100: Verificación y cierre | C100: Seguridad | D100: Revisar si conviene confiar en x-forwarded-for para el límite de intentos por IP | E100: ga-revisor-seguridad | F100: Media | G100: Hecho | H100: 6.2 | I100: =IFERROR(INDEX(Plan!$B$5:$B$129,MATCH(H100,Plan!$A$5:$A$129,0)),"—") | J100: Sugerido por ga-verificador-qa el 23-sep. Documentado por ga-funcionalidad-botones como O-01 en lib/servidor/limite.ts: x-forwarded-for/x-real-ip solo son confiables detrás de Vercel (nuestro caso); el límite real por cédula/IP lo hace la app, no Supabase.
A101: P-50 | B101: Verificación y cierre | C101: Correos | D101: Confirmar que salen los correos de afiliación (el log queda en la terminal de next dev) | E101: Yo | F101: Media | G101: Hecho | H101: — | I101: =IFERROR(INDEX(Plan!$B$5:$B$129,MATCH(H101,Plan!$A$5:$A$129,0)),"—") | J101: Ya no aplica: el 23-sep se quitaron los correos de afiliación del código (decisión de Sebas).
A102: P-62 | B102: Verificación y cierre | C102: Base de datos | D102: Borrar la cuenta admin de prueba «Test QA» (cédula 1099887766) desde el panel de Supabase | E102: Sebas | F102: Media | G102: Hecho | H102: 6.13 | I102: =IFERROR(INDEX(Plan!$B$5:$B$129,MATCH(H102,Plan!$A$5:$A$129,0)),"—") | J102: Ya hay 3 administradores reales en producción: Ricardo, Abogados Prieto y Sebas. 24-sep: usuario «Test QA» borrado de producción por Sebas.
A103: P-71 | B103: Verificación y cierre | C103: Pruebas | D103: Actualizar tests/e2e b-ingreso, i-despliegue y j-produccion al formato nuevo de máscara de correo | E103: Carlos Pardo | F103: Media | G103: Hecho | H103: 6.15 | I103: =IFERROR(INDEX(Plan!$B$5:$B$129,MATCH(H103,Plan!$A$5:$A$129,0)),"—") | J103: Encargo externo (500.000 COP) por PR a develop. Parte del alcance que P-58 dejó fuera. Ver P-73. 27-sep: ga-verificador-qa se adelantó al encargo de Carlos y actualizó b-ingreso y j-produccion al formato de máscara con dominio oculto; i-despliegue ya usaba el formato nuevo, no necesitó cambio. Los 3 archivos quedan al día. La actividad 6.15 sigue Pendiente en el plan porque depende de 6.1 (En curso), pero su alcance ya está cubierto.
A104: P-94 | B104: Verificación y cierre | C104: Pruebas | D104: Correr tests/e2e/b-ingreso.spec.ts y d-afiliacion.spec.ts contra la maquetación C+ de ingreso y afiliación, con Supabase local | E104: ga-verificador-qa o ga-escritor-tests | F104: Media | G104: Hecho | H104: 2.15 | I104: =IFERROR(INDEX(Plan!$B$5:$B$129,MATCH(H104,Plan!$A$5:$A$129,0)),"—") | J104: 25-sep: reportado por ga-diseno-a-codigo tras maquetar 2.15 en C+; no se corrieron porque requieren Supabase local. 27-sep: ga-verificador-qa corrió el QA completo contra Supabase local (161/162 escritorio, 129/129 celular) y actualizó f-accesibilidad/utils.ts a la afiliación v2; queda cerrado.
A105: P-102 | B105: Verificación y cierre | C105: Landing | D105: B-01: sección de testimonios de la landing con corchetes de ejemplo visibles ([Nombre], [Testimonio]...) | E105: sesión principal | F105: Baja | G105: Hecho | H105: 2.14 | I105: =IFERROR(INDEX(Plan!$B$5:$B$129,MATCH(H105,Plan!$A$5:$A$129,0)),"—") | J105: 27-sep: hallazgo Bajo de ga-verificador-qa. Corregido en rediseno-c-plus (commit local fdab456): la sección se oculta mientras tenga textos de ejemplo. Falta el contenido real y decidir si se mantiene la sección, ver P-103.
A106: P-52 | B106: Verificación y cierre | C106: Documentación | D106: Mapa de botones: §4 «Nueva solicitud» → /cuenta/solicitar y sección para la ruta /cuenta/solicitar | E106: ga-funcionalidad-botones | F106: Baja | G106: Hecho | H106: 3.7 | I106: =IFERROR(INDEX(Plan!$B$5:$B$129,MATCH(H106,Plan!$A$5:$A$129,0)),"—") | J106: Reportado por ga-diseno-a-codigo. Verificado el 23-sep: docs/mapa-de-botones.md ya tiene §4 «Nueva solicitud» → /cuenta/solicitar (Definido) y §4b /cuenta/solicitar; /dashboard se eliminó.
... A111: P-02 | B111: Decisión | C111: /cuenta | D111: Preguntar a la cooperativa si los convenios tendrán página propia | E111: Cooperativa | F111: Baja | G111: Pendiente | H111: 5.1 | I111: =IFERROR(INDEX(Plan!$B$5:$B$129,MATCH(H111,Plan!$A$5:$A$129,0)),"—") | J111: Por ahora son una sección en /cuenta (#convenios).
A112: P-107 | B112: Decisión | C112: /afiliacion/enviada | D112: Confirmar si «4 horas» de /afiliacion/enviada también cambia | E112: Sebas | F112: Baja | G112: Pendiente | H112: 6.22 | I112: =IFERROR(INDEX(Plan!$B$5:$B$129,MATCH(H112,Plan!$A$5:$A$129,0)),"—")
A113: P-09 | B113: Decisión | C113: Base de datos | D113: Revisar y aplicar en producción la migración blindar_solicitudes_y_revisiones | E113: Sebas (ga-auditor-supabase revisa antes) | F113: Alta | G113: Hecho | H113: 6.10 | I113: =IFERROR(INDEX(Plan!$B$5:$B$129,MATCH(H113,Plan!$A$5:$A$129,0)),"—") | J113: Verificado con list_migrations el 23-sep: producción ya tiene 20260923173355_blindar_solicitudes_y_revisiones.
A114: P-08 | B114: Decisión | C114: /cuenta | D114: P-10: el asociado no cambia su nombre pero sí su teléfono | E114: Yo | F114: Media | G114: Hecho | H114: 3.6 | I114: =IFERROR(INDEX(Plan!$B$5:$B$129,MATCH(H114,Plan!$A$5:$A$129,0)),"—") | J114: Apartado «Mis datos» ya maquetado.
A115: P-100 | B115: Decisión | C115: Seguridad | D115: Migración de permisos por columna para que un asociado no pueda leer la tasa de interés consultando la API directo con su sesión | E115: Sebas | F115: Media | G115: Hecho | H115: 3.5 | I115: =IFERROR(INDEX(Plan!$B$5:$B$129,MATCH(H115,Plan!$A$5:$A$129,0)),"—") | J115: 27-sep: residuo tras corregir P-99. Aunque la tasa ya no llega al payload de /cuenta, la RLS actual le sigue permitiendo al asociado leer sus propias solicitudes y grados_credito por la API REST/PostgREST con su sesión, así que la tasa se puede seguir consultando ahí. Ocultarla del todo requiere una migración de permisos por columna (revoke/grant o vista); pendiente de que Sebas decida si vale la pena.
A116: P-106 | B116: Decisión | C116: Admin | D116: R-09: quién registra los pagos de comisión | E116: Sebas + Ricardo | F116: Media | G116: Hecho | H116: — | I116: =IFERROR(INDEX(Plan!$B$5:$B$129,MATCH(H116,Plan!$A$5:$A$129,0)),"—") | J116: R-10 y R-11 cerrados por Sebas (§12.14).
A117: P-111 | B117: Decisión | C117: /admin | D117: ¿«Inscritos al sorteo» entra al dashboard del admin? | E117: Cooperativa | F117: Media | G117: Hecho | H117: 4.7 | I117: =IFERROR(INDEX(Plan!$B$5:$B$129,MATCH(H117,Plan!$A$5:$A$129,0)),"—") | J117: 30-sep: reportado por ga-disenador-lienzo y ga-diseno-a-codigo.
A118: P-119 | B118: Decisión | C118: Admin | D118: Preguntas sobre el rol secretario (¿ve Asociados/Créditos en solo lectura?) | E118: Cooperativa | F118: Media | G118: Hecho | H118: 4.20 | I118: =IFERROR(INDEX(Plan!$B$5:$B$129,MATCH(H118,Plan!$A$5:$A$129,0)),"—")
A119: P-120 | B119: Decisión | C119: Admin | D119: ¿Se borran los comprobantes de desembolso al eliminar definitivamente a un asociado? | E119: Cooperativa | F119: Media | G119: Hecho | H119: 4.19 | I119: =IFERROR(INDEX(Plan!$B$5:$B$129,MATCH(H119,Plan!$A$5:$A$129,0)),"—")
A120: P-122 | B120: Decisión | C120: /cuenta | D120: Moderación de las fotos que sube el asociado al carné | E120: Cooperativa | F120: Media | G120: Hecho | H120: 5.15 | I120: =IFERROR(INDEX(Plan!$B$5:$B$129,MATCH(H120,Plan!$A$5:$A$129,0)),"—")
A121: P-65 | B121: Decisión | C121: Sorteo | D121: Decidir si un admin o un asesor pueden participar en el sorteo mensual | E121: Cooperativa | F121: Media | G121: Hecho | H121: 3.9 | I121: =IFERROR(INDEX(Plan!$B$5:$B$129,MATCH(H121,Plan!$A$5:$A$129,0)),"—") | J121: Sugerido por ga-revisor-seguridad el 24-sep. 24-sep: decidido que solo participan asociados (S-13, ya implementado en participarSorteo).
A122: P-95 | B122: Decisión | C122: Admin | D122: Botón «Escribir por WhatsApp» en el detalle de afiliación del admin | E122: Cooperativa | F122: Media | G122: Hecho | H122: 4.11 | I122: =IFERROR(INDEX(Plan!$B$5:$B$129,MATCH(H122,Plan!$A$5:$A$129,0)),"—") | J122: 25-sep: propuesto por el diseño (pieza 3e del lienzo, detalle de afiliación); es funcionalidad nueva, no existía antes. El resto de las piezas 3d–3h usa componentes/rutas que ya existen. 27-sep: Sebas aprobó la funcionalidad; diseñada (D-08) y maquetada en código (enlace wa.me con mensaje prellenado).
A123: P-96 | B123: Decisión | C123: Admin | D123: Asignar/desactivar el asesor de un asociado (proceso sin definir) | E123: Cooperativa | F123: Media | G123: Hecho | H123: 4.11 | I123: =IFERROR(INDEX(Plan!$B$5:$B$129,MATCH(H123,Plan!$A$5:$A$129,0)),"—") | J123: 25-sep: ga-disenador-lienzo no puede diseñar esta pantalla porque no hay backend ni proceso definido para asignar o desactivar el asesor de un asociado. 27-sep: Sebas aprobó únicamente asignar asesor, y solo cuando la afiliación está aprobada y el asociado todavía no tiene asesor; sin cambiar ni quitar un asesor ya asignado por ahora. Diseñada (D-09, bloque «Asesor» 3i), con Server Action asignarAsesor y bloque conectado en código; estado «ya asignado» persistente al recargar agregado por la sesión principal (commit 3b5ae14).
A124: P-97 | B124: Decisión | C124: Admin | D124: Motivo de rechazo visible en el detalle de afiliación (requiere migración) | E124: Cooperativa | F124: Media | G124: Hecho | H124: 4.11 | I124: =IFERROR(INDEX(Plan!$B$5:$B$129,MATCH(H124,Plan!$A$5:$A$129,0)),"—") | J124: 25-sep: identificado en el detalle de afiliación del lienzo (pieza 3e). Relacionado con P-69/5.10 (Carlos Pardo ya tiene encargada la columna motivo_rechazo y el borrado automático de fotos); se deja anotado aparte para que la cooperativa confirme el texto/proceso del motivo que verá el admin.
A125: P-01 | B125: Decisión | C125: General | D125: Color de error #B3261E | E125: Yo | F125: Baja | G125: Hecho | H125: — | I125: =IFERROR(INDEX(Plan!$B$5:$B$129,MATCH(H125,Plan!$A$5:$A$129,0)),"—") | J125: Se deja.
A126: P-03 | B126: Decisión | C126: /cuenta | D126: Estado vacío de «Tu solicitud» | E126: Yo | F126: Baja | G126: Hecho | H126: 3.4 | I126: =IFERROR(INDEX(Plan!$B$5:$B$129,MATCH(H126,Plan!$A$5:$A$129,0)),"—") | J126: Ver con /cuenta?vacio=1.
A127: P-04 | B127: Decisión | C127: General | D127: Logo en celular como enlace a la landing | E127: Yo | F127: Baja | G127: Hecho | H127: — | I127: =IFERROR(INDEX(Plan!$B$5:$B$129,MATCH(H127,Plan!$A$5:$A$129,0)),"—")
A128: P-05 | B128: Decisión | C128: General | D128: Escudo: public/logos/vector/green-alliance-logo.svg | E128: Yo | F128: Baja | G128: Hecho | H128: — | I128: =IFERROR(INDEX(Plan!$B$5:$B$129,MATCH(H128,Plan!$A$5:$A$129,0)),"—")
A129: P-06 | B129: Decisión | C129: /ingresar | D129: Formulario de ingreso entre 640 y 767 px (columna de 440 px) | E129: Yo | F129: Baja | G129: Hecho | H129: 5.2 | I129: =IFERROR(INDEX(Plan!$B$5:$B$129,MATCH(H129,Plan!$A$5:$A$129,0)),"—")
A130: P-07 | B130: Decisión | C130: /ingresar | D130: Panel verde en tableta (640–1023 px) centrado | E130: Yo | F130: Baja | G130: Hecho | H130: 5.2 | I130: =IFERROR(INDEX(Plan!$B$5:$B$129,MATCH(H130,Plan!$A$5:$A$129,0)),"—")
A131: P-103 | B131: Decisión | C131: Landing | D131: D-07: ¿se mantiene la sección de testimonios de la landing? si sí, falta su diseño en la pieza 2a y de dónde salen los testimonios reales | E131: Cooperativa | F131: Baja | G131: Hecho | H131: 2.14 | I131: =IFERROR(INDEX(Plan!$B$5:$B$129,MATCH(H131,Plan!$A$5:$A$129,0)),"—") | J131: 27-sep: pedido de diseño nuevo de ga-verificador-qa (la sección no tiene respaldo en la pieza 2a del lienzo). Relacionado con P-16 (fotos/cifras/testimonios reales, 5.3). 27-sep: Sebas decidió quitar la sección de testimonios de la landing (commit 4c63924).
A132: P-115 | B132: Decisión | C132: /cuenta | D132: ¿El carné virtual lleva un código QR? | E132: Cooperativa | F132: Baja | G132: Hecho | H132: 5.12 | I132: =IFERROR(INDEX(Plan!$B$5:$B$129,MATCH(H132,Plan!$A$5:$A$129,0)),"—") | J132: 01-oct: planteado por ga-disenador-lienzo al maquetar 3u. 01-oct: el carné lleva QR con /verificar/[token] (5.14).
A133: P-121 | B133: Decisión | C133: /cuenta | D133: ¿El carné sin foto lleva una silueta? | E133: Cooperativa | F133: Baja | G133: Hecho | H133: 5.15 | I133: =IFERROR(INDEX(Plan!$B$5:$B$129,MATCH(H133,Plan!$A$5:$A$129,0)),"—")
A134: P-125 | B134: Decisión | C134: /verificar | D134: ¿El nombre completo del asociado puede verse públicamente en /verificar? | E134: Cooperativa | F134: Baja | G134: Hecho | H134: 5.14 | I134: =IFERROR(INDEX(Plan!$B$5:$B$129,MATCH(H134,Plan!$A$5:$A$129,0)),"—") | J134: 01-oct: planteado por ga-revisor-seguridad.
A135: P-53 | B135: Decisión | C135: Landing | D135: A 320 px la línea «COOPERATIVA» del logo mide ~5 px de alto (opcional: ocultarla o achicar «Ingresar» bajo 360 px) | E135: Yo | F135: Baja | G135: Hecho | H135: — | I135: =IFERROR(INDEX(Plan!$B$5:$B$129,MATCH(H135,Plan!$A$5:$A$129,0)),"—") | J135: Menor y opcional, reportado por ga-verificador-responsive el 23-sep. 01-oct: el logo horizontal oculta «COOPERATIVA» bajo 360 px.
A136: P-126 | B136: Seguridad | C136: Landing / convenios | D136: H-01: el WhatsApp de convenios llega al navegador en la landing y anon puede leer telefono_contacto de la API | E136: ga-funcionalidad-botones | F136: Alta | G136: Hecho | H136: 6.32 | I136: =IFERROR(INDEX(Plan!$B$5:$B$129,MATCH(H136,Plan!$A$5:$A$129,0)),"—") | J136: 08-oct: ga-revisor-seguridad. 09-oct: Hecho en código; falta aplicar la migración 20261009000000 (P-138) y desplegar (P-139).
A137: P-101 | B137: Seguridad | C137: Admin | D137: H2/M-01: cédula sin enmascarar de las «hermanas» en el detalle de afiliación viajaba completa a un client component | E137: sesión principal | F137: Media | G137: Hecho | H137: 4.11 | I137: =IFERROR(INDEX(Plan!$B$5:$B$129,MATCH(H137,Plan!$A$5:$A$129,0)),"—") | J137: 27-sep: hallazgo de ga-revisor-seguridad, confirmado por ga-verificador-qa el mismo día (se mostraba enmascarada en pantalla pero viajaba completa en las props de PanelAfiliacionDetalle / app/admin/afiliaciones/_datos.ts). Corregido en rediseno-c-plus (commit local fdab456): la cédula se enmascara en el servidor antes de llegar al client component.
...

Sheet Plan
A1: Plan optimizado — tabla de actividades
A2: Inicio, Listo y Fila los calcula el optimizador (2 filas, cola infinita). Si cambias pesos o dependencias, pide a ga-supervisor-avances que regenere el libro.
A4: ID | B4: Fase | C4: Actividad | D4: Peso (1–5) | E4: Duración (bloques) | F4: Depende de | G4: ¿Simultánea con otras? | H4: En paralelo con | I4: Fila | J4: Entra a la cola (bloque) | K4: Inicio (bloque) | L4: Fin (bloque) | M4: Espera en cola | N4: Semanas | O4: Estado | P4: Origen | Q4: Agente / responsable | R4: Bloqueo externo
A5: 1.1 | B5: 1. Diseño y arquitectura | C5: Diseño visual de las 6 pantallas (PC 1280 px y celular 390 px) | D5: 4 | E5: =D5 | F5: — | G5: Sí | H5: 1.3, 1.2 | I5: A | J5: 0 | K5: 0 | L5: =K5+E5 | M5: =K5-J5 | N5: ="S"&(INT(K5/Resumen!$C$5)+1)&"–S"&MAX(INT(K5/Resumen!$C$5)+1,ROUNDUP(L5/Resumen!$C$5,0)) | O5: Hecho | P5: Propuesta | Q5: —
A6: 1.2 | B6: 1. Diseño y arquitectura | C6: Modelo de datos en Supabase (perfiles, grados, solicitudes, convenios) | D6: 3 | E6: =D6 | F6: — | G6: Sí | H6: 1.1 | I6: B | J6: 0 | K6: 1 | L6: =K6+E6 | M6: =K6-J6 | N6: ="S"&(INT(K6/Resumen!$C$5)+1)&"–S"&MAX(INT(K6/Resumen!$C$5)+1,ROUNDUP(L6/Resumen!$C$5,0)) | O6: Hecho | P6: Propuesta | Q6: ga-auditor-supabase
A7: 1.3 | B7: 1. Diseño y arquitectura | C7: Stack y proyecto base (Next.js 16, Supabase, Resend) | D7: 1 | E7: =D7 | F7: — | G7: Sí | H7: 1.1 | I7: B | J7: 0 | K7: 0 | L7: =K7+E7 | M7: =K7-J7 | N7: ="S"&(INT(K7/Resumen!$C$5)+1)&"–S"&MAX(INT(K7/Resumen!$C$5)+1,ROUNDUP(L7/Resumen!$C$5,0)) | O7: Hecho | P7: Propuesta | Q7: —
A8: 1.4 | B8: 1. Diseño y arquitectura | C8: Tokens de diseño y componentes UI (Tailwind, globals.css) | D8: 2 | E8: =D8 | F8: 1.1, 1.3 | G8: Sí | H8: 2.4 | I8: A | J8: 4 | K8: 4 | L8: =K8+E8 | M8: =K8-J8 | N8: ="S"&(INT(K8/Resumen!$C$5)+1)&"–S"&MAX(INT(K8/Resumen!$C$5)+1,ROUNDUP(L8/Resumen!$C$5,0)) | O8: Hecho | P8: Propuesta | Q8: ga-diseno-a-codigo
A9: 1.5 | B9: 1. Diseño y arquitectura | C9: Modelo de datos fase 2: rol asesor, afiliación v2 (fotos), bucket privado de documentos y sorteo mensual (6 migraciones + seed) | D9: 5 | E9: =D9 | F9: 1.2 | G9: Sí | H9: 2.6, 1.7, 2.14 | I9: B | J9: 4 | K9: 13 | L9: =K9+E9 | M9: =K9-J9 | N9: ="S"&(INT(K9/Resumen!$C$5)+1)&"–S"&MAX(INT(K9/Resumen!$C$5)+1,ROUNDUP(L9/Resumen!$C$5,0)) | O9: Hecho | P9: Agregado | Q9: ga-auditor-supabase
A10: 1.6 | B10: 1. Diseño y arquitectura | C10: Auditoría de las migraciones de fase 2 y 3 migraciones correctivas de seguridad (boleta del sorteo oculta, asesor degradado, trigger de sincronía app_metadata) | D10: 3 | E10: =D10 | F10: 1.5 | G10: Sí | H10: 4.10, 2.17 | I10: B | J10: 18 | K10: 33 | L10: =K10+E10 | M10: =K10-J10 | N10: ="S"&(INT(K10/Resumen!$C$5)+1)&"–S"&MAX(INT(K10/Resumen!$C$5)+1,ROUNDUP(L10/Resumen!$C$5,0)) | O10: Hecho | P10: Agregado | Q10: ga-auditor-supabase
A11: 1.7 | B11: 1. Diseño y arquitectura | C11: Rediseño C+: design system y tokens (colores claro/oscuro, tipografía, radios, sombras, movimiento) en el lienzo y en globals.css/tailwind.config.ts | D11: 2 | E11: =D11 | F11: 1.4 | G11: Sí | H11: 1.5 | I11: A | J11: 6 | K11: 14 | L11: =K11+E11 | M11: =K11-J11 | N11: ="S"&(INT(K11/Resumen!$C$5)+1)&"–S"&MAX(INT(K11/Resumen!$C$5)+1,ROUNDUP(L11/Resumen!$C$5,0)) | O11: Hecho | P11: Agregado | Q11: ga-disenador-lienzo + ga-diseno-a-codigo
A12: 1.8 | B12: 1. Diseño y arquitectura | C12: Backend del rediseño C+: revisar y aplicar 5 migraciones propuestas (aviso del sorteo, institución/activo en perfiles, historial + nota interna del admin, Realtime de solicitudes, índices de búsqueda) | D12: 2 | E12: =D12 | F12: 1.6 | G12: Sí | H12: 6.17 | I12: A | J12: 36 | K12: 36 | L12: =K12+E12 | M12: =K12-J12 | N12: ="S"&(INT(K12/Resumen!$C$5)+1)&"–S"&MAX(INT(K12/Resumen!$C$5)+1,ROUNDUP(L12/Resumen!$C$5,0)) | O12: Hecho | P12: Agregado | Q12: Sebas (ga-auditor-supabase revisa antes)
A13: 2.1 | B13: 2. Landing y autenticación | C13: Maquetar la landing (misión, visión, servicios) | D13: 3 | E13: =D13 | F13: 1.4 | G13: Sí | H13: 2.2, 2.5 | I13: B | J13: 6 | K13: 6 | L13: =K13+E13 | M13: =K13-J13 | N13: ="S"&(INT(K13/Resumen!$C$5)+1)&"–S"&MAX(INT(K13/Resumen!$C$5)+1,ROUNDUP(L13/Resumen!$C$5,0)) | O13: Hecho | P13: Propuesta | Q13: ga-diseno-a-codigo
A14: 2.2 | B14: 2. Landing y autenticación | C14: Maquetar /ingresar y /ingresar/codigo | D14: 2 | E14: =D14 | F14: 1.4 | G14: Sí | H14: 2.1 | I14: A | J14: 6 | K14: 6 | L14: =K14+E14 | M14: =K14-J14 | N14: ="S"&(INT(K14/Resumen!$C$5)+1)&"–S"&MAX(INT(K14/Resumen!$C$5)+1,ROUNDUP(L14/Resumen!$C$5,0)) | O14: Hecho | P14: Propuesta | Q14: ga-diseno-a-codigo
A15: 2.3 | B15: 2. Landing y autenticación | C15: Maquetar /afiliacion y /afiliacion/enviada | D15: 2 | E15: =D15 | F15: 1.4 | G15: Sí | H15: 4.1 | I15: A | J15: 6 | K15: 20 | L15: =K15+E15 | M15: =K15-J15 | N15: ="S"&(INT(K15/Resumen!$C$5)+1)&"–S"&MAX(INT(K15/Resumen!$C$5)+1,ROUNDUP(L15/Resumen!$C$5,0)) | O15: Hecho | P15: Agregado | Q15: ga-diseno-a-codigo
A16: 2.4 | B16: 2. Landing y autenticación | C16: SMTP propio con Resend y plantilla del código OTP en Supabase | D16: 2 | E16: =D16 | F16: 1.3 | G16: Sí | H16: 1.4 | I16: B | J16: 1 | K16: 4 | L16: =K16+E16 | M16: =K16-J16 | N16: ="S"&(INT(K16/Resumen!$C$5)+1)&"–S"&MAX(INT(K16/Resumen!$C$5)+1,ROUNDUP(L16/Resumen!$C$5,0)) | O16: Hecho | P16: Agregado | Q16: Yo (panel Supabase)
... A39: 4.3 | B39: 4. Panel de administración | C39: Correo al asociado al resolver y estado actualizado en su pantalla | D39: 2 | E39: =D39 | F39: 4.2, 2.4 | G39: Sí | H39: 4.13, 2.12 | I39: B | J39: 49 | K39: 49 | L39: =K39+E39 | M39: =K39-J39 | N39: ="S"&(INT(K39/Resumen!$C$5)+1)&"–S"&MAX(INT(K39/Resumen!$C$5)+1,ROUNDUP(L39/Resumen!$C$5,0)) | O39: Hecho | P39: Propuesta | Q39: ga-funcionalidad-botones
A40: 4.4 | B40: 4. Panel de administración | C40: Importar asociados desde Excel (con correos reales) | D40: 4 | E40: =D40 | F40: 1.2 | G40: Sí | H40: 2.16, 6.3 | I40: B | J40: 4 | K40: 91 | L40: =K40+E40 | M40: =K40-J40 | N40: ="S"&(INT(K40/Resumen!$C$5)+1)&"–S"&MAX(INT(K40/Resumen!$C$5)+1,ROUNDUP(L40/Resumen!$C$5,0)) | O40: Hecho | P40: Agregado | Q40: ga-funcionalidad-botones | R40: Cancelada: decisión de la cooperativa 2026-09-24, no habrá importación de Excel de asociados.
A41: 4.5 | B41: 4. Panel de administración | C41: Aprobar afiliaciones en /admin: crear el usuario y enviar el correo «Ingreso aceptado» (Resend, ga-ingreso-aceptado) | D41: 3 | E41: =D41 | F41: 4.1, 2.9 | G41: Sí | H41: 2.12 | I41: B | J41: 43 | K41: 51 | L41: =K41+E41 | M41: =K41-J41 | N41: ="S"&(INT(K41/Resumen!$C$5)+1)&"–S"&MAX(INT(K41/Resumen!$C$5)+1,ROUNDUP(L41/Resumen!$C$5,0)) | O41: Hecho | P41: Agregado | Q41: ga-funcionalidad-botones
A42: 4.6 | B42: 4. Panel de administración | C42: Rol asesor: pantalla /asesor (mis clientes) y /asesor/demo (cuenta de demostración) | D42: 3 | E42: =D42 | F42: 1.5 | G42: Sí | H42: 3.10 | I42: B | J42: 18 | K42: 30 | L42: =K42+E42 | M42: =K42-J42 | N42: ="S"&(INT(K42/Resumen!$C$5)+1)&"–S"&MAX(INT(K42/Resumen!$C$5)+1,ROUNDUP(L42/Resumen!$C$5,0)) | O42: Hecho | P42: Agregado | Q42: ga-funcionalidad-botones
A43: 4.7 | B43: 4. Panel de administración | C43: Dashboard de clientes en /admin: métricas (asociados por grado/institución, afiliaciones y créditos pendientes, montos del mes, inscritos al sorteo), lista con buscador/filtros, detalle de cliente y reasignar asesor | D43: 4 | E43: =D43 | F43: 4.1, 4.6 | G43: Sí | H43: 4.17, 5.19 | I43: A | J43: 33 | K43: 85 | L43: =K43+E43 | M43: =K43-J43 | N43: ="S"&(INT(K43/Resumen!$C$5)+1)&"–S"&MAX(INT(K43/Resumen!$C$5)+1,ROUNDUP(L43/Resumen!$C$5,0)) | O43: Hecho | P43: Agregado | Q43: ga-funcionalidad-botones (antes Carlos Pardo)
A44: 4.8 | B44: 4. Panel de administración | C44: Dashboard del asesor en /asesor: métricas de sus clientes (por estado, créditos pendientes, afiliaciones referidas en el mes) y detalle de cliente sin celular, correo, Nequi ni fotos | D44: 3 | E44: =D44 | F44: 4.6 | G44: Sí | H44: 5.18, 6.28, 6.35 | I44: B | J44: 33 | K44: 117 | L44: =K44+E44 | M44: =K44-J44 | N44: ="S"&(INT(K44/Resumen!$C$5)+1)&"–S"&MAX(INT(K44/Resumen!$C$5)+1,ROUNDUP(L44/Resumen!$C$5,0)) | O44: Hecho | P44: Agregado | Q44: ga-funcionalidad-botones (antes Carlos Pardo)
A45: 4.9 | B45: 4. Panel de administración | C45: Cuenta de demostración para administradores en /admin/demo (pestaña «Demostración»): reutiliza la cuenta fantasma de /asesor/demo, un asesor no puede entrar | D45: 2 | E45: =D45 | F45: 4.1, 4.6 | G45: Sí | H45: 3.2 | I45: B | J45: 33 | K45: 128 | L45: =K45+E45 | M45: =K45-J45 | N45: ="S"&(INT(K45/Resumen!$C$5)+1)&"–S"&MAX(INT(K45/Resumen!$C$5)+1,ROUNDUP(L45/Resumen!$C$5,0)) | O45: Hecho | P45: Agregado | Q45: sesión principal
A46: 4.10 | B46: 4. Panel de administración | C46: Rediseño C+ del asesor (/asesor y /asesor/demo) | D46: 2 | E46: =D46 | F46: 4.6, 1.7 | G46: Sí | H46: 1.6 | I46: A | J46: 33 | K46: 33 | L46: =K46+E46 | M46: =K46-J46 | N46: ="S"&(INT(K46/Resumen!$C$5)+1)&"–S"&MAX(INT(K46/Resumen!$C$5)+1,ROUNDUP(L46/Resumen!$C$5,0)) | O46: Hecho | P46: Agregado | Q46: ga-disenador-lienzo + ga-diseno-a-codigo
A47: 4.11 | B47: 4. Panel de administración | C47: Rediseño C+ del admin (incluye la vista en celular) | D47: 3 | E47: =D47 | F47: 4.1, 1.7 | G47: Sí | H47: 2.15 | I47: A | J47: 24 | K47: 24 | L47: =K47+E47 | M47: =K47-J47 | N47: ="S"&(INT(K47/Resumen!$C$5)+1)&"–S"&MAX(INT(K47/Resumen!$C$5)+1,ROUNDUP(L47/Resumen!$C$5,0)) | O47: Hecho | P47: Agregado | Q47: ga-disenador-lienzo + ga-diseno-a-codigo
A48: 5.1 | B48: 5. Convenios y pulido | C48: Sección de convenios (en /cuenta y landing) | D48: 2 | E48: =D48 | F48: 3.4 | G48: Sí | H48: 4.20, 5.2 | I48: B | J48: 30 | K48: 63 | L48: =K48+E48 | M48: =K48-J48 | N48: ="S"&(INT(K48/Resumen!$C$5)+1)&"–S"&MAX(INT(K48/Resumen!$C$5)+1,ROUNDUP(L48/Resumen!$C$5,0)) | O48: Hecho | P48: Propuesta | Q48: ga-diseno-a-codigo
A49: 5.2 | B49: 5. Convenios y pulido | C49: Diseño responsive celular / tableta / PC | D49: 3 | E49: =D49 | F49: 2.1, 2.2, 2.3, 3.4 | G49: Sí | H49: 5.1, 3.6 | I49: A | J49: 30 | K49: 64 | L49: =K49+E49 | M49: =K49-J49 | N49: ="S"&(INT(K49/Resumen!$C$5)+1)&"–S"&MAX(INT(K49/Resumen!$C$5)+1,ROUNDUP(L49/Resumen!$C$5,0)) | O49: Hecho | P49: Propuesta | Q49: ga-verificador-responsive
A50: 5.3 | B50: 5. Convenios y pulido | C50: Cambiar datos de ejemplo por reales (config.ts, mock.ts, fotos, cifras) | D50: 2 | E50: =D50 | F50: 5.2 | G50: Sí | H50: 6.42 | I50: B | J50: 134 | K50: 139 | L50: =K50+E50 | M50: =K50-J50 | N50: ="S"&(INT(K50/Resumen!$C$5)+1)&"–S"&MAX(INT(K50/Resumen!$C$5)+1,ROUNDUP(L50/Resumen!$C$5,0)) | O50: Bloqueado | P50: Propuesta | Q50: ga-diseno-a-codigo | R50: Falta de la cooperativa: fotos, cifras, testimonios y fotos de las sedes.
A51: 5.4 | B51: 5. Convenios y pulido | C51: Página de política de datos (/politica-de-datos) | D51: 1 | E51: =D51 | F51: 5.2 | G51: Sí | H51: 5.5 | I51: A | J51: 67 | K51: 79 | L51: =K51+E51 | M51: =K51-J51 | N51: ="S"&(INT(K51/Resumen!$C$5)+1)&"–S"&MAX(INT(K51/Resumen!$C$5)+1,ROUNDUP(L51/Resumen!$C$5,0)) | O51: Hecho | P51: Agregado | Q51: ga-diseno-a-codigo
A52: 5.5 | B52: 5. Convenios y pulido | C52: Borrar las rutas viejas /login y /dashboard | D52: 1 | E52: =D52 | F52: 3.7, 2.7 | G52: Sí | H52: 5.4 | I52: B | J52: 62 | K52: 79 | L52: =K52+E52 | M52: =K52-J52 | N52: ="S"&(INT(K52/Resumen!$C$5)+1)&"–S"&MAX(INT(K52/Resumen!$C$5)+1,ROUNDUP(L52/Resumen!$C$5,0)) | O52: Hecho | P52: Agregado | Q52: ga-funcionalidad-botones
A53: 5.6 | B53: 5. Convenios y pulido | C53: Revisar el diseño de /cuenta/solicitar (pantalla sin maqueta; selector 50/100 ahora son radios) | D53: 1 | E53: =D53 | F53: 3.7 | G53: Sí | H53: 4.20 | I53: B | J53: 62 | K53: 62 | L53: =K53+E53 | M53: =K53-J53 | N53: ="S"&(INT(K53/Resumen!$C$5)+1)&"–S"&MAX(INT(K53/Resumen!$C$5)+1,ROUNDUP(L53/Resumen!$C$5,0)) | O53: Hecho | P53: Agregado | Q53: ga-diseno-a-codigo
A54: 5.7 | B54: 5. Convenios y pulido | C54: Logo horizontal con las letras oficiales (SVG) y espacios de foto de marca en la landing (EspacioFoto) | D54: 2 | E54: =D54 | F54: 2.1 | G54: Sí | H54: 6.33, 6.32 | I54: B | J54: 9 | K54: 98 | L54: =K54+E54 | M54: =K54-J54 | N54: ="S"&(INT(K54/Resumen!$C$5)+1)&"–S"&MAX(INT(K54/Resumen!$C$5)+1,ROUNDUP(L54/Resumen!$C$5,0)) | O54: Hecho | P54: Agregado | Q54: ga-diseno-a-codigo
A55: 5.8 | B55: 5. Convenios y pulido | C55: Corregir scroll horizontal: headers con logo (320 px) y formulario de /ingresar y /ingresar/codigo (1024–1075 px) | D55: 1 | E55: =D55 | F55: 5.2, 5.7 | G55: Sí | H55: 4.25 | I55: A | J55: 100 | K55: 103 | L55: =K55+E55 | M55: =K55-J55 | N55: ="S"&(INT(K55/Resumen!$C$5)+1)&"–S"&MAX(INT(K55/Resumen!$C$5)+1,ROUNDUP(L55/Resumen!$C$5,0)) | O55: Hecho | P55: Agregado | Q55: ga-diseno-a-codigo + ga-verificador-responsive
A56: 5.9 | B56: 5. Convenios y pulido | C56: Convenios administrables desde /admin (crear, editar, ocultar y ordenar, logo en Storage); landing y /cuenta leen de la tabla convenios | D56: 3 | E56: =D56 | F56: 4.1, 5.1 | G56: Sí | H56: 5.15 | I56: B | J56: 65 | K56: 80 | L56: =K56+E56 | M56: =K56-J56 | N56: ="S"&(INT(K56/Resumen!$C$5)+1)&"–S"&MAX(INT(K56/Resumen!$C$5)+1,ROUNDUP(L56/Resumen!$C$5,0)) | O56: Hecho | P56: Agregado | Q56: ga-funcionalidad-botones + ga-auditor-supabase
A57: 5.10 | B57: 5. Convenios y pulido | C57: Ley 1581: borrado automático de fotos de afiliaciones rechazadas tras X días (pg_cron o cron de Vercel) y motivo de rechazo en /admin (columna y campo) | D57: 2 | E57: =D57 | F57: 2.12, 4.1 | G57: Sí | H57: 4.21 | I57: B | J57: 54 | K57: 124 | L57: =K57+E57 | M57: =K57-J57 | N57: ="S"&(INT(K57/Resumen!$C$5)+1)&"–S"&MAX(INT(K57/Resumen!$C$5)+1,ROUNDUP(L57/Resumen!$C$5,0)) | O57: Hecho | P57: Agregado | Q57: ga-funcionalidad-botones + ga-auditor-supabase (antes Carlos Pardo)
A58: 6.1 | B58: 6. Pruebas y lanzamiento | C58: Pruebas de las nuevas Server Actions (login, afiliación, crédito, admin) | D58: 3 | E58: =D58 | F58: 2.10, 3.6, 4.3, 4.5 | G58: Sí | H58: 5.12, 4.23 | I58: B | J58: 67 | K58: 72 | L58: =K58+E58 | M58: =K58-J58 | N58: ="S"&(INT(K58/Resumen!$C$5)+1)&"–S"&MAX(INT(K58/Resumen!$C$5)+1,ROUNDUP(L58/Resumen!$C$5,0)) | O58: Hecho | P58: Propuesta | Q58: ga-escritor-tests
A59: 6.2 | B59: 6. Pruebas y lanzamiento | C59: Revisión de seguridad completa | D59: 2 | E59: =D59 | F59: 2.10, 3.6, 4.3, 4.5, 2.12, 3.9, 4.6 | G59: Sí | H59: 5.16, 6.15 | I59: A | J59: 71 | K59: 101 | L59: =K59+E59 | M59: =K59-J59 | N59: ="S"&(INT(K59/Resumen!$C$5)+1)&"–S"&MAX(INT(K59/Resumen!$C$5)+1,ROUNDUP(L59/Resumen!$C$5,0)) | O59: Hecho | P59: Propuesta | Q59: ga-revisor-seguridad
A60: 6.3 | B60: 6. Pruebas y lanzamiento | C60: QA de punta a punta y verificación responsive | D60: 3 | E60: =D60 | F60: 6.1, 5.5, 2.8, 5.4, 2.11, 5.6, 1.6, 2.12, 3.9, 4.6 | G60: Sí | H60: 4.4, 6.26 | I60: A | J60: 85 | K60: 93 | L60: =K60+E60 | M60: =K60-J60 | N60: ="S"&(INT(K60/Resumen!$C$5)+1)&"–S"&MAX(INT(K60/Resumen!$C$5)+1,ROUNDUP(L60/Resumen!$C$5,0)) | O60: Hecho | P60: Propuesta | Q60: ga-verificador-qa + ga-verificador-responsive
A61: 6.4 | B61: 6. Pruebas y lanzamiento | C61: Registrar dominio (5 años) y protección de dominio | D61: 1 | E61: =D61 | F61: — | G61: Sí | H61: 3.4 | I61: A | J61: 0 | K61: 29 | L61: =K61+E61 | M61: =K61-J61 | N61: ="S"&(INT(K61/Resumen!$C$5)+1)&"–S"&MAX(INT(K61/Resumen!$C$5)+1,ROUNDUP(L61/Resumen!$C$5,0)) | O61: Hecho | P61: Propuesta | Q61: Yo + cooperativa
A62: 6.5 | B62: 6. Pruebas y lanzamiento | C62: Subir a GitHub y desplegar en Vercel (producción) | D62: 2 | E62: =D62 | F62: 6.2, 6.3, 6.4, 2.4, 6.8, 6.9, 6.10, 6.13 | G62: No (usa las 2 filas) | H62: — | I62: A+B | J62: 107 | K62: 111 | L62: =K62+E62 | M62: =K62-J62 | N62: ="S"&(INT(K62/Resumen!$C$5)+1)&"–S"&MAX(INT(K62/Resumen!$C$5)+1,ROUNDUP(L62/Resumen!$C$5,0)) | O62: Hecho | P62: Propuesta | Q62: Yo
... A129: 6.42 | B129: 6. Pruebas y lanzamiento | C129: Revisión de seguridad y QA de Editar datos del asociado, Afiliación sin repetidos, Pausa de cuenta, Avisos, botón de WhatsApp y selfie | D129: 3 | E129: =D129 | F129: 4.23, 2.16, 4.24, 4.25, 3.11, 2.17, 4.26, 4.27 | G129: Sí | H129: 5.3 | I129: A | J129: 138 | K129: 139 | L129: =K129+E129 | M129: =K129-J129 | N129: ="S"&(INT(K129/Resumen!$C$5)+1)&"–S"&MAX(INT(K129/Resumen!$C$5)+1,ROUNDUP(L129/Resumen!$C$5,0)) | O129: En curso | P129: Agregado | Q129: ga-revisor-seguridad
A131: Notas
A132: Peso (azul, fondo amarillo) = dato de entrada; 1 punto de peso = 1 bloque de tiempo (ver hoja Pesos).
A133: «Origen: Agregado» = actividad que no estaba en la propuesta del 31-ago (p. ej. ingreso con código, afiliación, importación).
A134: «En paralelo con» lista las tareas que comparten tiempo con esta en el plan optimizado.
A135: Espera en cola = bloques entre que la tarea queda lista y una fila la toma.

Sheet Gantt
A1: Diagrama de Gantt optimizado — 2 filas, cola infinita
A2: El número al inicio de cada barra es el peso (1–5). Verde = Fila A, azul = Fila B, morado = usa las 2 filas, gris verdoso = hecho, ámbar = bloqueado por la cooperativa. Columna roja = HOY.
H4: Semana 1 | R4: Semana 2 | AB4: Semana 3 | AL4: Semana 4 | AV4: Semana 5 | BF4: Semana 6 | BP4: Semana 7 | BZ4: Semana 8 | CJ4: Semana 9 | CT4: Semana 10 | DD4: Semana 11 | DN4: Semana 12 | DX4: Semana 13 | EH4: Semana 14 | ER4: Semana 15
A5: ID | B5: Actividad | C5: Peso | D5: Fila | E5: Inicio | F5: Fin | G5: Estado | H5: 1 | I5: 2 | J5: 3 | K5: 4 | L5: 5 | M5: 6 | N5: 7 | O5: 8 | P5: 9 | Q5: 10 | R5: 11 | S5: 12 | T5: 13 | U5: 14 | V5: 15 | W5: 16 | X5: 17 | Y5: 18 | Z5: 19 | AA5: 20 | AB5: 21 | AC5: 22 | AD5: 23 | AE5: 24 | AF5: 25 | AG5: 26 | AH5: 27 | AI5: 28 | AJ5: 29 | AK5: 30 | AL5: 31 | AM5: 32 | AN5: 33 | AO5: 34 | AP5: 35 | AQ5: 36 | AR5: 37 | AS5: 38 | AT5: 39 | AU5: 40 | AV5: 41 | AW5: 42 | AX5: 43 | AY5: 44 | AZ5: 45 | BA5: 46 | BB5: 47 | BC5: 48 | BD5: 49 | BE5: 50 | BF5: 51 | BG5: 52 | BH5: 53 | BI5: 54 | BJ5: 55 | BK5: 56 | BL5: 57 | BM5: 58 | BN5: 59 | BO5: 60 | BP5: 61 | BQ5: 62 | BR5: 63 | BS5: 64 | BT5: 65 | BU5: 66 | BV5: 67 | BW5: 68 | BX5: 69 | BY5: 70 | BZ5: 71 | CA5: 72 | CB5: 73 | CC5: 74 | CD5: 75 | CE5: 76 | CF5: 77 | CG5: 78 | CH5: 79 | CI5: 80 | CJ5: 81 | CK5: 82 | CL5: 83 | CM5: 84 | CN5: 85 | CO5: 86 | CP5: 87 | CQ5: 88 | CR5: 89 | CS5: 90 | CT5: 91 | CU5: 92 | CV5: 93 | CW5: 94 | CX5: 95 | CY5: 96 | CZ5: 97 | DA5: 98 | DB5: 99 | DC5: 100 | DD5: 101 | DE5: 102 | DF5: 103 | DG5: 104 | DH5: 105 | DI5: 106 | DJ5: 107 | DK5: 108 | DL5: 109 | DM5: 110 | DN5: 111 | DO5: 112 | DP5: 113 | DQ5: 114 | DR5: 115 | DS5: 116 | DT5: 117 | DU5: 118 | DV5: 119 | DW5: 120 | DX5: 121 | DY5: 122 | DZ5: 123 | EA5: 124 | EB5: 125 | EC5: 126 | ED5: 127 | EE5: 128 | EF5: 129 | EG5: 130 | EH5: 131 | EI5: 132 | EJ5: 133 | EK5: 134 | EL5: 135 | EM5: 136 | EN5: 137 | EO5: 138 | EP5: 139 | EQ5: 140 | ER5: 141 | ES5: 142 | ET5: 143 | EU5: 144 | EV5: 145 | EW5: 146 | EX5: 147 | EY5: 148 | EZ5: 149 | FA5: 150
A6: Fila A — tarea en curso | H6: =IF(SUMPRODUCT(((Plan!$I$5:$I$129="A")+(Plan!$I$5:$I$129="A+B"))*(Plan!$K$5:$K$129<H$5)*(Plan!$L$5:$L$129>=H$5))=0,"",INDEX(Plan!$A$5:$A$129,SUMPRODUCT(((Plan!$I$5:$I$129="A")+(Plan!$I$5:$I$129="A+B"))*(Plan!$K$5:$K$129<H$5)*(Plan!$L$5:$L$129>=H$5)*(ROW(Plan!$A$5:$A$129)-4)))) | I6: =IF(SUMPRODUCT(((Plan!$I$5:$I$129="A")+(Plan!$I$5:$I$129="A+B"))*(Plan!$K$5:$K$129<I$5)*(Plan!$L$5:$L$129>=I$5))=0,"",INDEX(Plan!$A$5:$A$129,SUMPRODUCT(((Plan!$I$5:$I$129="A")+(Plan!$I$5:$I$129="A+B"))*(Plan!$K$5:$K$129<I$5)*(Plan!$L$5:$L$129>=I$5)*(ROW(Plan!$A$5:$A$129)-4)))) | J6: =IF(SUMPRODUCT(((Plan!$I$5:$I$129="A")+(Plan!$I$5:$I$129="A+B"))*(Plan!$K$5:$K$129<J$5)*(Plan!$L$5:$L$129>=J$5))=0,"",INDEX(Plan!$A$5:$A$129,SUMPRODUCT(((Plan!$I$5:$I$129="A")+(Plan!$I$5:$I$129="A+B"))*(Plan!$K$5:$K$129<J$5)*(Plan!$L$5:$L$129>=J$5)*(ROW(Plan!$A$5:$A$129)-4)))) | K6: =IF(SUMPRODUCT(((Plan!$I$5:$I$129="A")+(Plan!$I$5:$I$129="A+B"))*(Plan!$K$5:$K$129<K$5)*(Plan!$L$5:$L$129>=K$5))=0,"",INDEX(Plan!$A$5:$A$129,SUMPRODUCT(((Plan!$I$5:$I$129="A")+(Plan!$I$5:$I$129="A+B"))*(Plan!$K$5:$K$129<K$5)*(Plan!$L$5:$L$129>=K$5)*(ROW(Plan!$A$5:$A$129)-4)))) | L6: =IF(SUMPRODUCT(((Plan!$I$5:$I$129="A")+(Plan!$I$5:$I$129="A+B"))*(Plan!$K$5:$K$129<L$5)*(Plan!$L$5:$L$129>=L$5))=0,"",INDEX(Plan!$A$5:$A$129,SUMPRODUCT(((Plan!$I$5:$I$129="A")+(Plan!$I$5:$I$129="A+B"))*(Plan!$K$5:$K$129<L$5)*(Plan!$L$5:$L$129>=L$5)*(ROW(Plan!$A$5:$A$129)-4)))) | M6: =IF(SUMPRODUCT(((Plan!$I$5:$I$129="A")+(Plan!$I$5:$I$129="A+B"))*(Plan!$K$5:$K$129<M$5)*(Plan!$L$5:$L$129>=M$5))=0,"",INDEX(Plan!$A$5:$A$129,SUMPRODUCT(((Plan!$I$5:$I$129="A")+(Plan!$I$5:$I$129="A+B"))*(Plan!$K$5:$K$129<M$5)*(Plan!$L$5:$L$129>=M$5)*(ROW(Plan!$A$5:$A$129)-4)))) | N6: =IF(SUMPRODUCT(((Plan!$I$5:$I$129="A")+(Plan!$I$5:$I$129="A+B"))*(Plan!$K$5:$K$129<N$5)*(Plan!$L$5:$L$129>=N$5))=0,"",INDEX(Plan!$A$5:$A$129,SUMPRODUCT(((Plan!$I$5:$I$129="A")+(Plan!$I$5:$I$129="A+B"))*(Plan!$K$5:$K$129<N$5)*(Plan!$L$5:$L$129>=N$5)*(ROW(Plan!$A$5:$A$129)-4)))) | O6: =IF(SUMPRODUCT(((Plan!$I$5:$I$129="A")+(Plan!$I$5:$I$129="A+B"))*(Plan!$K$5:$K$129<O$5)*(Plan!$L$5:$L$129>=O$5))=0,"",INDEX(Plan!$A$5:$A$129,SUMPRODUCT(((Plan!$I$5:$I$129="A")+(Plan!$I$5:$I$129="A+B"))*(Plan!$K$5:$K$129<O$5)*(Plan!$L$5:$L$129>=O$5)*(ROW(Plan!$A$5:$A$129)-4)))) | ... FA6: =IF(SUMPRODUCT(((Plan!$I$5:$I$129="A")+(Plan!$I$5:$I$129="A+B"))*(Plan!$K$5:$K$129<FA$5)*(Plan!$L$5:$L$129>=FA$5))=0,"",INDEX(Plan!$A$5:$A$129,SUMPRODUCT(((Plan!$I$5:$I$129="A")+(Plan!$I$5:$I$129="A+B"))*(Plan!$K$5:$K$129<FA$5)*(Plan!$L$5:$L$129>=FA$5)*(ROW(Plan!$A$5:$A$129)-4))))
A7: Fila B — tarea en curso | H7: =IF(SUMPRODUCT(((Plan!$I$5:$I$129="B")+(Plan!$I$5:$I$129="A+B"))*(Plan!$K$5:$K$129<H$5)*(Plan!$L$5:$L$129>=H$5))=0,"",INDEX(Plan!$A$5:$A$129,SUMPRODUCT(((Plan!$I$5:$I$129="B")+(Plan!$I$5:$I$129="A+B"))*(Plan!$K$5:$K$129<H$5)*(Plan!$L$5:$L$129>=H$5)*(ROW(Plan!$A$5:$A$129)-4)))) | I7: =IF(SUMPRODUCT(((Plan!$I$5:$I$129="B")+(Plan!$I$5:$I$129="A+B"))*(Plan!$K$5:$K$129<I$5)*(Plan!$L$5:$L$129>=I$5))=0,"",INDEX(Plan!$A$5:$A$129,SUMPRODUCT(((Plan!$I$5:$I$129="B")+(Plan!$I$5:$I$129="A+B"))*(Plan!$K$5:$K$129<I$5)*(Plan!$L$5:$L$129>=I$5)*(ROW(Plan!$A$5:$A$129)-4)))) | J7: =IF(SUMPRODUCT(((Plan!$I$5:$I$129="B")+(Plan!$I$5:$I$129="A+B"))*(Plan!$K$5:$K$129<J$5)*(Plan!$L$5:$L$129>=J$5))=0,"",INDEX(Plan!$A$5:$A$129,SUMPRODUCT(((Plan!$I$5:$I$129="B")+(Plan!$I$5:$I$129="A+B"))*(Plan!$K$5:$K$129<J$5)*(Plan!$L$5:$L$129>=J$5)*(ROW(Plan!$A$5:$A$129)-4)))) | K7: =IF(SUMPRODUCT(((Plan!$I$5:$I$129="B")+(Plan!$I$5:$I$129="A+B"))*(Plan!$K$5:$K$129<K$5)*(Plan!$L$5:$L$129>=K$5))=0,"",INDEX(Plan!$A$5:$A$129,SUMPRODUCT(((Plan!$I$5:$I$129="B")+(Plan!$I$5:$I$129="A+B"))*(Plan!$K$5:$K$129<K$5)*(Plan!$L$5:$L$129>=K$5)*(ROW(Plan!$A$5:$A$129)-4)))) | L7: =IF(SUMPRODUCT(((Plan!$I$5:$I$129="B")+(Plan!$I$5:$I$129="A+B"))*(Plan!$K$5:$K$129<L$5)*(Plan!$L$5:$L$129>=L$5))=0,"",INDEX(Plan!$A$5:$A$129,SUMPRODUCT(((Plan!$I$5:$I$129="B")+(Plan!$I$5:$I$129="A+B"))*(Plan!$K$5:$K$129<L$5)*(Plan!$L$5:$L$129>=L$5)*(ROW(Plan!$A$5:$A$129)-4)))) | M7: =IF(SUMPRODUCT(((Plan!$I$5:$I$129="B")+(Plan!$I$5:$I$129="A+B"))*(Plan!$K$5:$K$129<M$5)*(Plan!$L$5:$L$129>=M$5))=0,"",INDEX(Plan!$A$5:$A$129,SUMPRODUCT(((Plan!$I$5:$I$129="B")+(Plan!$I$5:$I$129="A+B"))*(Plan!$K$5:$K$129<M$5)*(Plan!$L$5:$L$129>=M$5)*(ROW(Plan!$A$5:$A$129)-4)))) | N7: =IF(SUMPRODUCT(((Plan!$I$5:$I$129="B")+(Plan!$I$5:$I$129="A+B"))*(Plan!$K$5:$K$129<N$5)*(Plan!$L$5:$L$129>=N$5))=0,"",INDEX(Plan!$A$5:$A$129,SUMPRODUCT(((Plan!$I$5:$I$129="B")+(Plan!$I$5:$I$129="A+B"))*(Plan!$K$5:$K$129<N$5)*(Plan!$L$5:$L$129>=N$5)*(ROW(Plan!$A$5:$A$129)-4)))) | O7: =IF(SUMPRODUCT(((Plan!$I$5:$I$129="B")+(Plan!$I$5:$I$129="A+B"))*(Plan!$K$5:$K$129<O$5)*(Plan!$L$5:$L$129>=O$5))=0,"",INDEX(Plan!$A$5:$A$129,SUMPRODUCT(((Plan!$I$5:$I$129="B")+(Plan!$I$5:$I$129="A+B"))*(Plan!$K$5:$K$129<O$5)*(Plan!$L$5:$L$129>=O$5)*(ROW(Plan!$A$5:$A$129)-4)))) | ... FA7: =IF(SUMPRODUCT(((Plan!$I$5:$I$129="B")+(Plan!$I$5:$I$129="A+B"))*(Plan!$K$5:$K$129<FA$5)*(Plan!$L$5:$L$129>=FA$5))=0,"",INDEX(Plan!$A$5:$A$129,SUMPRODUCT(((Plan!$I$5:$I$129="B")+(Plan!$I$5:$I$129="A+B"))*(Plan!$K$5:$K$129<FA$5)*(Plan!$L$5:$L$129>=FA$5)*(ROW(Plan!$A$5:$A$129)-4))))
A9: Fase 1. Diseño y arquitectura | E9: =SUMPRODUCT(MIN((Plan!$B$5:$B$129="1. Diseño y arquitectura")*Plan!$K$5:$K$129+(Plan!$B$5:$B$129<>"1. Diseño y arquitectura")*1E9)) | F9: =SUMPRODUCT(MAX((Plan!$B$5:$B$129="1. Diseño y arquitectura")*Plan!$L$5:$L$129)) | G9: =Resumen!E29
A10: =Plan!A5 | B10: =Plan!C5 | C10: =Plan!D5 | D10: =Plan!I5 | E10: =Plan!K5 | F10: =Plan!L5 | G10: =Plan!O5 | H10: =IF(AND(H$5>$E10,H$5<=$F10),IF(H$5=$E10+1,$C10,""),"") | I10: =IF(AND(I$5>$E10,I$5<=$F10),IF(I$5=$E10+1,$C10,""),"") | J10: =IF(AND(J$5>$E10,J$5<=$F10),IF(J$5=$E10+1,$C10,""),"") | K10: =IF(AND(K$5>$E10,K$5<=$F10),IF(K$5=$E10+1,$C10,""),"") | L10: =IF(AND(L$5>$E10,L$5<=$F10),IF(L$5=$E10+1,$C10,""),"") | M10: =IF(AND(M$5>$E10,M$5<=$F10),IF(M$5=$E10+1,$C10,""),"") | N10: =IF(AND(N$5>$E10,N$5<=$F10),IF(N$5=$E10+1,$C10,""),"") | O10: =IF(AND(O$5>$E10,O$5<=$F10),IF(O$5=$E10+1,$C10,""),"") | ... FA10: =IF(AND(FA$5>$E10,FA$5<=$F10),IF(FA$5=$E10+1,$C10,""),"")
A11: =Plan!A6 | B11: =Plan!C6 | C11: =Plan!D6 | D11: =Plan!I6 | E11: =Plan!K6 | F11: =Plan!L6 | G11: =Plan!O6 | H11: =IF(AND(H$5>$E11,H$5<=$F11),IF(H$5=$E11+1,$C11,""),"") | I11: =IF(AND(I$5>$E11,I$5<=$F11),IF(I$5=$E11+1,$C11,""),"") | J11: =IF(AND(J$5>$E11,J$5<=$F11),IF(J$5=$E11+1,$C11,""),"") | K11: =IF(AND(K$5>$E11,K$5<=$F11),IF(K$5=$E11+1,$C11,""),"") | L11: =IF(AND(L$5>$E11,L$5<=$F11),IF(L$5=$E11+1,$C11,""),"") | M11: =IF(AND(M$5>$E11,M$5<=$F11),IF(M$5=$E11+1,$C11,""),"") | N11: =IF(AND(N$5>$E11,N$5<=$F11),IF(N$5=$E11+1,$C11,""),"") | O11: =IF(AND(O$5>$E11,O$5<=$F11),IF(O$5=$E11+1,$C11,""),"") | ... FA11: =IF(AND(FA$5>$E11,FA$5<=$F11),IF(FA$5=$E11+1,$C11,""),"")
A12: =Plan!A7 | B12: =Plan!C7 | C12: =Plan!D7 | D12: =Plan!I7 | E12: =Plan!K7 | F12: =Plan!L7 | G12: =Plan!O7 | H12: =IF(AND(H$5>$E12,H$5<=$F12),IF(H$5=$E12+1,$C12,""),"") | I12: =IF(AND(I$5>$E12,I$5<=$F12),IF(I$5=$E12+1,$C12,""),"") | J12: =IF(AND(J$5>$E12,J$5<=$F12),IF(J$5=$E12+1,$C12,""),"") | K12: =IF(AND(K$5>$E12,K$5<=$F12),IF(K$5=$E12+1,$C12,""),"") | L12: =IF(AND(L$5>$E12,L$5<=$F12),IF(L$5=$E12+1,$C12,""),"") | M12: =IF(AND(M$5>$E12,M$5<=$F12),IF(M$5=$E12+1,$C12,""),"") | N12: =IF(AND(N$5>$E12,N$5<=$F12),IF(N$5=$E12+1,$C12,""),"") | O12: =IF(AND(O$5>$E12,O$5<=$F12),IF(O$5=$E12+1,$C12,""),"") | ... FA12: =IF(AND(FA$5>$E12,FA$5<=$F12),IF(FA$5=$E12+1,$C12,""),"")
A13: =Plan!A8 | B13: =Plan!C8 | C13: =Plan!D8 | D13: =Plan!I8 | E13: =Plan!K8 | F13: =Plan!L8 | G13: =Plan!O8 | H13: =IF(AND(H$5>$E13,H$5<=$F13),IF(H$5=$E13+1,$C13,""),"") | I13: =IF(AND(I$5>$E13,I$5<=$F13),IF(I$5=$E13+1,$C13,""),"") | J13: =IF(AND(J$5>$E13,J$5<=$F13),IF(J$5=$E13+1,$C13,""),"") | K13: =IF(AND(K$5>$E13,K$5<=$F13),IF(K$5=$E13+1,$C13,""),"") | L13: =IF(AND(L$5>$E13,L$5<=$F13),IF(L$5=$E13+1,$C13,""),"") | M13: =IF(AND(M$5>$E13,M$5<=$F13),IF(M$5=$E13+1,$C13,""),"") | N13: =IF(AND(N$5>$E13,N$5<=$F13),IF(N$5=$E13+1,$C13,""),"") | O13: =IF(AND(O$5>$E13,O$5<=$F13),IF(O$5=$E13+1,$C13,""),"") | ... FA13: =IF(AND(FA$5>$E13,FA$5<=$F13),IF(FA$5=$E13+1,$C13,""),"")
A14: =Plan!A9 | B14: =Plan!C9 | C14: =Plan!D9 | D14: =Plan!I9 | E14: =Plan!K9 | F14: =Plan!L9 | G14: =Plan!O9 | H14: =IF(AND(H$5>$E14,H$5<=$F14),IF(H$5=$E14+1,$C14,""),"") | I14: =IF(AND(I$5>$E14,I$5<=$F14),IF(I$5=$E14+1,$C14,""),"") | J14: =IF(AND(J$5>$E14,J$5<=$F14),IF(J$5=$E14+1,$C14,""),"") | K14: =IF(AND(K$5>$E14,K$5<=$F14),IF(K$5=$E14+1,$C14,""),"") | L14: =IF(AND(L$5>$E14,L$5<=$F14),IF(L$5=$E14+1,$C14,""),"") | M14: =IF(AND(M$5>$E14,M$5<=$F14),IF(M$5=$E14+1,$C14,""),"") | N14: =IF(AND(N$5>$E14,N$5<=$F14),IF(N$5=$E14+1,$C14,""),"") | O14: =IF(AND(O$5>$E14,O$5<=$F14),IF(O$5=$E14+1,$C14,""),"") | ... FA14: =IF(AND(FA$5>$E14,FA$5<=$F14),IF(FA$5=$E14+1,$C14,""),"")
A15: =Plan!A10 | B15: =Plan!C10 | C15: =Plan!D10 | D15: =Plan!I10 | E15: =Plan!K10 | F15: =Plan!L10 | G15: =Plan!O10 | H15: =IF(AND(H$5>$E15,H$5<=$F15),IF(H$5=$E15+1,$C15,""),"") | I15: =IF(AND(I$5>$E15,I$5<=$F15),IF(I$5=$E15+1,$C15,""),"") | J15: =IF(AND(J$5>$E15,J$5<=$F15),IF(J$5=$E15+1,$C15,""),"") | K15: =IF(AND(K$5>$E15,K$5<=$F15),IF(K$5=$E15+1,$C15,""),"") | L15: =IF(AND(L$5>$E15,L$5<=$F15),IF(L$5=$E15+1,$C15,""),"") | M15: =IF(AND(M$5>$E15,M$5<=$F15),IF(M$5=$E15+1,$C15,""),"") | N15: =IF(AND(N$5>$E15,N$5<=$F15),IF(N$5=$E15+1,$C15,""),"") | O15: =IF(AND(O$5>$E15,O$5<=$F15),IF(O$5=$E15+1,$C15,""),"") | ... FA15: =IF(AND(FA$5>$E15,FA$5<=$F15),IF(FA$5=$E15+1,$C15,""),"")
A16: =Plan!A11 | B16: =Plan!C11 | C16: =Plan!D11 | D16: =Plan!I11 | E16: =Plan!K11 | F16: =Plan!L11 | G16: =Plan!O11 | H16: =IF(AND(H$5>$E16,H$5<=$F16),IF(H$5=$E16+1,$C16,""),"") | I16: =IF(AND(I$5>$E16,I$5<=$F16),IF(I$5=$E16+1,$C16,""),"") | J16: =IF(AND(J$5>$E16,J$5<=$F16),IF(J$5=$E16+1,$C16,""),"") | K16: =IF(AND(K$5>$E16,K$5<=$F16),IF(K$5=$E16+1,$C16,""),"") | L16: =IF(AND(L$5>$E16,L$5<=$F16),IF(L$5=$E16+1,$C16,""),"") | M16: =IF(AND(M$5>$E16,M$5<=$F16),IF(M$5=$E16+1,$C16,""),"") | N16: =IF(AND(N$5>$E16,N$5<=$F16),IF(N$5=$E16+1,$C16,""),"") | O16: =IF(AND(O$5>$E16,O$5<=$F16),IF(O$5=$E16+1,$C16,""),"") | ... FA16: =IF(AND(FA$5>$E16,FA$5<=$F16),IF(FA$5=$E16+1,$C16,""),"")
A17: =Plan!A12 | B17: =Plan!C12 | C17: =Plan!D12 | D17: =Plan!I12 | E17: =Plan!K12 | F17: =Plan!L12 | G17: =Plan!O12 | H17: =IF(AND(H$5>$E17,H$5<=$F17),IF(H$5=$E17+1,$C17,""),"") | I17: =IF(AND(I$5>$E17,I$5<=$F17),IF(I$5=$E17+1,$C17,""),"") | J17: =IF(AND(J$5>$E17,J$5<=$F17),IF(J$5=$E17+1,$C17,""),"") | K17: =IF(AND(K$5>$E17,K$5<=$F17),IF(K$5=$E17+1,$C17,""),"") | L17: =IF(AND(L$5>$E17,L$5<=$F17),IF(L$5=$E17+1,$C17,""),"") | M17: =IF(AND(M$5>$E17,M$5<=$F17),IF(M$5=$E17+1,$C17,""),"") | N17: =IF(AND(N$5>$E17,N$5<=$F17),IF(N$5=$E17+1,$C17,""),"") | O17: =IF(AND(O$5>$E17,O$5<=$F17),IF(O$5=$E17+1,$C17,""),"") | ... FA17: =IF(AND(FA$5>$E17,FA$5<=$F17),IF(FA$5=$E17+1,$C17,""),"")
A18: Fase 2. Landing y autenticación | E18: =SUMPRODUCT(MIN((Plan!$B$5:$B$129="2. Landing y autenticación")*Plan!$K$5:$K$129+(Plan!$B$5:$B$129<>"2. Landing y autenticación")*1E9)) | F18: =SUMPRODUCT(MAX((Plan!$B$5:$B$129="2. Landing y autenticación")*Plan!$L$5:$L$129)) | G18: =Resumen!E30
A19: =Plan!A13 | B19: =Plan!C13 | C19: =Plan!D13 | D19: =Plan!I13 | E19: =Plan!K13 | F19: =Plan!L13 | G19: =Plan!O13 | H19: =IF(AND(H$5>$E19,H$5<=$F19),IF(H$5=$E19+1,$C19,""),"") | I19: =IF(AND(I$5>$E19,I$5<=$F19),IF(I$5=$E19+1,$C19,""),"") | J19: =IF(AND(J$5>$E19,J$5<=$F19),IF(J$5=$E19+1,$C19,""),"") | K19: =IF(AND(K$5>$E19,K$5<=$F19),IF(K$5=$E19+1,$C19,""),"") | L19: =IF(AND(L$5>$E19,L$5<=$F19),IF(L$5=$E19+1,$C19,""),"") | M19: =IF(AND(M$5>$E19,M$5<=$F19),IF(M$5=$E19+1,$C19,""),"") | N19: =IF(AND(N$5>$E19,N$5<=$F19),IF(N$5=$E19+1,$C19,""),"") | O19: =IF(AND(O$5>$E19,O$5<=$F19),IF(O$5=$E19+1,$C19,""),"") | ... FA19: =IF(AND(FA$5>$E19,FA$5<=$F19),IF(FA$5=$E19+1,$C19,""),"")
A20: =Plan!A14 | B20: =Plan!C14 | C20: =Plan!D14 | D20: =Plan!I14 | E20: =Plan!K14 | F20: =Plan!L14 | G20: =Plan!O14 | H20: =IF(AND(H$5>$E20,H$5<=$F20),IF(H$5=$E20+1,$C20,""),"") | I20: =IF(AND(I$5>$E20,I$5<=$F20),IF(I$5=$E20+1,$C20,""),"") | J20: =IF(AND(J$5>$E20,J$5<=$F20),IF(J$5=$E20+1,$C20,""),"") | K20: =IF(AND(K$5>$E20,K$5<=$F20),IF(K$5=$E20+1,$C20,""),"") | L20: =IF(AND(L$5>$E20,L$5<=$F20),IF(L$5=$E20+1,$C20,""),"") | M20: =IF(AND(M$5>$E20,M$5<=$F20),IF(M$5=$E20+1,$C20,""),"") | N20: =IF(AND(N$5>$E20,N$5<=$F20),IF(N$5=$E20+1,$C20,""),"") | O20: =IF(AND(O$5>$E20,O$5<=$F20),IF(O$5=$E20+1,$C20,""),"") | ... FA20: =IF(AND(FA$5>$E20,FA$5<=$F20),IF(FA$5=$E20+1,$C20,""),"")
A21: =Plan!A15 | B21: =Plan!C15 | C21: =Plan!D15 | D21: =Plan!I15 | E21: =Plan!K15 | F21: =Plan!L15 | G21: =Plan!O15 | H21: =IF(AND(H$5>$E21,H$5<=$F21),IF(H$5=$E21+1,$C21,""),"") | I21: =IF(AND(I$5>$E21,I$5<=$F21),IF(I$5=$E21+1,$C21,""),"") | J21: =IF(AND(J$5>$E21,J$5<=$F21),IF(J$5=$E21+1,$C21,""),"") | K21: =IF(AND(K$5>$E21,K$5<=$F21),IF(K$5=$E21+1,$C21,""),"") | L21: =IF(AND(L$5>$E21,L$5<=$F21),IF(L$5=$E21+1,$C21,""),"") | M21: =IF(AND(M$5>$E21,M$5<=$F21),IF(M$5=$E21+1,$C21,""),"") | N21: =IF(AND(N$5>$E21,N$5<=$F21),IF(N$5=$E21+1,$C21,""),"") | O21: =IF(AND(O$5>$E21,O$5<=$F21),IF(O$5=$E21+1,$C21,""),"") | ... FA21: =IF(AND(FA$5>$E21,FA$5<=$F21),IF(FA$5=$E21+1,$C21,""),"")
A22: =Plan!A16 | B22: =Plan!C16 | C22: =Plan!D16 | D22: =Plan!I16 | E22: =Plan!K16 | F22: =Plan!L16 | G22: =Plan!O16 | H22: =IF(AND(H$5>$E22,H$5<=$F22),IF(H$5=$E22+1,$C22,""),"") | I22: =IF(AND(I$5>$E22,I$5<=$F22),IF(I$5=$E22+1,$C22,""),"") | J22: =IF(AND(J$5>$E22,J$5<=$F22),IF(J$5=$E22+1,$C22,""),"") | K22: =IF(AND(K$5>$E22,K$5<=$F22),IF(K$5=$E22+1,$C22,""),"") | L22: =IF(AND(L$5>$E22,L$5<=$F22),IF(L$5=$E22+1,$C22,""),"") | M22: =IF(AND(M$5>$E22,M$5<=$F22),IF(M$5=$E22+1,$C22,""),"") | N22: =IF(AND(N$5>$E22,N$5<=$F22),IF(N$5=$E22+1,$C22,""),"") | O22: =IF(AND(O$5>$E22,O$5<=$F22),IF(O$5=$E22+1,$C22,""),"") | ... FA22: =IF(AND(FA$5>$E22,FA$5<=$F22),IF(FA$5=$E22+1,$C22,""),"")
A23: =Plan!A17 | B23: =Plan!C17 | C23: =Plan!D17 | D23: =Plan!I17 | E23: =Plan!K17 | F23: =Plan!L17 | G23: =Plan!O17 | H23: =IF(AND(H$5>$E23,H$5<=$F23),IF(H$5=$E23+1,$C23,""),"") | I23: =IF(AND(I$5>$E23,I$5<=$F23),IF(I$5=$E23+1,$C23,""),"") | J23: =IF(AND(J$5>$E23,J$5<=$F23),IF(J$5=$E23+1,$C23,""),"") | K23: =IF(AND(K$5>$E23,K$5<=$F23),IF(K$5=$E23+1,$C23,""),"") | L23: =IF(AND(L$5>$E23,L$5<=$F23),IF(L$5=$E23+1,$C23,""),"") | M23: =IF(AND(M$5>$E23,M$5<=$F23),IF(M$5=$E23+1,$C23,""),"") | N23: =IF(AND(N$5>$E23,N$5<=$F23),IF(N$5=$E23+1,$C23,""),"") | O23: =IF(AND(O$5>$E23,O$5<=$F23),IF(O$5=$E23+1,$C23,""),"") | ... FA23: =IF(AND(FA$5>$E23,FA$5<=$F23),IF(FA$5=$E23+1,$C23,""),"")
A24: =Plan!A18 | B24: =Plan!C18 | C24: =Plan!D18 | D24: =Plan!I18 | E24: =Plan!K18 | F24: =Plan!L18 | G24: =Plan!O18 | H24: =IF(AND(H$5>$E24,H$5<=$F24),IF(H$5=$E24+1,$C24,""),"") | I24: =IF(AND(I$5>$E24,I$5<=$F24),IF(I$5=$E24+1,$C24,""),"") | J24: =IF(AND(J$5>$E24,J$5<=$F24),IF(J$5=$E24+1,$C24,""),"") | K24: =IF(AND(K$5>$E24,K$5<=$F24),IF(K$5=$E24+1,$C24,""),"") | L24: =IF(AND(L$5>$E24,L$5<=$F24),IF(L$5=$E24+1,$C24,""),"") | M24: =IF(AND(M$5>$E24,M$5<=$F24),IF(M$5=$E24+1,$C24,""),"") | N24: =IF(AND(N$5>$E24,N$5<=$F24),IF(N$5=$E24+1,$C24,""),"") | O24: =IF(AND(O$5>$E24,O$5<=$F24),IF(O$5=$E24+1,$C24,""),"") | ... FA24: =IF(AND(FA$5>$E24,FA$5<=$F24),IF(FA$5=$E24+1,$C24,""),"")
A25: =Plan!A19 | B25: =Plan!C19 | C25: =Plan!D19 | D25: =Plan!I19 | E25: =Plan!K19 | F25: =Plan!L19 | G25: =Plan!O19 | H25: =IF(AND(H$5>$E25,H$5<=$F25),IF(H$5=$E25+1,$C25,""),"") | I25: =IF(AND(I$5>$E25,I$5<=$F25),IF(I$5=$E25+1,$C25,""),"") | J25: =IF(AND(J$5>$E25,J$5<=$F25),IF(J$5=$E25+1,$C25,""),"") | K25: =IF(AND(K$5>$E25,K$5<=$F25),IF(K$5=$E25+1,$C25,""),"") | L25: =IF(AND(L$5>$E25,L$5<=$F25),IF(L$5=$E25+1,$C25,""),"") | M25: =IF(AND(M$5>$E25,M$5<=$F25),IF(M$5=$E25+1,$C25,""),"") | N25: =IF(AND(N$5>$E25,N$5<=$F25),IF(N$5=$E25+1,$C25,""),"") | O25: =IF(AND(O$5>$E25,O$5<=$F25),IF(O$5=$E25+1,$C25,""),"") | ... FA25: =IF(AND(FA$5>$E25,FA$5<=$F25),IF(FA$5=$E25+1,$C25,""),"")
A26: =Plan!A20 | B26: =Plan!C20 | C26: =Plan!D20 | D26: =Plan!I20 | E26: =Plan!K20 | F26: =Plan!L20 | G26: =Plan!O20 | H26: =IF(AND(H$5>$E26,H$5<=$F26),IF(H$5=$E26+1,$C26,""),"") | I26: =IF(AND(I$5>$E26,I$5<=$F26),IF(I$5=$E26+1,$C26,""),"") | J26: =IF(AND(J$5>$E26,J$5<=$F26),IF(J$5=$E26+1,$C26,""),"") | K26: =IF(AND(K$5>$E26,K$5<=$F26),IF(K$5=$E26+1,$C26,""),"") | L26: =IF(AND(L$5>$E26,L$5<=$F26),IF(L$5=$E26+1,$C26,""),"") | M26: =IF(AND(M$5>$E26,M$5<=$F26),IF(M$5=$E26+1,$C26,""),"") | N26: =IF(AND(N$5>$E26,N$5<=$F26),IF(N$5=$E26+1,$C26,""),"") | O26: =IF(AND(O$5>$E26,O$5<=$F26),IF(O$5=$E26+1,$C26,""),"") | ... FA26: =IF(AND(FA$5>$E26,FA$5<=$F26),IF(FA$5=$E26+1,$C26,""),"")
A27: =Plan!A21 | B27: =Plan!C21 | C27: =Plan!D21 | D27: =Plan!I21 | E27: =Plan!K21 | F27: =Plan!L21 | G27: =Plan!O21 | H27: =IF(AND(H$5>$E27,H$5<=$F27),IF(H$5=$E27+1,$C27,""),"") | I27: =IF(AND(I$5>$E27,I$5<=$F27),IF(I$5=$E27+1,$C27,""),"") | J27: =IF(AND(J$5>$E27,J$5<=$F27),IF(J$5=$E27+1,$C27,""),"") | K27: =IF(AND(K$5>$E27,K$5<=$F27),IF(K$5=$E27+1,$C27,""),"") | L27: =IF(AND(L$5>$E27,L$5<=$F27),IF(L$5=$E27+1,$C27,""),"") | M27: =IF(AND(M$5>$E27,M$5<=$F27),IF(M$5=$E27+1,$C27,""),"") | N27: =IF(AND(N$5>$E27,N$5<=$F27),IF(N$5=$E27+1,$C27,""),"") | O27: =IF(AND(O$5>$E27,O$5<=$F27),IF(O$5=$E27+1,$C27,""),"") | ... FA27: =IF(AND(FA$5>$E27,FA$5<=$F27),IF(FA$5=$E27+1,$C27,""),"")
A28: =Plan!A22 | B28: =Plan!C22 | C28: =Plan!D22 | D28: =Plan!I22 | E28: =Plan!K22 | F28: =Plan!L22 | G28: =Plan!O22 | H28: =IF(AND(H$5>$E28,H$5<=$F28),IF(H$5=$E28+1,$C28,""),"") | I28: =IF(AND(I$5>$E28,I$5<=$F28),IF(I$5=$E28+1,$C28,""),"") | J28: =IF(AND(J$5>$E28,J$5<=$F28),IF(J$5=$E28+1,$C28,""),"") | K28: =IF(AND(K$5>$E28,K$5<=$F28),IF(K$5=$E28+1,$C28,""),"") | L28: =IF(AND(L$5>$E28,L$5<=$F28),IF(L$5=$E28+1,$C28,""),"") | M28: =IF(AND(M$5>$E28,M$5<=$F28),IF(M$5=$E28+1,$C28,""),"") | N28: =IF(AND(N$5>$E28,N$5<=$F28),IF(N$5=$E28+1,$C28,""),"") | O28: =IF(AND(O$5>$E28,O$5<=$F28),IF(O$5=$E28+1,$C28,""),"") | ... FA28: =IF(AND(FA$5>$E28,FA$5<=$F28),IF(FA$5=$E28+1,$C28,""),"")
A29: =Plan!A23 | B29: =Plan!C23 | C29: =Plan!D23 | D29: =Plan!I23 | E29: =Plan!K23 | F29: =Plan!L23 | G29: =Plan!O23 | H29: =IF(AND(H$5>$E29,H$5<=$F29),IF(H$5=$E29+1,$C29,""),"") | I29: =IF(AND(I$5>$E29,I$5<=$F29),IF(I$5=$E29+1,$C29,""),"") | J29: =IF(AND(J$5>$E29,J$5<=$F29),IF(J$5=$E29+1,$C29,""),"") | K29: =IF(AND(K$5>$E29,K$5<=$F29),IF(K$5=$E29+1,$C29,""),"") | L29: =IF(AND(L$5>$E29,L$5<=$F29),IF(L$5=$E29+1,$C29,""),"") | M29: =IF(AND(M$5>$E29,M$5<=$F29),IF(M$5=$E29+1,$C29,""),"") | N29: =IF(AND(N$5>$E29,N$5<=$F29),IF(N$5=$E29+1,$C29,""),"") | O29: =IF(AND(O$5>$E29,O$5<=$F29),IF(O$5=$E29+1,$C29,""),"") | ... FA29: =IF(AND(FA$5>$E29,FA$5<=$F29),IF(FA$5=$E29+1,$C29,""),"")
A30: =Plan!A24 | B30: =Plan!C24 | C30: =Plan!D24 | D30: =Plan!I24 | E30: =Plan!K24 | F30: =Plan!L24 | G30: =Plan!O24 | H30: =IF(AND(H$5>$E30,H$5<=$F30),IF(H$5=$E30+1,$C30,""),"") | I30: =IF(AND(I$5>$E30,I$5<=$F30),IF(I$5=$E30+1,$C30,""),"") | J30: =IF(AND(J$5>$E30,J$5<=$F30),IF(J$5=$E30+1,$C30,""),"") | K30: =IF(AND(K$5>$E30,K$5<=$F30),IF(K$5=$E30+1,$C30,""),"") | L30: =IF(AND(L$5>$E30,L$5<=$F30),IF(L$5=$E30+1,$C30,""),"") | M30: =IF(AND(M$5>$E30,M$5<=$F30),IF(M$5=$E30+1,$C30,""),"") | N30: =IF(AND(N$5>$E30,N$5<=$F30),IF(N$5=$E30+1,$C30,""),"") | O30: =IF(AND(O$5>$E30,O$5<=$F30),IF(O$5=$E30+1,$C30,""),"") | ... FA30: =IF(AND(FA$5>$E30,FA$5<=$F30),IF(FA$5=$E30+1,$C30,""),"")
... A33: =Plan!A27 | B33: =Plan!C27 | C33: =Plan!D27 | D33: =Plan!I27 | E33: =Plan!K27 | F33: =Plan!L27 | G33: =Plan!O27 | H33: =IF(AND(H$5>$E33,H$5<=$F33),IF(H$5=$E33+1,$C33,""),"") | I33: =IF(AND(I$5>$E33,I$5<=$F33),IF(I$5=$E33+1,$C33,""),"") | J33: =IF(AND(J$5>$E33,J$5<=$F33),IF(J$5=$E33+1,$C33,""),"") | K33: =IF(AND(K$5>$E33,K$5<=$F33),IF(K$5=$E33+1,$C33,""),"") | L33: =IF(AND(L$5>$E33,L$5<=$F33),IF(L$5=$E33+1,$C33,""),"") | M33: =IF(AND(M$5>$E33,M$5<=$F33),IF(M$5=$E33+1,$C33,""),"") | N33: =IF(AND(N$5>$E33,N$5<=$F33),IF(N$5=$E33+1,$C33,""),"") | O33: =IF(AND(O$5>$E33,O$5<=$F33),IF(O$5=$E33+1,$C33,""),"") | ... FA33: =IF(AND(FA$5>$E33,FA$5<=$F33),IF(FA$5=$E33+1,$C33,""),"")
A34: =Plan!A119 | B34: =Plan!C119 | C34: =Plan!D119 | D34: =Plan!I119 | E34: =Plan!K119 | F34: =Plan!L119 | G34: =Plan!O119 | H34: =IF(AND(H$5>$E34,H$5<=$F34),IF(H$5=$E34+1,$C34,""),"") | I34: =IF(AND(I$5>$E34,I$5<=$F34),IF(I$5=$E34+1,$C34,""),"") | J34: =IF(AND(J$5>$E34,J$5<=$F34),IF(J$5=$E34+1,$C34,""),"") | K34: =IF(AND(K$5>$E34,K$5<=$F34),IF(K$5=$E34+1,$C34,""),"") | L34: =IF(AND(L$5>$E34,L$5<=$F34),IF(L$5=$E34+1,$C34,""),"") | M34: =IF(AND(M$5>$E34,M$5<=$F34),IF(M$5=$E34+1,$C34,""),"") | N34: =IF(AND(N$5>$E34,N$5<=$F34),IF(N$5=$E34+1,$C34,""),"") | O34: =IF(AND(O$5>$E34,O$5<=$F34),IF(O$5=$E34+1,$C34,""),"") | ... FA34: =IF(AND(FA$5>$E34,FA$5<=$F34),IF(FA$5=$E34+1,$C34,""),"")
A35: =Plan!A125 | B35: =Plan!C125 | C35: =Plan!D125 | D35: =Plan!I125 | E35: =Plan!K125 | F35: =Plan!L125 | G35: =Plan!O125 | H35: =IF(AND(H$5>$E35,H$5<=$F35),IF(H$5=$E35+1,$C35,""),"") | I35: =IF(AND(I$5>$E35,I$5<=$F35),IF(I$5=$E35+1,$C35,""),"") | J35: =IF(AND(J$5>$E35,J$5<=$F35),IF(J$5=$E35+1,$C35,""),"") | K35: =IF(AND(K$5>$E35,K$5<=$F35),IF(K$5=$E35+1,$C35,""),"") | L35: =IF(AND(L$5>$E35,L$5<=$F35),IF(L$5=$E35+1,$C35,""),"") | M35: =IF(AND(M$5>$E35,M$5<=$F35),IF(M$5=$E35+1,$C35,""),"") | N35: =IF(AND(N$5>$E35,N$5<=$F35),IF(N$5=$E35+1,$C35,""),"") | O35: =IF(AND(O$5>$E35,O$5<=$F35),IF(O$5=$E35+1,$C35,""),"") | ... FA35: =IF(AND(FA$5>$E35,FA$5<=$F35),IF(FA$5=$E35+1,$C35,""),"")
A36: Fase 3. Flujo de solicitud de crédito | E36: =SUMPRODUCT(MIN((Plan!$B$5:$B$129="3. Flujo de solicitud de crédito")*Plan!$K$5:$K$129+(Plan!$B$5:$B$129<>"3. Flujo de solicitud de crédito")*1E9)) | F36: =SUMPRODUCT(MAX((Plan!$B$5:$B$129="3. Flujo de solicitud de crédito")*Plan!$L$5:$L$129)) | G36: =Resumen!E31
A37: =Plan!A28 | B37: =Plan!C28 | C37: =Plan!D28 | D37: =Plan!I28 | E37: =Plan!K28 | F37: =Plan!L28 | G37: =Plan!O28 | H37: =IF(AND(H$5>$E37,H$5<=$F37),IF(H$5=$E37+1,$C37,""),"") | I37: =IF(AND(I$5>$E37,I$5<=$F37),IF(I$5=$E37+1,$C37,""),"") | J37: =IF(AND(J$5>$E37,J$5<=$F37),IF(J$5=$E37+1,$C37,""),"") | K37: =IF(AND(K$5>$E37,K$5<=$F37),IF(K$5=$E37+1,$C37,""),"") | L37: =IF(AND(L$5>$E37,L$5<=$F37),IF(L$5=$E37+1,$C37,""),"") | M37: =IF(AND(M$5>$E37,M$5<=$F37),IF(M$5=$E37+1,$C37,""),"") | N37: =IF(AND(N$5>$E37,N$5<=$F37),IF(N$5=$E37+1,$C37,""),"") | O37: =IF(AND(O$5>$E37,O$5<=$F37),IF(O$5=$E37+1,$C37,""),"") | ... FA37: =IF(AND(FA$5>$E37,FA$5<=$F37),IF(FA$5=$E37+1,$C37,""),"")
A38: =Plan!A29 | B38: =Plan!C29 | C38: =Plan!D29 | D38: =Plan!I29 | E38: =Plan!K29 | F38: =Plan!L29 | G38: =Plan!O29 | H38: =IF(AND(H$5>$E38,H$5<=$F38),IF(H$5=$E38+1,$C38,""),"") | I38: =IF(AND(I$5>$E38,I$5<=$F38),IF(I$5=$E38+1,$C38,""),"") | J38: =IF(AND(J$5>$E38,J$5<=$F38),IF(J$5=$E38+1,$C38,""),"") | K38: =IF(AND(K$5>$E38,K$5<=$F38),IF(K$5=$E38+1,$C38,""),"") | L38: =IF(AND(L$5>$E38,L$5<=$F38),IF(L$5=$E38+1,$C38,""),"") | M38: =IF(AND(M$5>$E38,M$5<=$F38),IF(M$5=$E38+1,$C38,""),"") | N38: =IF(AND(N$5>$E38,N$5<=$F38),IF(N$5=$E38+1,$C38,""),"") | O38: =IF(AND(O$5>$E38,O$5<=$F38),IF(O$5=$E38+1,$C38,""),"") | ... FA38: =IF(AND(FA$5>$E38,FA$5<=$F38),IF(FA$5=$E38+1,$C38,""),"")
A39: =Plan!A30 | B39: =Plan!C30 | C39: =Plan!D30 | D39: =Plan!I30 | E39: =Plan!K30 | F39: =Plan!L30 | G39: =Plan!O30 | H39: =IF(AND(H$5>$E39,H$5<=$F39),IF(H$5=$E39+1,$C39,""),"") | I39: =IF(AND(I$5>$E39,I$5<=$F39),IF(I$5=$E39+1,$C39,""),"") | J39: =IF(AND(J$5>$E39,J$5<=$F39),IF(J$5=$E39+1,$C39,""),"") | K39: =IF(AND(K$5>$E39,K$5<=$F39),IF(K$5=$E39+1,$C39,""),"") | L39: =IF(AND(L$5>$E39,L$5<=$F39),IF(L$5=$E39+1,$C39,""),"") | M39: =IF(AND(M$5>$E39,M$5<=$F39),IF(M$5=$E39+1,$C39,""),"") | N39: =IF(AND(N$5>$E39,N$5<=$F39),IF(N$5=$E39+1,$C39,""),"") | O39: =IF(AND(O$5>$E39,O$5<=$F39),IF(O$5=$E39+1,$C39,""),"") | ... FA39: =IF(AND(FA$5>$E39,FA$5<=$F39),IF(FA$5=$E39+1,$C39,""),"")
A40: =Plan!A31 | B40: =Plan!C31 | C40: =Plan!D31 | D40: =Plan!I31 | E40: =Plan!K31 | F40: =Plan!L31 | G40: =Plan!O31 | H40: =IF(AND(H$5>$E40,H$5<=$F40),IF(H$5=$E40+1,$C40,""),"") | I40: =IF(AND(I$5>$E40,I$5<=$F40),IF(I$5=$E40+1,$C40,""),"") | J40: =IF(AND(J$5>$E40,J$5<=$F40),IF(J$5=$E40+1,$C40,""),"") | K40: =IF(AND(K$5>$E40,K$5<=$F40),IF(K$5=$E40+1,$C40,""),"") | L40: =IF(AND(L$5>$E40,L$5<=$F40),IF(L$5=$E40+1,$C40,""),"") | M40: =IF(AND(M$5>$E40,M$5<=$F40),IF(M$5=$E40+1,$C40,""),"") | N40: =IF(AND(N$5>$E40,N$5<=$F40),IF(N$5=$E40+1,$C40,""),"") | O40: =IF(AND(O$5>$E40,O$5<=$F40),IF(O$5=$E40+1,$C40,""),"") | ... FA40: =IF(AND(FA$5>$E40,FA$5<=$F40),IF(FA$5=$E40+1,$C40,""),"")
A41: =Plan!A32 | B41: =Plan!C32 | C41: =Plan!D32 | D41: =Plan!I32 | E41: =Plan!K32 | F41: =Plan!L32 | G41: =Plan!O32 | H41: =IF(AND(H$5>$E41,H$5<=$F41),IF(H$5=$E41+1,$C41,""),"") | I41: =IF(AND(I$5>$E41,I$5<=$F41),IF(I$5=$E41+1,$C41,""),"") | J41: =IF(AND(J$5>$E41,J$5<=$F41),IF(J$5=$E41+1,$C41,""),"") | K41: =IF(AND(K$5>$E41,K$5<=$F41),IF(K$5=$E41+1,$C41,""),"") | L41: =IF(AND(L$5>$E41,L$5<=$F41),IF(L$5=$E41+1,$C41,""),"") | M41: =IF(AND(M$5>$E41,M$5<=$F41),IF(M$5=$E41+1,$C41,""),"") | N41: =IF(AND(N$5>$E41,N$5<=$F41),IF(N$5=$E41+1,$C41,""),"") | O41: =IF(AND(O$5>$E41,O$5<=$F41),IF(O$5=$E41+1,$C41,""),"") | ... FA41: =IF(AND(FA$5>$E41,FA$5<=$F41),IF(FA$5=$E41+1,$C41,""),"")
A42: =Plan!A33 | B42: =Plan!C33 | C42: =Plan!D33 | D42: =Plan!I33 | E42: =Plan!K33 | F42: =Plan!L33 | G42: =Plan!O33 | H42: =IF(AND(H$5>$E42,H$5<=$F42),IF(H$5=$E42+1,$C42,""),"") | I42: =IF(AND(I$5>$E42,I$5<=$F42),IF(I$5=$E42+1,$C42,""),"") | J42: =IF(AND(J$5>$E42,J$5<=$F42),IF(J$5=$E42+1,$C42,""),"") | K42: =IF(AND(K$5>$E42,K$5<=$F42),IF(K$5=$E42+1,$C42,""),"") | L42: =IF(AND(L$5>$E42,L$5<=$F42),IF(L$5=$E42+1,$C42,""),"") | M42: =IF(AND(M$5>$E42,M$5<=$F42),IF(M$5=$E42+1,$C42,""),"") | N42: =IF(AND(N$5>$E42,N$5<=$F42),IF(N$5=$E42+1,$C42,""),"") | O42: =IF(AND(O$5>$E42,O$5<=$F42),IF(O$5=$E42+1,$C42,""),"") | ... FA42: =IF(AND(FA$5>$E42,FA$5<=$F42),IF(FA$5=$E42+1,$C42,""),"")
A43: =Plan!A34 | B43: =Plan!C34 | C43: =Plan!D34 | D43: =Plan!I34 | E43: =Plan!K34 | F43: =Plan!L34 | G43: =Plan!O34 | H43: =IF(AND(H$5>$E43,H$5<=$F43),IF(H$5=$E43+1,$C43,""),"") | I43: =IF(AND(I$5>$E43,I$5<=$F43),IF(I$5=$E43+1,$C43,""),"") | J43: =IF(AND(J$5>$E43,J$5<=$F43),IF(J$5=$E43+1,$C43,""),"") | K43: =IF(AND(K$5>$E43,K$5<=$F43),IF(K$5=$E43+1,$C43,""),"") | L43: =IF(AND(L$5>$E43,L$5<=$F43),IF(L$5=$E43+1,$C43,""),"") | M43: =IF(AND(M$5>$E43,M$5<=$F43),IF(M$5=$E43+1,$C43,""),"") | N43: =IF(AND(N$5>$E43,N$5<=$F43),IF(N$5=$E43+1,$C43,""),"") | O43: =IF(AND(O$5>$E43,O$5<=$F43),IF(O$5=$E43+1,$C43,""),"") | ... FA43: =IF(AND(FA$5>$E43,FA$5<=$F43),IF(FA$5=$E43+1,$C43,""),"")
A44: =Plan!A35 | B44: =Plan!C35 | C44: =Plan!D35 | D44: =Plan!I35 | E44: =Plan!K35 | F44: =Plan!L35 | G44: =Plan!O35 | H44: =IF(AND(H$5>$E44,H$5<=$F44),IF(H$5=$E44+1,$C44,""),"") | I44: =IF(AND(I$5>$E44,I$5<=$F44),IF(I$5=$E44+1,$C44,""),"") | J44: =IF(AND(J$5>$E44,J$5<=$F44),IF(J$5=$E44+1,$C44,""),"") | K44: =IF(AND(K$5>$E44,K$5<=$F44),IF(K$5=$E44+1,$C44,""),"") | L44: =IF(AND(L$5>$E44,L$5<=$F44),IF(L$5=$E44+1,$C44,""),"") | M44: =IF(AND(M$5>$E44,M$5<=$F44),IF(M$5=$E44+1,$C44,""),"") | N44: =IF(AND(N$5>$E44,N$5<=$F44),IF(N$5=$E44+1,$C44,""),"") | O44: =IF(AND(O$5>$E44,O$5<=$F44),IF(O$5=$E44+1,$C44,""),"") | ... FA44: =IF(AND(FA$5>$E44,FA$5<=$F44),IF(FA$5=$E44+1,$C44,""),"")
A45: =Plan!A36 | B45: =Plan!C36 | C45: =Plan!D36 | D45: =Plan!I36 | E45: =Plan!K36 | F45: =Plan!L36 | G45: =Plan!O36 | H45: =IF(AND(H$5>$E45,H$5<=$F45),IF(H$5=$E45+1,$C45,""),"") | I45: =IF(AND(I$5>$E45,I$5<=$F45),IF(I$5=$E45+1,$C45,""),"") | J45: =IF(AND(J$5>$E45,J$5<=$F45),IF(J$5=$E45+1,$C45,""),"") | K45: =IF(AND(K$5>$E45,K$5<=$F45),IF(K$5=$E45+1,$C45,""),"") | L45: =IF(AND(L$5>$E45,L$5<=$F45),IF(L$5=$E45+1,$C45,""),"") | M45: =IF(AND(M$5>$E45,M$5<=$F45),IF(M$5=$E45+1,$C45,""),"") | N45: =IF(AND(N$5>$E45,N$5<=$F45),IF(N$5=$E45+1,$C45,""),"") | O45: =IF(AND(O$5>$E45,O$5<=$F45),IF(O$5=$E45+1,$C45,""),"") | ... FA45: =IF(AND(FA$5>$E45,FA$5<=$F45),IF(FA$5=$E45+1,$C45,""),"")
A46: =Plan!A124 | B46: =Plan!C124 | C46: =Plan!D124 | D46: =Plan!I124 | E46: =Plan!K124 | F46: =Plan!L124 | G46: =Plan!O124 | H46: =IF(AND(H$5>$E46,H$5<=$F46),IF(H$5=$E46+1,$C46,""),"") | I46: =IF(AND(I$5>$E46,I$5<=$F46),IF(I$5=$E46+1,$C46,""),"") | J46: =IF(AND(J$5>$E46,J$5<=$F46),IF(J$5=$E46+1,$C46,""),"") | K46: =IF(AND(K$5>$E46,K$5<=$F46),IF(K$5=$E46+1,$C46,""),"") | L46: =IF(AND(L$5>$E46,L$5<=$F46),IF(L$5=$E46+1,$C46,""),"") | M46: =IF(AND(M$5>$E46,M$5<=$F46),IF(M$5=$E46+1,$C46,""),"") | N46: =IF(AND(N$5>$E46,N$5<=$F46),IF(N$5=$E46+1,$C46,""),"") | O46: =IF(AND(O$5>$E46,O$5<=$F46),IF(O$5=$E46+1,$C46,""),"") | ... FA46: =IF(AND(FA$5>$E46,FA$5<=$F46),IF(FA$5=$E46+1,$C46,""),"")
A47: Fase 4. Panel de administración | E47: =SUMPRODUCT(MIN((Plan!$B$5:$B$129="4. Panel de administración")*Plan!$K$5:$K$129+(Plan!$B$5:$B$129<>"4. Panel de administración")*1E9)) | F47: =SUMPRODUCT(MAX((Plan!$B$5:$B$129="4. Panel de administración")*Plan!$L$5:$L$129)) | G47: =Resumen!E32
A48: =Plan!A37 | B48: =Plan!C37 | C48: =Plan!D37 | D48: =Plan!I37 | E48: =Plan!K37 | F48: =Plan!L37 | G48: =Plan!O37 | H48: =IF(AND(H$5>$E48,H$5<=$F48),IF(H$5=$E48+1,$C48,""),"") | I48: =IF(AND(I$5>$E48,I$5<=$F48),IF(I$5=$E48+1,$C48,""),"") | J48: =IF(AND(J$5>$E48,J$5<=$F48),IF(J$5=$E48+1,$C48,""),"") | K48: =IF(AND(K$5>$E48,K$5<=$F48),IF(K$5=$E48+1,$C48,""),"") | L48: =IF(AND(L$5>$E48,L$5<=$F48),IF(L$5=$E48+1,$C48,""),"") | M48: =IF(AND(M$5>$E48,M$5<=$F48),IF(M$5=$E48+1,$C48,""),"") | N48: =IF(AND(N$5>$E48,N$5<=$F48),IF(N$5=$E48+1,$C48,""),"") | O48: =IF(AND(O$5>$E48,O$5<=$F48),IF(O$5=$E48+1,$C48,""),"") | ... FA48: =IF(AND(FA$5>$E48,FA$5<=$F48),IF(FA$5=$E48+1,$C48,""),"")
A49: =Plan!A38 | B49: =Plan!C38 | C49: =Plan!D38 | D49: =Plan!I38 | E49: =Plan!K38 | F49: =Plan!L38 | G49: =Plan!O38 | H49: =IF(AND(H$5>$E49,H$5<=$F49),IF(H$5=$E49+1,$C49,""),"") | I49: =IF(AND(I$5>$E49,I$5<=$F49),IF(I$5=$E49+1,$C49,""),"") | J49: =IF(AND(J$5>$E49,J$5<=$F49),IF(J$5=$E49+1,$C49,""),"") | K49: =IF(AND(K$5>$E49,K$5<=$F49),IF(K$5=$E49+1,$C49,""),"") | L49: =IF(AND(L$5>$E49,L$5<=$F49),IF(L$5=$E49+1,$C49,""),"") | M49: =IF(AND(M$5>$E49,M$5<=$F49),IF(M$5=$E49+1,$C49,""),"") | N49: =IF(AND(N$5>$E49,N$5<=$F49),IF(N$5=$E49+1,$C49,""),"") | O49: =IF(AND(O$5>$E49,O$5<=$F49),IF(O$5=$E49+1,$C49,""),"") | ... FA49: =IF(AND(FA$5>$E49,FA$5<=$F49),IF(FA$5=$E49+1,$C49,""),"")
A50: =Plan!A39 | B50: =Plan!C39 | C50: =Plan!D39 | D50: =Plan!I39 | E50: =Plan!K39 | F50: =Plan!L39 | G50: =Plan!O39 | H50: =IF(AND(H$5>$E50,H$5<=$F50),IF(H$5=$E50+1,$C50,""),"") | I50: =IF(AND(I$5>$E50,I$5<=$F50),IF(I$5=$E50+1,$C50,""),"") | J50: =IF(AND(J$5>$E50,J$5<=$F50),IF(J$5=$E50+1,$C50,""),"") | K50: =IF(AND(K$5>$E50,K$5<=$F50),IF(K$5=$E50+1,$C50,""),"") | L50: =IF(AND(L$5>$E50,L$5<=$F50),IF(L$5=$E50+1,$C50,""),"") | M50: =IF(AND(M$5>$E50,M$5<=$F50),IF(M$5=$E50+1,$C50,""),"") | N50: =IF(AND(N$5>$E50,N$5<=$F50),IF(N$5=$E50+1,$C50,""),"") | O50: =IF(AND(O$5>$E50,O$5<=$F50),IF(O$5=$E50+1,$C50,""),"") | ... FA50: =IF(AND(FA$5>$E50,FA$5<=$F50),IF(FA$5=$E50+1,$C50,""),"")
A51: =Plan!A40 | B51: =Plan!C40 | C51: =Plan!D40 | D51: =Plan!I40 | E51: =Plan!K40 | F51: =Plan!L40 | G51: =Plan!O40 | H51: =IF(AND(H$5>$E51,H$5<=$F51),IF(H$5=$E51+1,$C51,""),"") | I51: =IF(AND(I$5>$E51,I$5<=$F51),IF(I$5=$E51+1,$C51,""),"") | J51: =IF(AND(J$5>$E51,J$5<=$F51),IF(J$5=$E51+1,$C51,""),"") | K51: =IF(AND(K$5>$E51,K$5<=$F51),IF(K$5=$E51+1,$C51,""),"") | L51: =IF(AND(L$5>$E51,L$5<=$F51),IF(L$5=$E51+1,$C51,""),"") | M51: =IF(AND(M$5>$E51,M$5<=$F51),IF(M$5=$E51+1,$C51,""),"") | N51: =IF(AND(N$5>$E51,N$5<=$F51),IF(N$5=$E51+1,$C51,""),"") | O51: =IF(AND(O$5>$E51,O$5<=$F51),IF(O$5=$E51+1,$C51,""),"") | ... FA51: =IF(AND(FA$5>$E51,FA$5<=$F51),IF(FA$5=$E51+1,$C51,""),"")
A52: =Plan!A41 | B52: =Plan!C41 | C52: =Plan!D41 | D52: =Plan!I41 | E52: =Plan!K41 | F52: =Plan!L41 | G52: =Plan!O41 | H52: =IF(AND(H$5>$E52,H$5<=$F52),IF(H$5=$E52+1,$C52,""),"") | I52: =IF(AND(I$5>$E52,I$5<=$F52),IF(I$5=$E52+1,$C52,""),"") | J52: =IF(AND(J$5>$E52,J$5<=$F52),IF(J$5=$E52+1,$C52,""),"") | K52: =IF(AND(K$5>$E52,K$5<=$F52),IF(K$5=$E52+1,$C52,""),"") | L52: =IF(AND(L$5>$E52,L$5<=$F52),IF(L$5=$E52+1,$C52,""),"") | M52: =IF(AND(M$5>$E52,M$5<=$F52),IF(M$5=$E52+1,$C52,""),"") | N52: =IF(AND(N$5>$E52,N$5<=$F52),IF(N$5=$E52+1,$C52,""),"") | O52: =IF(AND(O$5>$E52,O$5<=$F52),IF(O$5=$E52+1,$C52,""),"") | ... FA52: =IF(AND(FA$5>$E52,FA$5<=$F52),IF(FA$5=$E52+1,$C52,""),"")
A53: =Plan!A42 | B53: =Plan!C42 | C53: =Plan!D42 | D53: =Plan!I42 | E53: =Plan!K42 | F53: =Plan!L42 | G53: =Plan!O42 | H53: =IF(AND(H$5>$E53,H$5<=$F53),IF(H$5=$E53+1,$C53,""),"") | I53: =IF(AND(I$5>$E53,I$5<=$F53),IF(I$5=$E53+1,$C53,""),"") | J53: =IF(AND(J$5>$E53,J$5<=$F53),IF(J$5=$E53+1,$C53,""),"") | K53: =IF(AND(K$5>$E53,K$5<=$F53),IF(K$5=$E53+1,$C53,""),"") | L53: =IF(AND(L$5>$E53,L$5<=$F53),IF(L$5=$E53+1,$C53,""),"") | M53: =IF(AND(M$5>$E53,M$5<=$F53),IF(M$5=$E53+1,$C53,""),"") | N53: =IF(AND(N$5>$E53,N$5<=$F53),IF(N$5=$E53+1,$C53,""),"") | O53: =IF(AND(O$5>$E53,O$5<=$F53),IF(O$5=$E53+1,$C53,""),"") | ... FA53: =IF(AND(FA$5>$E53,FA$5<=$F53),IF(FA$5=$E53+1,$C53,""),"")
A54: =Plan!A43 | B54: =Plan!C43 | C54: =Plan!D43 | D54: =Plan!I43 | E54: =Plan!K43 | F54: =Plan!L43 | G54: =Plan!O43 | H54: =IF(AND(H$5>$E54,H$5<=$F54),IF(H$5=$E54+1,$C54,""),"") | I54: =IF(AND(I$5>$E54,I$5<=$F54),IF(I$5=$E54+1,$C54,""),"") | J54: =IF(AND(J$5>$E54,J$5<=$F54),IF(J$5=$E54+1,$C54,""),"") | K54: =IF(AND(K$5>$E54,K$5<=$F54),IF(K$5=$E54+1,$C54,""),"") | L54: =IF(AND(L$5>$E54,L$5<=$F54),IF(L$5=$E54+1,$C54,""),"") | M54: =IF(AND(M$5>$E54,M$5<=$F54),IF(M$5=$E54+1,$C54,""),"") | N54: =IF(AND(N$5>$E54,N$5<=$F54),IF(N$5=$E54+1,$C54,""),"") | O54: =IF(AND(O$5>$E54,O$5<=$F54),IF(O$5=$E54+1,$C54,""),"") | ... FA54: =IF(AND(FA$5>$E54,FA$5<=$F54),IF(FA$5=$E54+1,$C54,""),"")
A55: =Plan!A44 | B55: =Plan!C44 | C55: =Plan!D44 | D55: =Plan!I44 | E55: =Plan!K44 | F55: =Plan!L44 | G55: =Plan!O44 | H55: =IF(AND(H$5>$E55,H$5<=$F55),IF(H$5=$E55+1,$C55,""),"") | I55: =IF(AND(I$5>$E55,I$5<=$F55),IF(I$5=$E55+1,$C55,""),"") | J55: =IF(AND(J$5>$E55,J$5<=$F55),IF(J$5=$E55+1,$C55,""),"") | K55: =IF(AND(K$5>$E55,K$5<=$F55),IF(K$5=$E55+1,$C55,""),"") | L55: =IF(AND(L$5>$E55,L$5<=$F55),IF(L$5=$E55+1,$C55,""),"") | M55: =IF(AND(M$5>$E55,M$5<=$F55),IF(M$5=$E55+1,$C55,""),"") | N55: =IF(AND(N$5>$E55,N$5<=$F55),IF(N$5=$E55+1,$C55,""),"") | O55: =IF(AND(O$5>$E55,O$5<=$F55),IF(O$5=$E55+1,$C55,""),"") | ... FA55: =IF(AND(FA$5>$E55,FA$5<=$F55),IF(FA$5=$E55+1,$C55,""),"")
A56: =Plan!A45 | B56: =Plan!C45 | C56: =Plan!D45 | D56: =Plan!I45 | E56: =Plan!K45 | F56: =Plan!L45 | G56: =Plan!O45 | H56: =IF(AND(H$5>$E56,H$5<=$F56),IF(H$5=$E56+1,$C56,""),"") | I56: =IF(AND(I$5>$E56,I$5<=$F56),IF(I$5=$E56+1,$C56,""),"") | J56: =IF(AND(J$5>$E56,J$5<=$F56),IF(J$5=$E56+1,$C56,""),"") | K56: =IF(AND(K$5>$E56,K$5<=$F56),IF(K$5=$E56+1,$C56,""),"") | L56: =IF(AND(L$5>$E56,L$5<=$F56),IF(L$5=$E56+1,$C56,""),"") | M56: =IF(AND(M$5>$E56,M$5<=$F56),IF(M$5=$E56+1,$C56,""),"") | N56: =IF(AND(N$5>$E56,N$5<=$F56),IF(N$5=$E56+1,$C56,""),"") | O56: =IF(AND(O$5>$E56,O$5<=$F56),IF(O$5=$E56+1,$C56,""),"") | ... FA56: =IF(AND(FA$5>$E56,FA$5<=$F56),IF(FA$5=$E56+1,$C56,""),"")
A57: =Plan!A46 | B57: =Plan!C46 | C57: =Plan!D46 | D57: =Plan!I46 | E57: =Plan!K46 | F57: =Plan!L46 | G57: =Plan!O46 | H57: =IF(AND(H$5>$E57,H$5<=$F57),IF(H$5=$E57+1,$C57,""),"") | I57: =IF(AND(I$5>$E57,I$5<=$F57),IF(I$5=$E57+1,$C57,""),"") | J57: =IF(AND(J$5>$E57,J$5<=$F57),IF(J$5=$E57+1,$C57,""),"") | K57: =IF(AND(K$5>$E57,K$5<=$F57),IF(K$5=$E57+1,$C57,""),"") | L57: =IF(AND(L$5>$E57,L$5<=$F57),IF(L$5=$E57+1,$C57,""),"") | M57: =IF(AND(M$5>$E57,M$5<=$F57),IF(M$5=$E57+1,$C57,""),"") | N57: =IF(AND(N$5>$E57,N$5<=$F57),IF(N$5=$E57+1,$C57,""),"") | O57: =IF(AND(O$5>$E57,O$5<=$F57),IF(O$5=$E57+1,$C57,""),"") | ... FA57: =IF(AND(FA$5>$E57,FA$5<=$F57),IF(FA$5=$E57+1,$C57,""),"")
A58: =Plan!A47 | B58: =Plan!C47 | C58: =Plan!D47 | D58: =Plan!I47 | E58: =Plan!K47 | F58: =Plan!L47 | G58: =Plan!O47 | H58: =IF(AND(H$5>$E58,H$5<=$F58),IF(H$5=$E58+1,$C58,""),"") | I58: =IF(AND(I$5>$E58,I$5<=$F58),IF(I$5=$E58+1,$C58,""),"") | J58: =IF(AND(J$5>$E58,J$5<=$F58),IF(J$5=$E58+1,$C58,""),"") | K58: =IF(AND(K$5>$E58,K$5<=$F58),IF(K$5=$E58+1,$C58,""),"") | L58: =IF(AND(L$5>$E58,L$5<=$F58),IF(L$5=$E58+1,$C58,""),"") | M58: =IF(AND(M$5>$E58,M$5<=$F58),IF(M$5=$E58+1,$C58,""),"") | N58: =IF(AND(N$5>$E58,N$5<=$F58),IF(N$5=$E58+1,$C58,""),"") | O58: =IF(AND(O$5>$E58,O$5<=$F58),IF(O$5=$E58+1,$C58,""),"") | ... FA58: =IF(AND(FA$5>$E58,FA$5<=$F58),IF(FA$5=$E58+1,$C58,""),"")
A59: =Plan!A77 | B59: =Plan!C77 | C59: =Plan!D77 | D59: =Plan!I77 | E59: =Plan!K77 | F59: =Plan!L77 | G59: =Plan!O77 | H59: =IF(AND(H$5>$E59,H$5<=$F59),IF(H$5=$E59+1,$C59,""),"") | I59: =IF(AND(I$5>$E59,I$5<=$F59),IF(I$5=$E59+1,$C59,""),"") | J59: =IF(AND(J$5>$E59,J$5<=$F59),IF(J$5=$E59+1,$C59,""),"") | K59: =IF(AND(K$5>$E59,K$5<=$F59),IF(K$5=$E59+1,$C59,""),"") | L59: =IF(AND(L$5>$E59,L$5<=$F59),IF(L$5=$E59+1,$C59,""),"") | M59: =IF(AND(M$5>$E59,M$5<=$F59),IF(M$5=$E59+1,$C59,""),"") | N59: =IF(AND(N$5>$E59,N$5<=$F59),IF(N$5=$E59+1,$C59,""),"") | O59: =IF(AND(O$5>$E59,O$5<=$F59),IF(O$5=$E59+1,$C59,""),"") | ... FA59: =IF(AND(FA$5>$E59,FA$5<=$F59),IF(FA$5=$E59+1,$C59,""),"")
A60: =Plan!A78 | B60: =Plan!C78 | C60: =Plan!D78 | D60: =Plan!I78 | E60: =Plan!K78 | F60: =Plan!L78 | G60: =Plan!O78 | H60: =IF(AND(H$5>$E60,H$5<=$F60),IF(H$5=$E60+1,$C60,""),"") | I60: =IF(AND(I$5>$E60,I$5<=$F60),IF(I$5=$E60+1,$C60,""),"") | J60: =IF(AND(J$5>$E60,J$5<=$F60),IF(J$5=$E60+1,$C60,""),"") | K60: =IF(AND(K$5>$E60,K$5<=$F60),IF(K$5=$E60+1,$C60,""),"") | L60: =IF(AND(L$5>$E60,L$5<=$F60),IF(L$5=$E60+1,$C60,""),"") | M60: =IF(AND(M$5>$E60,M$5<=$F60),IF(M$5=$E60+1,$C60,""),"") | N60: =IF(AND(N$5>$E60,N$5<=$F60),IF(N$5=$E60+1,$C60,""),"") | O60: =IF(AND(O$5>$E60,O$5<=$F60),IF(O$5=$E60+1,$C60,""),"") | ... FA60: =IF(AND(FA$5>$E60,FA$5<=$F60),IF(FA$5=$E60+1,$C60,""),"")
A61: =Plan!A80 | B61: =Plan!C80 | C61: =Plan!D80 | D61: =Plan!I80 | E61: =Plan!K80 | F61: =Plan!L80 | G61: =Plan!O80 | H61: =IF(AND(H$5>$E61,H$5<=$F61),IF(H$5=$E61+1,$C61,""),"") | I61: =IF(AND(I$5>$E61,I$5<=$F61),IF(I$5=$E61+1,$C61,""),"") | J61: =IF(AND(J$5>$E61,J$5<=$F61),IF(J$5=$E61+1,$C61,""),"") | K61: =IF(AND(K$5>$E61,K$5<=$F61),IF(K$5=$E61+1,$C61,""),"") | L61: =IF(AND(L$5>$E61,L$5<=$F61),IF(L$5=$E61+1,$C61,""),"") | M61: =IF(AND(M$5>$E61,M$5<=$F61),IF(M$5=$E61+1,$C61,""),"") | N61: =IF(AND(N$5>$E61,N$5<=$F61),IF(N$5=$E61+1,$C61,""),"") | O61: =IF(AND(O$5>$E61,O$5<=$F61),IF(O$5=$E61+1,$C61,""),"") | ... FA61: =IF(AND(FA$5>$E61,FA$5<=$F61),IF(FA$5=$E61+1,$C61,""),"")
A62: =Plan!A81 | B62: =Plan!C81 | C62: =Plan!D81 | D62: =Plan!I81 | E62: =Plan!K81 | F62: =Plan!L81 | G62: =Plan!O81 | H62: =IF(AND(H$5>$E62,H$5<=$F62),IF(H$5=$E62+1,$C62,""),"") | I62: =IF(AND(I$5>$E62,I$5<=$F62),IF(I$5=$E62+1,$C62,""),"") | J62: =IF(AND(J$5>$E62,J$5<=$F62),IF(J$5=$E62+1,$C62,""),"") | K62: =IF(AND(K$5>$E62,K$5<=$F62),IF(K$5=$E62+1,$C62,""),"") | L62: =IF(AND(L$5>$E62,L$5<=$F62),IF(L$5=$E62+1,$C62,""),"") | M62: =IF(AND(M$5>$E62,M$5<=$F62),IF(M$5=$E62+1,$C62,""),"") | N62: =IF(AND(N$5>$E62,N$5<=$F62),IF(N$5=$E62+1,$C62,""),"") | O62: =IF(AND(O$5>$E62,O$5<=$F62),IF(O$5=$E62+1,$C62,""),"") | ... FA62: =IF(AND(FA$5>$E62,FA$5<=$F62),IF(FA$5=$E62+1,$C62,""),"")
A63: =Plan!A90 | B63: =Plan!C90 | C63: =Plan!D90 | D63: =Plan!I90 | E63: =Plan!K90 | F63: =Plan!L90 | G63: =Plan!O90 | H63: =IF(AND(H$5>$E63,H$5<=$F63),IF(H$5=$E63+1,$C63,""),"") | I63: =IF(AND(I$5>$E63,I$5<=$F63),IF(I$5=$E63+1,$C63,""),"") | J63: =IF(AND(J$5>$E63,J$5<=$F63),IF(J$5=$E63+1,$C63,""),"") | K63: =IF(AND(K$5>$E63,K$5<=$F63),IF(K$5=$E63+1,$C63,""),"") | L63: =IF(AND(L$5>$E63,L$5<=$F63),IF(L$5=$E63+1,$C63,""),"") | M63: =IF(AND(M$5>$E63,M$5<=$F63),IF(M$5=$E63+1,$C63,""),"") | N63: =IF(AND(N$5>$E63,N$5<=$F63),IF(N$5=$E63+1,$C63,""),"") | O63: =IF(AND(O$5>$E63,O$5<=$F63),IF(O$5=$E63+1,$C63,""),"") | ... FA63: =IF(AND(FA$5>$E63,FA$5<=$F63),IF(FA$5=$E63+1,$C63,""),"")
A64: =Plan!A92 | B64: =Plan!C92 | C64: =Plan!D92 | D64: =Plan!I92 | E64: =Plan!K92 | F64: =Plan!L92 | G64: =Plan!O92 | H64: =IF(AND(H$5>$E64,H$5<=$F64),IF(H$5=$E64+1,$C64,""),"") | I64: =IF(AND(I$5>$E64,I$5<=$F64),IF(I$5=$E64+1,$C64,""),"") | J64: =IF(AND(J$5>$E64,J$5<=$F64),IF(J$5=$E64+1,$C64,""),"") | K64: =IF(AND(K$5>$E64,K$5<=$F64),IF(K$5=$E64+1,$C64,""),"") | L64: =IF(AND(L$5>$E64,L$5<=$F64),IF(L$5=$E64+1,$C64,""),"") | M64: =IF(AND(M$5>$E64,M$5<=$F64),IF(M$5=$E64+1,$C64,""),"") | N64: =IF(AND(N$5>$E64,N$5<=$F64),IF(N$5=$E64+1,$C64,""),"") | O64: =IF(AND(O$5>$E64,O$5<=$F64),IF(O$5=$E64+1,$C64,""),"") | ... FA64: =IF(AND(FA$5>$E64,FA$5<=$F64),IF(FA$5=$E64+1,$C64,""),"")
A65: =Plan!A93 | B65: =Plan!C93 | C65: =Plan!D93 | D65: =Plan!I93 | E65: =Plan!K93 | F65: =Plan!L93 | G65: =Plan!O93 | H65: =IF(AND(H$5>$E65,H$5<=$F65),IF(H$5=$E65+1,$C65,""),"") | I65: =IF(AND(I$5>$E65,I$5<=$F65),IF(I$5=$E65+1,$C65,""),"") | J65: =IF(AND(J$5>$E65,J$5<=$F65),IF(J$5=$E65+1,$C65,""),"") | K65: =IF(AND(K$5>$E65,K$5<=$F65),IF(K$5=$E65+1,$C65,""),"") | L65: =IF(AND(L$5>$E65,L$5<=$F65),IF(L$5=$E65+1,$C65,""),"") | M65: =IF(AND(M$5>$E65,M$5<=$F65),IF(M$5=$E65+1,$C65,""),"") | N65: =IF(AND(N$5>$E65,N$5<=$F65),IF(N$5=$E65+1,$C65,""),"") | O65: =IF(AND(O$5>$E65,O$5<=$F65),IF(O$5=$E65+1,$C65,""),"") | ... FA65: =IF(AND(FA$5>$E65,FA$5<=$F65),IF(FA$5=$E65+1,$C65,""),"")
A66: =Plan!A94 | B66: =Plan!C94 | C66: =Plan!D94 | D66: =Plan!I94 | E66: =Plan!K94 | F66: =Plan!L94 | G66: =Plan!O94 | H66: =IF(AND(H$5>$E66,H$5<=$F66),IF(H$5=$E66+1,$C66,""),"") | I66: =IF(AND(I$5>$E66,I$5<=$F66),IF(I$5=$E66+1,$C66,""),"") | J66: =IF(AND(J$5>$E66,J$5<=$F66),IF(J$5=$E66+1,$C66,""),"") | K66: =IF(AND(K$5>$E66,K$5<=$F66),IF(K$5=$E66+1,$C66,""),"") | L66: =IF(AND(L$5>$E66,L$5<=$F66),IF(L$5=$E66+1,$C66,""),"") | M66: =IF(AND(M$5>$E66,M$5<=$F66),IF(M$5=$E66+1,$C66,""),"") | N66: =IF(AND(N$5>$E66,N$5<=$F66),IF(N$5=$E66+1,$C66,""),"") | O66: =IF(AND(O$5>$E66,O$5<=$F66),IF(O$5=$E66+1,$C66,""),"") | ... FA66: =IF(AND(FA$5>$E66,FA$5<=$F66),IF(FA$5=$E66+1,$C66,""),"")
A67: =Plan!A95 | B67: =Plan!C95 | C67: =Plan!D95 | D67: =Plan!I95 | E67: =Plan!K95 | F67: =Plan!L95 | G67: =Plan!O95 | H67: =IF(AND(H$5>$E67,H$5<=$F67),IF(H$5=$E67+1,$C67,""),"") | I67: =IF(AND(I$5>$E67,I$5<=$F67),IF(I$5=$E67+1,$C67,""),"") | J67: =IF(AND(J$5>$E67,J$5<=$F67),IF(J$5=$E67+1,$C67,""),"") | K67: =IF(AND(K$5>$E67,K$5<=$F67),IF(K$5=$E67+1,$C67,""),"") | L67: =IF(AND(L$5>$E67,L$5<=$F67),IF(L$5=$E67+1,$C67,""),"") | M67: =IF(AND(M$5>$E67,M$5<=$F67),IF(M$5=$E67+1,$C67,""),"") | N67: =IF(AND(N$5>$E67,N$5<=$F67),IF(N$5=$E67+1,$C67,""),"") | O67: =IF(AND(O$5>$E67,O$5<=$F67),IF(O$5=$E67+1,$C67,""),"") | ... FA67: =IF(AND(FA$5>$E67,FA$5<=$F67),IF(FA$5=$E67+1,$C67,""),"")
A68: =Plan!A103 | B68: =Plan!C103 | C68: =Plan!D103 | D68: =Plan!I103 | E68: =Plan!K103 | F68: =Plan!L103 | G68: =Plan!O103 | H68: =IF(AND(H$5>$E68,H$5<=$F68),IF(H$5=$E68+1,$C68,""),"") | I68: =IF(AND(I$5>$E68,I$5<=$F68),IF(I$5=$E68+1,$C68,""),"") | J68: =IF(AND(J$5>$E68,J$5<=$F68),IF(J$5=$E68+1,$C68,""),"") | K68: =IF(AND(K$5>$E68,K$5<=$F68),IF(K$5=$E68+1,$C68,""),"") | L68: =IF(AND(L$5>$E68,L$5<=$F68),IF(L$5=$E68+1,$C68,""),"") | M68: =IF(AND(M$5>$E68,M$5<=$F68),IF(M$5=$E68+1,$C68,""),"") | N68: =IF(AND(N$5>$E68,N$5<=$F68),IF(N$5=$E68+1,$C68,""),"") | O68: =IF(AND(O$5>$E68,O$5<=$F68),IF(O$5=$E68+1,$C68,""),"") | ... FA68: =IF(AND(FA$5>$E68,FA$5<=$F68),IF(FA$5=$E68+1,$C68,""),"")
A69: =Plan!A104 | B69: =Plan!C104 | C69: =Plan!D104 | D69: =Plan!I104 | E69: =Plan!K104 | F69: =Plan!L104 | G69: =Plan!O104 | H69: =IF(AND(H$5>$E69,H$5<=$F69),IF(H$5=$E69+1,$C69,""),"") | I69: =IF(AND(I$5>$E69,I$5<=$F69),IF(I$5=$E69+1,$C69,""),"") | J69: =IF(AND(J$5>$E69,J$5<=$F69),IF(J$5=$E69+1,$C69,""),"") | K69: =IF(AND(K$5>$E69,K$5<=$F69),IF(K$5=$E69+1,$C69,""),"") | L69: =IF(AND(L$5>$E69,L$5<=$F69),IF(L$5=$E69+1,$C69,""),"") | M69: =IF(AND(M$5>$E69,M$5<=$F69),IF(M$5=$E69+1,$C69,""),"") | N69: =IF(AND(N$5>$E69,N$5<=$F69),IF(N$5=$E69+1,$C69,""),"") | O69: =IF(AND(O$5>$E69,O$5<=$F69),IF(O$5=$E69+1,$C69,""),"") | ... FA69: =IF(AND(FA$5>$E69,FA$5<=$F69),IF(FA$5=$E69+1,$C69,""),"")
A70: =Plan!A118 | B70: =Plan!C118 | C70: =Plan!D118 | D70: =Plan!I118 | E70: =Plan!K118 | F70: =Plan!L118 | G70: =Plan!O118 | H70: =IF(AND(H$5>$E70,H$5<=$F70),IF(H$5=$E70+1,$C70,""),"") | I70: =IF(AND(I$5>$E70,I$5<=$F70),IF(I$5=$E70+1,$C70,""),"") | J70: =IF(AND(J$5>$E70,J$5<=$F70),IF(J$5=$E70+1,$C70,""),"") | K70: =IF(AND(K$5>$E70,K$5<=$F70),IF(K$5=$E70+1,$C70,""),"") | L70: =IF(AND(L$5>$E70,L$5<=$F70),IF(L$5=$E70+1,$C70,""),"") | M70: =IF(AND(M$5>$E70,M$5<=$F70),IF(M$5=$E70+1,$C70,""),"") | N70: =IF(AND(N$5>$E70,N$5<=$F70),IF(N$5=$E70+1,$C70,""),"") | O70: =IF(AND(O$5>$E70,O$5<=$F70),IF(O$5=$E70+1,$C70,""),"") | ... FA70: =IF(AND(FA$5>$E70,FA$5<=$F70),IF(FA$5=$E70+1,$C70,""),"")
A71: =Plan!A120 | B71: =Plan!C120 | C71: =Plan!D120 | D71: =Plan!I120 | E71: =Plan!K120 | F71: =Plan!L120 | G71: =Plan!O120 | H71: =IF(AND(H$5>$E71,H$5<=$F71),IF(H$5=$E71+1,$C71,""),"") | I71: =IF(AND(I$5>$E71,I$5<=$F71),IF(I$5=$E71+1,$C71,""),"") | J71: =IF(AND(J$5>$E71,J$5<=$F71),IF(J$5=$E71+1,$C71,""),"") | K71: =IF(AND(K$5>$E71,K$5<=$F71),IF(K$5=$E71+1,$C71,""),"") | L71: =IF(AND(L$5>$E71,L$5<=$F71),IF(L$5=$E71+1,$C71,""),"") | M71: =IF(AND(M$5>$E71,M$5<=$F71),IF(M$5=$E71+1,$C71,""),"") | N71: =IF(AND(N$5>$E71,N$5<=$F71),IF(N$5=$E71+1,$C71,""),"") | O71: =IF(AND(O$5>$E71,O$5<=$F71),IF(O$5=$E71+1,$C71,""),"") | ... FA71: =IF(AND(FA$5>$E71,FA$5<=$F71),IF(FA$5=$E71+1,$C71,""),"")
A72: =Plan!A121 | B72: =Plan!C121 | C72: =Plan!D121 | D72: =Plan!I121 | E72: =Plan!K121 | F72: =Plan!L121 | G72: =Plan!O121 | H72: =IF(AND(H$5>$E72,H$5<=$F72),IF(H$5=$E72+1,$C72,""),"") | I72: =IF(AND(I$5>$E72,I$5<=$F72),IF(I$5=$E72+1,$C72,""),"") | J72: =IF(AND(J$5>$E72,J$5<=$F72),IF(J$5=$E72+1,$C72,""),"") | K72: =IF(AND(K$5>$E72,K$5<=$F72),IF(K$5=$E72+1,$C72,""),"") | L72: =IF(AND(L$5>$E72,L$5<=$F72),IF(L$5=$E72+1,$C72,""),"") | M72: =IF(AND(M$5>$E72,M$5<=$F72),IF(M$5=$E72+1,$C72,""),"") | N72: =IF(AND(N$5>$E72,N$5<=$F72),IF(N$5=$E72+1,$C72,""),"") | O72: =IF(AND(O$5>$E72,O$5<=$F72),IF(O$5=$E72+1,$C72,""),"") | ... FA72: =IF(AND(FA$5>$E72,FA$5<=$F72),IF(FA$5=$E72+1,$C72,""),"")
A73: =Plan!A122 | B73: =Plan!C122 | C73: =Plan!D122 | D73: =Plan!I122 | E73: =Plan!K122 | F73: =Plan!L122 | G73: =Plan!O122 | H73: =IF(AND(H$5>$E73,H$5<=$F73),IF(H$5=$E73+1,$C73,""),"") | I73: =IF(AND(I$5>$E73,I$5<=$F73),IF(I$5=$E73+1,$C73,""),"") | J73: =IF(AND(J$5>$E73,J$5<=$F73),IF(J$5=$E73+1,$C73,""),"") | K73: =IF(AND(K$5>$E73,K$5<=$F73),IF(K$5=$E73+1,$C73,""),"") | L73: =IF(AND(L$5>$E73,L$5<=$F73),IF(L$5=$E73+1,$C73,""),"") | M73: =IF(AND(M$5>$E73,M$5<=$F73),IF(M$5=$E73+1,$C73,""),"") | N73: =IF(AND(N$5>$E73,N$5<=$F73),IF(N$5=$E73+1,$C73,""),"") | O73: =IF(AND(O$5>$E73,O$5<=$F73),IF(O$5=$E73+1,$C73,""),"") | ... FA73: =IF(AND(FA$5>$E73,FA$5<=$F73),IF(FA$5=$E73+1,$C73,""),"")
A74: =Plan!A123 | B74: =Plan!C123 | C74: =Plan!D123 | D74: =Plan!I123 | E74: =Plan!K123 | F74: =Plan!L123 | G74: =Plan!O123 | H74: =IF(AND(H$5>$E74,H$5<=$F74),IF(H$5=$E74+1,$C74,""),"") | I74: =IF(AND(I$5>$E74,I$5<=$F74),IF(I$5=$E74+1,$C74,""),"") | J74: =IF(AND(J$5>$E74,J$5<=$F74),IF(J$5=$E74+1,$C74,""),"") | K74: =IF(AND(K$5>$E74,K$5<=$F74),IF(K$5=$E74+1,$C74,""),"") | L74: =IF(AND(L$5>$E74,L$5<=$F74),IF(L$5=$E74+1,$C74,""),"") | M74: =IF(AND(M$5>$E74,M$5<=$F74),IF(M$5=$E74+1,$C74,""),"") | N74: =IF(AND(N$5>$E74,N$5<=$F74),IF(N$5=$E74+1,$C74,""),"") | O74: =IF(AND(O$5>$E74,O$5<=$F74),IF(O$5=$E74+1,$C74,""),"") | ... FA74: =IF(AND(FA$5>$E74,FA$5<=$F74),IF(FA$5=$E74+1,$C74,""),"")
A75: Fase 5. Convenios y pulido | E75: =SUMPRODUCT(MIN((Plan!$B$5:$B$129="5. Convenios y pulido")*Plan!$K$5:$K$129+(Plan!$B$5:$B$129<>"5. Convenios y pulido")*1E9)) | F75: =SUMPRODUCT(MAX((Plan!$B$5:$B$129="5. Convenios y pulido")*Plan!$L$5:$L$129)) | G75: =Resumen!E33
A76: =Plan!A48 | B76: =Plan!C48 | C76: =Plan!D48 | D76: =Plan!I48 | E76: =Plan!K48 | F76: =Plan!L48 | G76: =Plan!O48 | H76: =IF(AND(H$5>$E76,H$5<=$F76),IF(H$5=$E76+1,$C76,""),"") | I76: =IF(AND(I$5>$E76,I$5<=$F76),IF(I$5=$E76+1,$C76,""),"") | J76: =IF(AND(J$5>$E76,J$5<=$F76),IF(J$5=$E76+1,$C76,""),"") | K76: =IF(AND(K$5>$E76,K$5<=$F76),IF(K$5=$E76+1,$C76,""),"") | L76: =IF(AND(L$5>$E76,L$5<=$F76),IF(L$5=$E76+1,$C76,""),"") | M76: =IF(AND(M$5>$E76,M$5<=$F76),IF(M$5=$E76+1,$C76,""),"") | N76: =IF(AND(N$5>$E76,N$5<=$F76),IF(N$5=$E76+1,$C76,""),"") | O76: =IF(AND(O$5>$E76,O$5<=$F76),IF(O$5=$E76+1,$C76,""),"") | ... FA76: =IF(AND(FA$5>$E76,FA$5<=$F76),IF(FA$5=$E76+1,$C76,""),"")
A77: =Plan!A49 | B77: =Plan!C49 | C77: =Plan!D49 | D77: =Plan!I49 | E77: =Plan!K49 | F77: =Plan!L49 | G77: =Plan!O49 | H77: =IF(AND(H$5>$E77,H$5<=$F77),IF(H$5=$E77+1,$C77,""),"") | I77: =IF(AND(I$5>$E77,I$5<=$F77),IF(I$5=$E77+1,$C77,""),"") | J77: =IF(AND(J$5>$E77,J$5<=$F77),IF(J$5=$E77+1,$C77,""),"") | K77: =IF(AND(K$5>$E77,K$5<=$F77),IF(K$5=$E77+1,$C77,""),"") | L77: =IF(AND(L$5>$E77,L$5<=$F77),IF(L$5=$E77+1,$C77,""),"") | M77: =IF(AND(M$5>$E77,M$5<=$F77),IF(M$5=$E77+1,$C77,""),"") | N77: =IF(AND(N$5>$E77,N$5<=$F77),IF(N$5=$E77+1,$C77,""),"") | O77: =IF(AND(O$5>$E77,O$5<=$F77),IF(O$5=$E77+1,$C77,""),"") | ... FA77: =IF(AND(FA$5>$E77,FA$5<=$F77),IF(FA$5=$E77+1,$C77,""),"")
A78: =Plan!A50 | B78: =Plan!C50 | C78: =Plan!D50 | D78: =Plan!I50 | E78: =Plan!K50 | F78: =Plan!L50 | G78: =Plan!O50 | H78: =IF(AND(H$5>$E78,H$5<=$F78),IF(H$5=$E78+1,$C78,""),"") | I78: =IF(AND(I$5>$E78,I$5<=$F78),IF(I$5=$E78+1,$C78,""),"") | J78: =IF(AND(J$5>$E78,J$5<=$F78),IF(J$5=$E78+1,$C78,""),"") | K78: =IF(AND(K$5>$E78,K$5<=$F78),IF(K$5=$E78+1,$C78,""),"") | L78: =IF(AND(L$5>$E78,L$5<=$F78),IF(L$5=$E78+1,$C78,""),"") | M78: =IF(AND(M$5>$E78,M$5<=$F78),IF(M$5=$E78+1,$C78,""),"") | N78: =IF(AND(N$5>$E78,N$5<=$F78),IF(N$5=$E78+1,$C78,""),"") | O78: =IF(AND(O$5>$E78,O$5<=$F78),IF(O$5=$E78+1,$C78,""),"") | ... FA78: =IF(AND(FA$5>$E78,FA$5<=$F78),IF(FA$5=$E78+1,$C78,""),"")
A79: =Plan!A51 | B79: =Plan!C51 | C79: =Plan!D51 | D79: =Plan!I51 | E79: =Plan!K51 | F79: =Plan!L51 | G79: =Plan!O51 | H79: =IF(AND(H$5>$E79,H$5<=$F79),IF(H$5=$E79+1,$C79,""),"") | I79: =IF(AND(I$5>$E79,I$5<=$F79),IF(I$5=$E79+1,$C79,""),"") | J79: =IF(AND(J$5>$E79,J$5<=$F79),IF(J$5=$E79+1,$C79,""),"") | K79: =IF(AND(K$5>$E79,K$5<=$F79),IF(K$5=$E79+1,$C79,""),"") | L79: =IF(AND(L$5>$E79,L$5<=$F79),IF(L$5=$E79+1,$C79,""),"") | M79: =IF(AND(M$5>$E79,M$5<=$F79),IF(M$5=$E79+1,$C79,""),"") | N79: =IF(AND(N$5>$E79,N$5<=$F79),IF(N$5=$E79+1,$C79,""),"") | O79: =IF(AND(O$5>$E79,O$5<=$F79),IF(O$5=$E79+1,$C79,""),"") | ... FA79: =IF(AND(FA$5>$E79,FA$5<=$F79),IF(FA$5=$E79+1,$C79,""),"")
A80: =Plan!A52 | B80: =Plan!C52 | C80: =Plan!D52 | D80: =Plan!I52 | E80: =Plan!K52 | F80: =Plan!L52 | G80: =Plan!O52 | H80: =IF(AND(H$5>$E80,H$5<=$F80),IF(H$5=$E80+1,$C80,""),"") | I80: =IF(AND(I$5>$E80,I$5<=$F80),IF(I$5=$E80+1,$C80,""),"") | J80: =IF(AND(J$5>$E80,J$5<=$F80),IF(J$5=$E80+1,$C80,""),"") | K80: =IF(AND(K$5>$E80,K$5<=$F80),IF(K$5=$E80+1,$C80,""),"") | L80: =IF(AND(L$5>$E80,L$5<=$F80),IF(L$5=$E80+1,$C80,""),"") | M80: =IF(AND(M$5>$E80,M$5<=$F80),IF(M$5=$E80+1,$C80,""),"") | N80: =IF(AND(N$5>$E80,N$5<=$F80),IF(N$5=$E80+1,$C80,""),"") | O80: =IF(AND(O$5>$E80,O$5<=$F80),IF(O$5=$E80+1,$C80,""),"") | ... FA80: =IF(AND(FA$5>$E80,FA$5<=$F80),IF(FA$5=$E80+1,$C80,""),"")
A81: =Plan!A53 | B81: =Plan!C53 | C81: =Plan!D53 | D81: =Plan!I53 | E81: =Plan!K53 | F81: =Plan!L53 | G81: =Plan!O53 | H81: =IF(AND(H$5>$E81,H$5<=$F81),IF(H$5=$E81+1,$C81,""),"") | I81: =IF(AND(I$5>$E81,I$5<=$F81),IF(I$5=$E81+1,$C81,""),"") | J81: =IF(AND(J$5>$E81,J$5<=$F81),IF(J$5=$E81+1,$C81,""),"") | K81: =IF(AND(K$5>$E81,K$5<=$F81),IF(K$5=$E81+1,$C81,""),"") | L81: =IF(AND(L$5>$E81,L$5<=$F81),IF(L$5=$E81+1,$C81,""),"") | M81: =IF(AND(M$5>$E81,M$5<=$F81),IF(M$5=$E81+1,$C81,""),"") | N81: =IF(AND(N$5>$E81,N$5<=$F81),IF(N$5=$E81+1,$C81,""),"") | O81: =IF(AND(O$5>$E81,O$5<=$F81),IF(O$5=$E81+1,$C81,""),"") | ... FA81: =IF(AND(FA$5>$E81,FA$5<=$F81),IF(FA$5=$E81+1,$C81,""),"")
A82: =Plan!A54 | B82: =Plan!C54 | C82: =Plan!D54 | D82: =Plan!I54 | E82: =Plan!K54 | F82: =Plan!L54 | G82: =Plan!O54 | H82: =IF(AND(H$5>$E82,H$5<=$F82),IF(H$5=$E82+1,$C82,""),"") | I82: =IF(AND(I$5>$E82,I$5<=$F82),IF(I$5=$E82+1,$C82,""),"") | J82: =IF(AND(J$5>$E82,J$5<=$F82),IF(J$5=$E82+1,$C82,""),"") | K82: =IF(AND(K$5>$E82,K$5<=$F82),IF(K$5=$E82+1,$C82,""),"") | L82: =IF(AND(L$5>$E82,L$5<=$F82),IF(L$5=$E82+1,$C82,""),"") | M82: =IF(AND(M$5>$E82,M$5<=$F82),IF(M$5=$E82+1,$C82,""),"") | N82: =IF(AND(N$5>$E82,N$5<=$F82),IF(N$5=$E82+1,$C82,""),"") | O82: =IF(AND(O$5>$E82,O$5<=$F82),IF(O$5=$E82+1,$C82,""),"") | ... FA82: =IF(AND(FA$5>$E82,FA$5<=$F82),IF(FA$5=$E82+1,$C82,""),"")
A83: =Plan!A55 | B83: =Plan!C55 | C83: =Plan!D55 | D83: =Plan!I55 | E83: =Plan!K55 | F83: =Plan!L55 | G83: =Plan!O55 | H83: =IF(AND(H$5>$E83,H$5<=$F83),IF(H$5=$E83+1,$C83,""),"") | I83: =IF(AND(I$5>$E83,I$5<=$F83),IF(I$5=$E83+1,$C83,""),"") | J83: =IF(AND(J$5>$E83,J$5<=$F83),IF(J$5=$E83+1,$C83,""),"") | K83: =IF(AND(K$5>$E83,K$5<=$F83),IF(K$5=$E83+1,$C83,""),"") | L83: =IF(AND(L$5>$E83,L$5<=$F83),IF(L$5=$E83+1,$C83,""),"") | M83: =IF(AND(M$5>$E83,M$5<=$F83),IF(M$5=$E83+1,$C83,""),"") | N83: =IF(AND(N$5>$E83,N$5<=$F83),IF(N$5=$E83+1,$C83,""),"") | O83: =IF(AND(O$5>$E83,O$5<=$F83),IF(O$5=$E83+1,$C83,""),"") | ... FA83: =IF(AND(FA$5>$E83,FA$5<=$F83),IF(FA$5=$E83+1,$C83,""),"")
A84: =Plan!A56 | B84: =Plan!C56 | C84: =Plan!D56 | D84: =Plan!I56 | E84: =Plan!K56 | F84: =Plan!L56 | G84: =Plan!O56 | H84: =IF(AND(H$5>$E84,H$5<=$F84),IF(H$5=$E84+1,$C84,""),"") | I84: =IF(AND(I$5>$E84,I$5<=$F84),IF(I$5=$E84+1,$C84,""),"") | J84: =IF(AND(J$5>$E84,J$5<=$F84),IF(J$5=$E84+1,$C84,""),"") | K84: =IF(AND(K$5>$E84,K$5<=$F84),IF(K$5=$E84+1,$C84,""),"") | L84: =IF(AND(L$5>$E84,L$5<=$F84),IF(L$5=$E84+1,$C84,""),"") | M84: =IF(AND(M$5>$E84,M$5<=$F84),IF(M$5=$E84+1,$C84,""),"") | N84: =IF(AND(N$5>$E84,N$5<=$F84),IF(N$5=$E84+1,$C84,""),"") | O84: =IF(AND(O$5>$E84,O$5<=$F84),IF(O$5=$E84+1,$C84,""),"") | ... FA84: =IF(AND(FA$5>$E84,FA$5<=$F84),IF(FA$5=$E84+1,$C84,""),"")
A85: =Plan!A57 | B85: =Plan!C57 | C85: =Plan!D57 | D85: =Plan!I57 | E85: =Plan!K57 | F85: =Plan!L57 | G85: =Plan!O57 | H85: =IF(AND(H$5>$E85,H$5<=$F85),IF(H$5=$E85+1,$C85,""),"") | I85: =IF(AND(I$5>$E85,I$5<=$F85),IF(I$5=$E85+1,$C85,""),"") | J85: =IF(AND(J$5>$E85,J$5<=$F85),IF(J$5=$E85+1,$C85,""),"") | K85: =IF(AND(K$5>$E85,K$5<=$F85),IF(K$5=$E85+1,$C85,""),"") | L85: =IF(AND(L$5>$E85,L$5<=$F85),IF(L$5=$E85+1,$C85,""),"") | M85: =IF(AND(M$5>$E85,M$5<=$F85),IF(M$5=$E85+1,$C85,""),"") | N85: =IF(AND(N$5>$E85,N$5<=$F85),IF(N$5=$E85+1,$C85,""),"") | O85: =IF(AND(O$5>$E85,O$5<=$F85),IF(O$5=$E85+1,$C85,""),"") | ... FA85: =IF(AND(FA$5>$E85,FA$5<=$F85),IF(FA$5=$E85+1,$C85,""),"")
A86: =Plan!A84 | B86: =Plan!C84 | C86: =Plan!D84 | D86: =Plan!I84 | E86: =Plan!K84 | F86: =Plan!L84 | G86: =Plan!O84 | H86: =IF(AND(H$5>$E86,H$5<=$F86),IF(H$5=$E86+1,$C86,""),"") | I86: =IF(AND(I$5>$E86,I$5<=$F86),IF(I$5=$E86+1,$C86,""),"") | J86: =IF(AND(J$5>$E86,J$5<=$F86),IF(J$5=$E86+1,$C86,""),"") | K86: =IF(AND(K$5>$E86,K$5<=$F86),IF(K$5=$E86+1,$C86,""),"") | L86: =IF(AND(L$5>$E86,L$5<=$F86),IF(L$5=$E86+1,$C86,""),"") | M86: =IF(AND(M$5>$E86,M$5<=$F86),IF(M$5=$E86+1,$C86,""),"") | N86: =IF(AND(N$5>$E86,N$5<=$F86),IF(N$5=$E86+1,$C86,""),"") | O86: =IF(AND(O$5>$E86,O$5<=$F86),IF(O$5=$E86+1,$C86,""),"") | ... FA86: =IF(AND(FA$5>$E86,FA$5<=$F86),IF(FA$5=$E86+1,$C86,""),"")
A87: =Plan!A85 | B87: =Plan!C85 | C87: =Plan!D85 | D87: =Plan!I85 | E87: =Plan!K85 | F87: =Plan!L85 | G87: =Plan!O85 | H87: =IF(AND(H$5>$E87,H$5<=$F87),IF(H$5=$E87+1,$C87,""),"") | I87: =IF(AND(I$5>$E87,I$5<=$F87),IF(I$5=$E87+1,$C87,""),"") | J87: =IF(AND(J$5>$E87,J$5<=$F87),IF(J$5=$E87+1,$C87,""),"") | K87: =IF(AND(K$5>$E87,K$5<=$F87),IF(K$5=$E87+1,$C87,""),"") | L87: =IF(AND(L$5>$E87,L$5<=$F87),IF(L$5=$E87+1,$C87,""),"") | M87: =IF(AND(M$5>$E87,M$5<=$F87),IF(M$5=$E87+1,$C87,""),"") | N87: =IF(AND(N$5>$E87,N$5<=$F87),IF(N$5=$E87+1,$C87,""),"") | O87: =IF(AND(O$5>$E87,O$5<=$F87),IF(O$5=$E87+1,$C87,""),"") | ... FA87: =IF(AND(FA$5>$E87,FA$5<=$F87),IF(FA$5=$E87+1,$C87,""),"")
A88: =Plan!A86 | B88: =Plan!C86 | C88: =Plan!D86 | D88: =Plan!I86 | E88: =Plan!K86 | F88: =Plan!L86 | G88: =Plan!O86 | H88: =IF(AND(H$5>$E88,H$5<=$F88),IF(H$5=$E88+1,$C88,""),"") | I88: =IF(AND(I$5>$E88,I$5<=$F88),IF(I$5=$E88+1,$C88,""),"") | J88: =IF(AND(J$5>$E88,J$5<=$F88),IF(J$5=$E88+1,$C88,""),"") | K88: =IF(AND(K$5>$E88,K$5<=$F88),IF(K$5=$E88+1,$C88,""),"") | L88: =IF(AND(L$5>$E88,L$5<=$F88),IF(L$5=$E88+1,$C88,""),"") | M88: =IF(AND(M$5>$E88,M$5<=$F88),IF(M$5=$E88+1,$C88,""),"") | N88: =IF(AND(N$5>$E88,N$5<=$F88),IF(N$5=$E88+1,$C88,""),"") | O88: =IF(AND(O$5>$E88,O$5<=$F88),IF(O$5=$E88+1,$C88,""),"") | ... FA88: =IF(AND(FA$5>$E88,FA$5<=$F88),IF(FA$5=$E88+1,$C88,""),"")
A89: =Plan!A91 | B89: =Plan!C91 | C89: =Plan!D91 | D89: =Plan!I91 | E89: =Plan!K91 | F89: =Plan!L91 | G89: =Plan!O91 | H89: =IF(AND(H$5>$E89,H$5<=$F89),IF(H$5=$E89+1,$C89,""),"") | I89: =IF(AND(I$5>$E89,I$5<=$F89),IF(I$5=$E89+1,$C89,""),"") | J89: =IF(AND(J$5>$E89,J$5<=$F89),IF(J$5=$E89+1,$C89,""),"") | K89: =IF(AND(K$5>$E89,K$5<=$F89),IF(K$5=$E89+1,$C89,""),"") | L89: =IF(AND(L$5>$E89,L$5<=$F89),IF(L$5=$E89+1,$C89,""),"") | M89: =IF(AND(M$5>$E89,M$5<=$F89),IF(M$5=$E89+1,$C89,""),"") | N89: =IF(AND(N$5>$E89,N$5<=$F89),IF(N$5=$E89+1,$C89,""),"") | O89: =IF(AND(O$5>$E89,O$5<=$F89),IF(O$5=$E89+1,$C89,""),"") | ... FA89: =IF(AND(FA$5>$E89,FA$5<=$F89),IF(FA$5=$E89+1,$C89,""),"")
A90: =Plan!A96 | B90: =Plan!C96 | C90: =Plan!D96 | D90: =Plan!I96 | E90: =Plan!K96 | F90: =Plan!L96 | G90: =Plan!O96 | H90: =IF(AND(H$5>$E90,H$5<=$F90),IF(H$5=$E90+1,$C90,""),"") | I90: =IF(AND(I$5>$E90,I$5<=$F90),IF(I$5=$E90+1,$C90,""),"") | J90: =IF(AND(J$5>$E90,J$5<=$F90),IF(J$5=$E90+1,$C90,""),"") | K90: =IF(AND(K$5>$E90,K$5<=$F90),IF(K$5=$E90+1,$C90,""),"") | L90: =IF(AND(L$5>$E90,L$5<=$F90),IF(L$5=$E90+1,$C90,""),"") | M90: =IF(AND(M$5>$E90,M$5<=$F90),IF(M$5=$E90+1,$C90,""),"") | N90: =IF(AND(N$5>$E90,N$5<=$F90),IF(N$5=$E90+1,$C90,""),"") | O90: =IF(AND(O$5>$E90,O$5<=$F90),IF(O$5=$E90+1,$C90,""),"") | ... FA90: =IF(AND(FA$5>$E90,FA$5<=$F90),IF(FA$5=$E90+1,$C90,""),"")
A91: =Plan!A97 | B91: =Plan!C97 | C91: =Plan!D97 | D91: =Plan!I97 | E91: =Plan!K97 | F91: =Plan!L97 | G91: =Plan!O97 | H91: =IF(AND(H$5>$E91,H$5<=$F91),IF(H$5=$E91+1,$C91,""),"") | I91: =IF(AND(I$5>$E91,I$5<=$F91),IF(I$5=$E91+1,$C91,""),"") | J91: =IF(AND(J$5>$E91,J$5<=$F91),IF(J$5=$E91+1,$C91,""),"") | K91: =IF(AND(K$5>$E91,K$5<=$F91),IF(K$5=$E91+1,$C91,""),"") | L91: =IF(AND(L$5>$E91,L$5<=$F91),IF(L$5=$E91+1,$C91,""),"") | M91: =IF(AND(M$5>$E91,M$5<=$F91),IF(M$5=$E91+1,$C91,""),"") | N91: =IF(AND(N$5>$E91,N$5<=$F91),IF(N$5=$E91+1,$C91,""),"") | O91: =IF(AND(O$5>$E91,O$5<=$F91),IF(O$5=$E91+1,$C91,""),"") | ... FA91: =IF(AND(FA$5>$E91,FA$5<=$F91),IF(FA$5=$E91+1,$C91,""),"")
A92: =Plan!A98 | B92: =Plan!C98 | C92: =Plan!D98 | D92: =Plan!I98 | E92: =Plan!K98 | F92: =Plan!L98 | G92: =Plan!O98 | H92: =IF(AND(H$5>$E92,H$5<=$F92),IF(H$5=$E92+1,$C92,""),"") | I92: =IF(AND(I$5>$E92,I$5<=$F92),IF(I$5=$E92+1,$C92,""),"") | J92: =IF(AND(J$5>$E92,J$5<=$F92),IF(J$5=$E92+1,$C92,""),"") | K92: =IF(AND(K$5>$E92,K$5<=$F92),IF(K$5=$E92+1,$C92,""),"") | L92: =IF(AND(L$5>$E92,L$5<=$F92),IF(L$5=$E92+1,$C92,""),"") | M92: =IF(AND(M$5>$E92,M$5<=$F92),IF(M$5=$E92+1,$C92,""),"") | N92: =IF(AND(N$5>$E92,N$5<=$F92),IF(N$5=$E92+1,$C92,""),"") | O92: =IF(AND(O$5>$E92,O$5<=$F92),IF(O$5=$E92+1,$C92,""),"") | ... FA92: =IF(AND(FA$5>$E92,FA$5<=$F92),IF(FA$5=$E92+1,$C92,""),"")
A93: =Plan!A105 | B93: =Plan!C105 | C93: =Plan!D105 | D93: =Plan!I105 | E93: =Plan!K105 | F93: =Plan!L105 | G93: =Plan!O105 | H93: =IF(AND(H$5>$E93,H$5<=$F93),IF(H$5=$E93+1,$C93,""),"") | I93: =IF(AND(I$5>$E93,I$5<=$F93),IF(I$5=$E93+1,$C93,""),"") | J93: =IF(AND(J$5>$E93,J$5<=$F93),IF(J$5=$E93+1,$C93,""),"") | K93: =IF(AND(K$5>$E93,K$5<=$F93),IF(K$5=$E93+1,$C93,""),"") | L93: =IF(AND(L$5>$E93,L$5<=$F93),IF(L$5=$E93+1,$C93,""),"") | M93: =IF(AND(M$5>$E93,M$5<=$F93),IF(M$5=$E93+1,$C93,""),"") | N93: =IF(AND(N$5>$E93,N$5<=$F93),IF(N$5=$E93+1,$C93,""),"") | O93: =IF(AND(O$5>$E93,O$5<=$F93),IF(O$5=$E93+1,$C93,""),"") | ... FA93: =IF(AND(FA$5>$E93,FA$5<=$F93),IF(FA$5=$E93+1,$C93,""),"")
A94: =Plan!A106 | B94: =Plan!C106 | C94: =Plan!D106 | D94: =Plan!I106 | E94: =Plan!K106 | F94: =Plan!L106 | G94: =Plan!O106 | H94: =IF(AND(H$5>$E94,H$5<=$F94),IF(H$5=$E94+1,$C94,""),"") | I94: =IF(AND(I$5>$E94,I$5<=$F94),IF(I$5=$E94+1,$C94,""),"") | J94: =IF(AND(J$5>$E94,J$5<=$F94),IF(J$5=$E94+1,$C94,""),"") | K94: =IF(AND(K$5>$E94,K$5<=$F94),IF(K$5=$E94+1,$C94,""),"") | L94: =IF(AND(L$5>$E94,L$5<=$F94),IF(L$5=$E94+1,$C94,""),"") | M94: =IF(AND(M$5>$E94,M$5<=$F94),IF(M$5=$E94+1,$C94,""),"") | N94: =IF(AND(N$5>$E94,N$5<=$F94),IF(N$5=$E94+1,$C94,""),"") | O94: =IF(AND(O$5>$E94,O$5<=$F94),IF(O$5=$E94+1,$C94,""),"") | ... FA94: =IF(AND(FA$5>$E94,FA$5<=$F94),IF(FA$5=$E94+1,$C94,""),"")
A95: Fase 6. Pruebas y lanzamiento | E95: =SUMPRODUCT(MIN((Plan!$B$5:$B$129="6. Pruebas y lanzamiento")*Plan!$K$5:$K$129+(Plan!$B$5:$B$129<>"6. Pruebas y lanzamiento")*1E9)) | F95: =SUMPRODUCT(MAX((Plan!$B$5:$B$129="6. Pruebas y lanzamiento")*Plan!$L$5:$L$129)) | G95: =Resumen!E34
A96: =Plan!A58 | B96: =Plan!C58 | C96: =Plan!D58 | D96: =Plan!I58 | E96: =Plan!K58 | F96: =Plan!L58 | G96: =Plan!O58 | H96: =IF(AND(H$5>$E96,H$5<=$F96),IF(H$5=$E96+1,$C96,""),"") | I96: =IF(AND(I$5>$E96,I$5<=$F96),IF(I$5=$E96+1,$C96,""),"") | J96: =IF(AND(J$5>$E96,J$5<=$F96),IF(J$5=$E96+1,$C96,""),"") | K96: =IF(AND(K$5>$E96,K$5<=$F96),IF(K$5=$E96+1,$C96,""),"") | L96: =IF(AND(L$5>$E96,L$5<=$F96),IF(L$5=$E96+1,$C96,""),"") | M96: =IF(AND(M$5>$E96,M$5<=$F96),IF(M$5=$E96+1,$C96,""),"") | N96: =IF(AND(N$5>$E96,N$5<=$F96),IF(N$5=$E96+1,$C96,""),"") | O96: =IF(AND(O$5>$E96,O$5<=$F96),IF(O$5=$E96+1,$C96,""),"") | ... FA96: =IF(AND(FA$5>$E96,FA$5<=$F96),IF(FA$5=$E96+1,$C96,""),"")
A97: =Plan!A59 | B97: =Plan!C59 | C97: =Plan!D59 | D97: =Plan!I59 | E97: =Plan!K59 | F97: =Plan!L59 | G97: =Plan!O59 | H97: =IF(AND(H$5>$E97,H$5<=$F97),IF(H$5=$E97+1,$C97,""),"") | I97: =IF(AND(I$5>$E97,I$5<=$F97),IF(I$5=$E97+1,$C97,""),"") | J97: =IF(AND(J$5>$E97,J$5<=$F97),IF(J$5=$E97+1,$C97,""),"") | K97: =IF(AND(K$5>$E97,K$5<=$F97),IF(K$5=$E97+1,$C97,""),"") | L97: =IF(AND(L$5>$E97,L$5<=$F97),IF(L$5=$E97+1,$C97,""),"") | M97: =IF(AND(M$5>$E97,M$5<=$F97),IF(M$5=$E97+1,$C97,""),"") | N97: =IF(AND(N$5>$E97,N$5<=$F97),IF(N$5=$E97+1,$C97,""),"") | O97: =IF(AND(O$5>$E97,O$5<=$F97),IF(O$5=$E97+1,$C97,""),"") | ... FA97: =IF(AND(FA$5>$E97,FA$5<=$F97),IF(FA$5=$E97+1,$C97,""),"")
A98: =Plan!A60 | B98: =Plan!C60 | C98: =Plan!D60 | D98: =Plan!I60 | E98: =Plan!K60 | F98: =Plan!L60 | G98: =Plan!O60 | H98: =IF(AND(H$5>$E98,H$5<=$F98),IF(H$5=$E98+1,$C98,""),"") | I98: =IF(AND(I$5>$E98,I$5<=$F98),IF(I$5=$E98+1,$C98,""),"") | J98: =IF(AND(J$5>$E98,J$5<=$F98),IF(J$5=$E98+1,$C98,""),"") | K98: =IF(AND(K$5>$E98,K$5<=$F98),IF(K$5=$E98+1,$C98,""),"") | L98: =IF(AND(L$5>$E98,L$5<=$F98),IF(L$5=$E98+1,$C98,""),"") | M98: =IF(AND(M$5>$E98,M$5<=$F98),IF(M$5=$E98+1,$C98,""),"") | N98: =IF(AND(N$5>$E98,N$5<=$F98),IF(N$5=$E98+1,$C98,""),"") | O98: =IF(AND(O$5>$E98,O$5<=$F98),IF(O$5=$E98+1,$C98,""),"") | ... FA98: =IF(AND(FA$5>$E98,FA$5<=$F98),IF(FA$5=$E98+1,$C98,""),"")
A99: =Plan!A61 | B99: =Plan!C61 | C99: =Plan!D61 | D99: =Plan!I61 | E99: =Plan!K61 | F99: =Plan!L61 | G99: =Plan!O61 | H99: =IF(AND(H$5>$E99,H$5<=$F99),IF(H$5=$E99+1,$C99,""),"") | I99: =IF(AND(I$5>$E99,I$5<=$F99),IF(I$5=$E99+1,$C99,""),"") | J99: =IF(AND(J$5>$E99,J$5<=$F99),IF(J$5=$E99+1,$C99,""),"") | K99: =IF(AND(K$5>$E99,K$5<=$F99),IF(K$5=$E99+1,$C99,""),"") | L99: =IF(AND(L$5>$E99,L$5<=$F99),IF(L$5=$E99+1,$C99,""),"") | M99: =IF(AND(M$5>$E99,M$5<=$F99),IF(M$5=$E99+1,$C99,""),"") | N99: =IF(AND(N$5>$E99,N$5<=$F99),IF(N$5=$E99+1,$C99,""),"") | O99: =IF(AND(O$5>$E99,O$5<=$F99),IF(O$5=$E99+1,$C99,""),"") | ... FA99: =IF(AND(FA$5>$E99,FA$5<=$F99),IF(FA$5=$E99+1,$C99,""),"")
A100: =Plan!A62 | B100: =Plan!C62 | C100: =Plan!D62 | D100: =Plan!I62 | E100: =Plan!K62 | F100: =Plan!L62 | G100: =Plan!O62 | H100: =IF(AND(H$5>$E100,H$5<=$F100),IF(H$5=$E100+1,$C100,""),"") | I100: =IF(AND(I$5>$E100,I$5<=$F100),IF(I$5=$E100+1,$C100,""),"") | J100: =IF(AND(J$5>$E100,J$5<=$F100),IF(J$5=$E100+1,$C100,""),"") | K100: =IF(AND(K$5>$E100,K$5<=$F100),IF(K$5=$E100+1,$C100,""),"") | L100: =IF(AND(L$5>$E100,L$5<=$F100),IF(L$5=$E100+1,$C100,""),"") | M100: =IF(AND(M$5>$E100,M$5<=$F100),IF(M$5=$E100+1,$C100,""),"") | N100: =IF(AND(N$5>$E100,N$5<=$F100),IF(N$5=$E100+1,$C100,""),"") | O100: =IF(AND(O$5>$E100,O$5<=$F100),IF(O$5=$E100+1,$C100,""),"") | ... FA100: =IF(AND(FA$5>$E100,FA$5<=$F100),IF(FA$5=$E100+1,$C100,""),"")
A101: =Plan!A63 | B101: =Plan!C63 | C101: =Plan!D63 | D101: =Plan!I63 | E101: =Plan!K63 | F101: =Plan!L63 | G101: =Plan!O63 | H101: =IF(AND(H$5>$E101,H$5<=$F101),IF(H$5=$E101+1,$C101,""),"") | I101: =IF(AND(I$5>$E101,I$5<=$F101),IF(I$5=$E101+1,$C101,""),"") | J101: =IF(AND(J$5>$E101,J$5<=$F101),IF(J$5=$E101+1,$C101,""),"") | K101: =IF(AND(K$5>$E101,K$5<=$F101),IF(K$5=$E101+1,$C101,""),"") | L101: =IF(AND(L$5>$E101,L$5<=$F101),IF(L$5=$E101+1,$C101,""),"") | M101: =IF(AND(M$5>$E101,M$5<=$F101),IF(M$5=$E101+1,$C101,""),"") | N101: =IF(AND(N$5>$E101,N$5<=$F101),IF(N$5=$E101+1,$C101,""),"") | O101: =IF(AND(O$5>$E101,O$5<=$F101),IF(O$5=$E101+1,$C101,""),"") | ... FA101: =IF(AND(FA$5>$E101,FA$5<=$F101),IF(FA$5=$E101+1,$C101,""),"")
A102: =Plan!A64 | B102: =Plan!C64 | C102: =Plan!D64 | D102: =Plan!I64 | E102: =Plan!K64 | F102: =Plan!L64 | G102: =Plan!O64 | H102: =IF(AND(H$5>$E102,H$5<=$F102),IF(H$5=$E102+1,$C102,""),"") | I102: =IF(AND(I$5>$E102,I$5<=$F102),IF(I$5=$E102+1,$C102,""),"") | J102: =IF(AND(J$5>$E102,J$5<=$F102),IF(J$5=$E102+1,$C102,""),"") | K102: =IF(AND(K$5>$E102,K$5<=$F102),IF(K$5=$E102+1,$C102,""),"") | L102: =IF(AND(L$5>$E102,L$5<=$F102),IF(L$5=$E102+1,$C102,""),"") | M102: =IF(AND(M$5>$E102,M$5<=$F102),IF(M$5=$E102+1,$C102,""),"") | N102: =IF(AND(N$5>$E102,N$5<=$F102),IF(N$5=$E102+1,$C102,""),"") | O102: =IF(AND(O$5>$E102,O$5<=$F102),IF(O$5=$E102+1,$C102,""),"") | ... FA102: =IF(AND(FA$5>$E102,FA$5<=$F102),IF(FA$5=$E102+1,$C102,""),"")
A103: =Plan!A65 | B103: =Plan!C65 | C103: =Plan!D65 | D103: =Plan!I65 | E103: =Plan!K65 | F103: =Plan!L65 | G103: =Plan!O65 | H103: =IF(AND(H$5>$E103,H$5<=$F103),IF(H$5=$E103+1,$C103,""),"") | I103: =IF(AND(I$5>$E103,I$5<=$F103),IF(I$5=$E103+1,$C103,""),"") | J103: =IF(AND(J$5>$E103,J$5<=$F103),IF(J$5=$E103+1,$C103,""),"") | K103: =IF(AND(K$5>$E103,K$5<=$F103),IF(K$5=$E103+1,$C103,""),"") | L103: =IF(AND(L$5>$E103,L$5<=$F103),IF(L$5=$E103+1,$C103,""),"") | M103: =IF(AND(M$5>$E103,M$5<=$F103),IF(M$5=$E103+1,$C103,""),"") | N103: =IF(AND(N$5>$E103,N$5<=$F103),IF(N$5=$E103+1,$C103,""),"") | O103: =IF(AND(O$5>$E103,O$5<=$F103),IF(O$5=$E103+1,$C103,""),"") | ... FA103: =IF(AND(FA$5>$E103,FA$5<=$F103),IF(FA$5=$E103+1,$C103,""),"")
A104: =Plan!A66 | B104: =Plan!C66 | C104: =Plan!D66 | D104: =Plan!I66 | E104: =Plan!K66 | F104: =Plan!L66 | G104: =Plan!O66 | H104: =IF(AND(H$5>$E104,H$5<=$F104),IF(H$5=$E104+1,$C104,""),"") | I104: =IF(AND(I$5>$E104,I$5<=$F104),IF(I$5=$E104+1,$C104,""),"") | J104: =IF(AND(J$5>$E104,J$5<=$F104),IF(J$5=$E104+1,$C104,""),"") | K104: =IF(AND(K$5>$E104,K$5<=$F104),IF(K$5=$E104+1,$C104,""),"") | L104: =IF(AND(L$5>$E104,L$5<=$F104),IF(L$5=$E104+1,$C104,""),"") | M104: =IF(AND(M$5>$E104,M$5<=$F104),IF(M$5=$E104+1,$C104,""),"") | N104: =IF(AND(N$5>$E104,N$5<=$F104),IF(N$5=$E104+1,$C104,""),"") | O104: =IF(AND(O$5>$E104,O$5<=$F104),IF(O$5=$E104+1,$C104,""),"") | ... FA104: =IF(AND(FA$5>$E104,FA$5<=$F104),IF(FA$5=$E104+1,$C104,""),"")
...

Sheet Cola
A1: Cola de trabajo — 2 filas, capacidad infinita
A2: Cada actividad entra a la cola cuando terminan sus dependencias y sale cuando una fila queda libre. Si hay varias esperando, sale primero la de mayor ruta crítica restante.
A4: Turno | B4: ID | C4: Actividad | D4: Prioridad (ruta crítica, bloques) | E4: Entra a la cola | F4: Sale de la cola (inicio) | G4: Espera | H4: Fila | I4: Estado
A5: 1 | B5: 1.1 | C5: =Plan!C5 | D5: 53 | E5: =Plan!J5 | F5: =Plan!K5 | G5: =F5-E5 | H5: =Plan!I5 | I5: =Plan!O5
A6: 2 | B6: 1.3 | C6: =Plan!C7 | D6: 50 | E6: =Plan!J7 | F6: =Plan!K7 | G6: =F6-E6 | H6: =Plan!I7 | I6: =Plan!O7
A7: 3 | B7: 1.2 | C7: =Plan!C6 | D7: 44 | E7: =Plan!J6 | F7: =Plan!K6 | G7: =F7-E7 | H7: =Plan!I6 | I7: =Plan!O6
A8: 4 | B8: 1.4 | C8: =Plan!C8 | D8: 49 | E8: =Plan!J8 | F8: =Plan!K8 | G8: =F8-E8 | H8: =Plan!I8 | I8: =Plan!O8
A9: 5 | B9: 2.4 | C9: =Plan!C16 | D9: 15 | E9: =Plan!J16 | F9: =Plan!K16 | G9: =F9-E9 | H9: =Plan!I16 | I9: =Plan!O16
A10: 6 | B10: 2.2 | C10: =Plan!C14 | D10: 47 | E10: =Plan!J14 | F10: =Plan!K14 | G10: =F10-E10 | H10: =Plan!I14 | I10: =Plan!O14
A11: 7 | B11: 2.1 | C11: =Plan!C13 | D11: 38 | E11: =Plan!J13 | F11: =Plan!K13 | G11: =F11-E11 | H11: =Plan!I13 | I11: =Plan!O13
A12: 8 | B12: 2.5 | C12: =Plan!C17 | D12: 45 | E12: =Plan!J17 | F12: =Plan!K17 | G12: =F12-E12 | H12: =Plan!I17 | I12: =Plan!O17
A13: 9 | B13: 3.1 | C13: =Plan!C28 | D13: 41 | E13: =Plan!J28 | F13: =Plan!K28 | G13: =F13-E13 | H13: =Plan!I28 | I13: =Plan!O28
A14: 10 | B14: 2.6 | C14: =Plan!C18 | D14: 42 | E14: =Plan!J18 | F14: =Plan!K18 | G14: =F14-E14 | H14: =Plan!I18 | I14: =Plan!O18
A15: 11 | B15: 1.5 | C15: =Plan!C9 | D15: 40 | E15: =Plan!J9 | F15: =Plan!K9 | G15: =F15-E15 | H15: =Plan!I9 | I15: =Plan!O9
A16: 12 | B16: 1.7 | C16: =Plan!C11 | D16: 37 | E16: =Plan!J11 | F16: =Plan!K11 | G16: =F16-E16 | H16: =Plan!I11 | I16: =Plan!O11
A17: 13 | B17: 2.14 | C17: =Plan!C26 | D17: 35 | E17: =Plan!J26 | F17: =Plan!K26 | G17: =F17-E17 | H17: =Plan!I26 | I17: =Plan!O26
A18: 14 | B18: 2.7 | C18: =Plan!C19 | D18: 39 | E18: =Plan!J19 | F18: =Plan!K19 | G18: =F18-E18 | H18: =Plan!I19 | I18: =Plan!O19
A19: 15 | B19: 4.1 | C19: =Plan!C37 | D19: 37 | E19: =Plan!J37 | F19: =Plan!K37 | G19: =F19-E19 | H19: =Plan!I37 | I19: =Plan!O37
A20: 16 | B20: 2.3 | C20: =Plan!C15 | D20: 36 | E20: =Plan!J15 | F20: =Plan!K15 | G20: =F20-E20 | H20: =Plan!I15 | I20: =Plan!O15
A21: 17 | B21: 2.8 | C21: =Plan!C20 | D21: 9 | E21: =Plan!J20 | F21: =Plan!K20 | G21: =F21-E21 | H21: =Plan!I20 | I21: =Plan!O20
A22: 18 | B22: 3.11 | C22: =Plan!C124 | D22: 4 | E22: =Plan!J124 | F22: =Plan!K124 | G22: =F22-E22 | H22: =Plan!I124 | I22: =Plan!O124
A23: 19 | B23: 2.15 | C23: =Plan!C27 | D23: 34 | E23: =Plan!J27 | F23: =Plan!K27 | G23: =F23-E23 | H23: =Plan!I27 | I23: =Plan!O27
A24: 20 | B24: 4.11 | C24: =Plan!C47 | D24: 33 | E24: =Plan!J47 | F24: =Plan!K47 | G24: =F24-E24 | H24: =Plan!I47 | I24: =Plan!O47
A25: 21 | B25: 3.4 | C25: =Plan!C31 | D25: 36 | E25: =Plan!J31 | F25: =Plan!K31 | G25: =F25-E25 | H25: =Plan!I31 | I25: =Plan!O31
A26: 22 | B26: 6.19 | C26: =Plan!C74 | D26: 31 | E26: =Plan!J74 | F26: =Plan!K74 | G26: =F26-E26 | H26: =Plan!I74 | I26: =Plan!O74
A27: 23 | B27: 6.16 | C27: =Plan!C73 | D27: 31 | E27: =Plan!J73 | F27: =Plan!K73 | G27: =F27-E27 | H27: =Plan!I73 | I27: =Plan!O73
A28: 24 | B28: 6.4 | C28: =Plan!C61 | D28: 6 | E28: =Plan!J61 | F28: =Plan!K61 | G28: =F28-E28 | H28: =Plan!I61 | I28: =Plan!O61
A29: 25 | B29: 4.6 | C29: =Plan!C42 | D29: 35 | E29: =Plan!J42 | F29: =Plan!K42 | G29: =F29-E29 | H29: =Plan!I42 | I29: =Plan!O42
A30: 26 | B30: 3.10 | C30: =Plan!C36 | D30: 33 | E30: =Plan!J36 | F30: =Plan!K36 | G30: =F30-E30 | H30: =Plan!I36 | I30: =Plan!O36
A31: 27 | B31: 4.10 | C31: =Plan!C46 | D31: 32 | E31: =Plan!J46 | F31: =Plan!K46 | G31: =F31-E31 | H31: =Plan!I46 | I31: =Plan!O46
A32: 28 | B32: 1.6 | C32: =Plan!C10 | D32: 31 | E32: =Plan!J10 | F32: =Plan!K10 | G32: =F32-E32 | H32: =Plan!I10 | I32: =Plan!O10
A33: 29 | B33: 2.17 | C33: =Plan!C125 | D33: 4 | E33: =Plan!J125 | F33: =Plan!K125 | G33: =F33-E33 | H33: =Plan!I125 | I33: =Plan!O125
A34: 30 | B34: 6.17 | C34: =Plan!C75 | D34: 30 | E34: =Plan!J75 | F34: =Plan!K75 | G34: =F34-E34 | H34: =Plan!I75 | I34: =Plan!O75
A35: 31 | B35: 1.8 | C35: =Plan!C12 | D35: 28 | E35: =Plan!J12 | F35: =Plan!K12 | G35: =F35-E35 | H35: =Plan!I12 | I35: =Plan!O12
A36: 32 | B36: 6.13 | C36: =Plan!C70 | D36: 6 | E36: =Plan!J70 | F36: =Plan!K70 | G36: =F36-E36 | H36: =Plan!I70 | I36: =Plan!O70
A37: 33 | B37: 6.18 | C37: =Plan!C76 | D37: 27 | E37: =Plan!J76 | F37: =Plan!K76 | G37: =F37-E37 | H37: =Plan!I76 | I37: =Plan!O76
A38: 34 | B38: 2.9 | C38: =Plan!C21 | D38: 18 | E38: =Plan!J21 | F38: =Plan!K21 | G38: =F38-E38 | H38: =Plan!I21 | I38: =Plan!O21
A39: 35 | B39: 4.12 | C39: =Plan!C77 | D39: 26 | E39: =Plan!J77 | F39: =Plan!K77 | G39: =F39-E39 | H39: =Plan!I77 | I39: =Plan!O77
A40: 36 | B40: 3.5 | C40: =Plan!C32 | D40: 16 | E40: =Plan!J32 | F40: =Plan!K32 | G40: =F40-E40 | H40: =Plan!I32 | I40: =Plan!O32
A41: 37 | B41: 4.13 | C41: =Plan!C78 | D41: 21 | E41: =Plan!J78 | F41: =Plan!K78 | G41: =F41-E41 | H41: =Plan!I78 | I41: =Plan!O78
A42: 38 | B42: 4.2 | C42: =Plan!C38 | D42: 16 | E42: =Plan!J38 | F42: =Plan!K38 | G42: =F42-E42 | H42: =Plan!I38 | I42: =Plan!O38
A43: 39 | B43: 4.3 | C43: =Plan!C39 | D43: 13 | E43: =Plan!J39 | F43: =Plan!K39 | G43: =F43-E43 | H43: =Plan!I39 | I43: =Plan!O39
A44: 40 | B44: 2.12 | C44: =Plan!C24 | D44: 12 | E44: =Plan!J24 | F44: =Plan!K24 | G44: =F44-E44 | H44: =Plan!I24 | I44: =Plan!O24
A45: 41 | B45: 4.5 | C45: =Plan!C41 | D45: 14 | E45: =Plan!J41 | F45: =Plan!K41 | G45: =F45-E45 | H45: =Plan!I41 | I45: =Plan!O41
A46: 42 | B46: 2.10 | C46: =Plan!C22 | D46: 12 | E46: =Plan!J22 | F46: =Plan!K22 | G46: =F46-E46 | H46: =Plan!I22 | I46: =Plan!O22
A47: 43 | B47: 6.11 | C47: =Plan!C68 | D47: 7 | E47: =Plan!J68 | F47: =Plan!K68 | G47: =F47-E47 | H47: =Plan!I68 | I47: =Plan!O68
A48: 44 | B48: 6.20 | C48: =Plan!C79 | D48: 16 | E48: =Plan!J79 | F48: =Plan!K79 | G48: =F48-E48 | H48: =Plan!I79 | I48: =Plan!O79
A49: 45 | B49: 3.3 | C49: =Plan!C30 | D49: 15 | E49: =Plan!J30 | F49: =Plan!K30 | G49: =F49-E49 | H49: =Plan!I30 | I49: =Plan!O30
A50: 46 | B50: 4.14 | C50: =Plan!C80 | D50: 15 | E50: =Plan!J80 | F50: =Plan!K80 | G50: =F50-E50 | H50: =Plan!I80 | I50: =Plan!O80
A51: 47 | B51: 3.7 | C51: =Plan!C34 | D51: 12 | E51: =Plan!J34 | F51: =Plan!K34 | G51: =F51-E51 | H51: =Plan!I34 | I51: =Plan!O34
A52: 48 | B52: 4.20 | C52: =Plan!C95 | D52: 11 | E52: =Plan!J95 | F52: =Plan!K95 | G52: =F52-E52 | H52: =Plan!I95 | I52: =Plan!O95
A53: 49 | B53: 5.6 | C53: =Plan!C53 | D53: 9 | E53: =Plan!J53 | F53: =Plan!K53 | G53: =F53-E53 | H53: =Plan!I53 | I53: =Plan!O53
A54: 50 | B54: 5.1 | C54: =Plan!C48 | D54: 10 | E54: =Plan!J48 | F54: =Plan!K48 | G54: =F54-E54 | H54: =Plan!I48 | I54: =Plan!O48
A55: 51 | B55: 5.2 | C55: =Plan!C49 | D55: 12 | E55: =Plan!J49 | F55: =Plan!K49 | G55: =F55-E55 | H55: =Plan!I49 | I55: =Plan!O49
A56: 52 | B56: 3.6 | C56: =Plan!C33 | D56: 13 | E56: =Plan!J33 | F56: =Plan!K33 | G56: =F56-E56 | H56: =Plan!I33 | I56: =Plan!O33
A57: 53 | B57: 3.9 | C57: =Plan!C35 | D57: 12 | E57: =Plan!J35 | F57: =Plan!K35 | G57: =F57-E57 | H57: =Plan!I35 | I57: =Plan!O35
A58: 54 | B58: 4.24 | C58: =Plan!C120 | D58: 8 | E58: =Plan!J120 | F58: =Plan!K120 | G58: =F58-E58 | H58: =Plan!I120 | I58: =Plan!O120
A59: 55 | B59: 6.31 | C59: =Plan!C108 | D59: 7 | E59: =Plan!J108 | F59: =Plan!K108 | G59: =F59-E59 | H59: =Plan!I108 | I59: =Plan!O108
A60: 56 | B60: 6.22 | C60: =Plan!C83 | D60: 10 | E60: =Plan!J83 | F60: =Plan!K83 | G60: =F60-E60 | H60: =Plan!I83 | I60: =Plan!O83
A61: 57 | B61: 6.1 | C61: =Plan!C58 | D61: 11 | E61: =Plan!J58 | F61: =Plan!K58 | G61: =F61-E61 | H61: =Plan!I58 | I61: =Plan!O58
A62: 58 | B62: 5.12 | C62: =Plan!C85 | D62: 9 | E62: =Plan!J85 | F62: =Plan!K85 | G62: =F62-E62 | H62: =Plan!I85 | I62: =Plan!O85
A63: 59 | B63: 4.23 | C63: =Plan!C118 | D63: 7 | E63: =Plan!J118 | F63: =Plan!K118 | G63: =F63-E63 | H63: =Plan!I118 | I63: =Plan!O118
A64: 60 | B64: 4.19 | C64: =Plan!C94 | D64: 6 | E64: =Plan!J94 | F64: =Plan!K94 | G64: =F64-E64 | H64: =Plan!I94 | I64: =Plan!O94
A65: 61 | B65: 5.14 | C65: =Plan!C91 | D65: 7 | E65: =Plan!J91 | F65: =Plan!K91 | G65: =F65-E65 | H65: =Plan!I91 | I65: =Plan!O91
A66: 62 | B66: 5.4 | C66: =Plan!C51 | D66: 9 | E66: =Plan!J51 | F66: =Plan!K51 | G66: =F66-E66 | H66: =Plan!I51 | I66: =Plan!O51
A67: 63 | B67: 5.5 | C67: =Plan!C52 | D67: 9 | E67: =Plan!J52 | F67: =Plan!K52 | G67: =F67-E67 | H67: =Plan!I52 | I67: =Plan!O52
A68: 64 | B68: 5.9 | C68: =Plan!C56 | D68: 8 | E68: =Plan!J56 | F68: =Plan!K56 | G68: =F68-E68 | H68: =Plan!I56 | I68: =Plan!O56
A69: 65 | B69: 5.15 | C69: =Plan!C96 | D69: 5 | E69: =Plan!J96 | F69: =Plan!K96 | G69: =F69-E69 | H69: =Plan!I96 | I69: =Plan!O96
A70: 66 | B70: 6.9 | C70: =Plan!C66 | D70: 6 | E70: =Plan!J66 | F70: =Plan!K66 | G70: =F70-E70 | H70: =Plan!I66 | I70: =Plan!O66
A71: 67 | B71: 6.34 | C71: =Plan!C111 | D71: 4 | E71: =Plan!J111 | F71: =Plan!K111 | G71: =F71-E71 | H71: =Plan!I111 | I71: =Plan!O111
A72: 68 | B72: 2.11 | C72: =Plan!C23 | D72: 9 | E72: =Plan!J23 | F72: =Plan!K23 | G72: =F72-E72 | H72: =Plan!I23 | I72: =Plan!O23
A73: 69 | B73: 4.17 | C73: =Plan!C92 | D73: 6 | E73: =Plan!J92 | F73: =Plan!K92 | G73: =F73-E73 | H73: =Plan!I92 | I73: =Plan!O92
A74: 70 | B74: 4.7 | C74: =Plan!C43 | D74: 5 | E74: =Plan!J43 | F74: =Plan!K43 | G74: =F74-E74 | H74: =Plan!I43 | I74: =Plan!O43
A75: 71 | B75: 5.19 | C75: =Plan!C106 | D75: 5 | E75: =Plan!J106 | F75: =Plan!K106 | G75: =F75-E75 | H75: =Plan!I106 | I75: =Plan!O106
A76: 72 | B76: 6.8 | C76: =Plan!C65 | D76: 6 | E76: =Plan!J65 | F76: =Plan!K65 | G76: =F76-E76 | H76: =Plan!I65 | I76: =Plan!O65
A77: 73 | B77: 4.18 | C77: =Plan!C93 | D77: 4 | E77: =Plan!J93 | F77: =Plan!K93 | G77: =F77-E77 | H77: =Plan!I93 | I77: =Plan!O93
A78: 74 | B78: 2.16 | C78: =Plan!C119 | D78: 6 | E78: =Plan!J119 | F78: =Plan!K119 | G78: =F78-E78 | H78: =Plan!I119 | I78: =Plan!O119
A79: 75 | B79: 4.4 | C79: =Plan!C40 | D79: 7 | E79: =Plan!J40 | F79: =Plan!K40 | G79: =F79-E79 | H79: =Plan!I40 | I79: =Plan!O40
A80: 76 | B80: 6.3 | C80: =Plan!C60 | D80: 8 | E80: =Plan!J60 | F80: =Plan!K60 | G80: =F80-E80 | H80: =Plan!I60 | I80: =Plan!O60
A81: 77 | B81: 6.26 | C81: =Plan!C99 | D81: 4 | E81: =Plan!J99 | F81: =Plan!K99 | G81: =F81-E81 | H81: =Plan!I99 | I81: =Plan!O99
A82: 78 | B82: 6.33 | C82: =Plan!C110 | D82: 6 | E82: =Plan!J110 | F82: =Plan!K110 | G82: =F82-E82 | H82: =Plan!I110 | I82: =Plan!O110
A83: 79 | B83: 5.7 | C83: =Plan!C54 | D83: 3 | E83: =Plan!J54 | F83: =Plan!K54 | G83: =F83-E83 | H83: =Plan!I54 | I83: =Plan!O54
A84: 80 | B84: 6.32 | C84: =Plan!C109 | D84: 5 | E84: =Plan!J109 | F84: =Plan!K109 | G84: =F84-E84 | H84: =Plan!I109 | I84: =Plan!O109
A85: 81 | B85: 5.16 | C85: =Plan!C97 | D85: 2 | E85: =Plan!J97 | F85: =Plan!K97 | G85: =F85-E85 | H85: =Plan!I97 | I85: =Plan!O97
A86: 82 | B86: 6.2 | C86: =Plan!C59 | D86: 7 | E86: =Plan!J59 | F86: =Plan!K59 | G86: =F86-E86 | H86: =Plan!I59 | I86: =Plan!O59
A87: 83 | B87: 6.15 | C87: =Plan!C72 | D87: 1 | E87: =Plan!J72 | F87: =Plan!K72 | G87: =F87-E87 | H87: =Plan!I72 | I87: =Plan!O72
A88: 84 | B88: 4.25 | C88: =Plan!C121 | D88: 5 | E88: =Plan!J121 | F88: =Plan!K121 | G88: =F88-E88 | H88: =Plan!I121 | I88: =Plan!O121
A89: 85 | B89: 5.8 | C89: =Plan!C55 | D89: 1 | E89: =Plan!J55 | F89: =Plan!K55 | G89: =F89-E89 | H89: =Plan!I55 | I89: =Plan!O55
A90: 86 | B90: 4.15 | C90: =Plan!C81 | D90: 4 | E90: =Plan!J81 | F90: =Plan!K81 | G90: =F90-E90 | H90: =Plan!I81 | I90: =Plan!O81
A91: 87 | B91: 6.12 | C91: =Plan!C69 | D91: 1 | E91: =Plan!J69 | F91: =Plan!K69 | G91: =F91-E91 | H91: =Plan!I69 | I91: =Plan!O69
A92: 88 | B92: 6.10 | C92: =Plan!C67 | D92: 6 | E92: =Plan!J67 | F92: =Plan!K67 | G92: =F92-E92 | H92: =Plan!I67 | I92: =Plan!O67
A93: 89 | B93: 6.25 | C93: =Plan!C89 | D93: 3 | E93: =Plan!J89 | F93: =Plan!K89 | G93: =F93-E93 | H93: =Plan!I89 | I93: =Plan!O89
A94: 90 | B94: 6.27 | C94: =Plan!C100 | D94: 2 | E94: =Plan!J100 | F94: =Plan!K100 | G94: =F94-E94 | H94: =Plan!I100 | I94: =Plan!O100
A95: 91 | B95: 6.21 | C95: =Plan!C82 | D95: 2 | E95: =Plan!J82 | F95: =Plan!K82 | G95: =F95-E95 | H95: =Plan!I82 | I95: =Plan!O82
A96: 92 | B96: 5.13 | C96: =Plan!C86 | D96: 1 | E96: =Plan!J86 | F96: =Plan!K86 | G96: =F96-E96 | H96: =Plan!I86 | I96: =Plan!O86
A97: 93 | B97: 5.17 | C97: =Plan!C98 | D97: 3 | E97: =Plan!J98 | F97: =Plan!K98 | G97: =F97-E97 | H97: =Plan!I98 | I97: =Plan!O98
A98: 94 | B98: 6.5 | C98: =Plan!C62 | D98: 5 | E98: =Plan!J62 | F98: =Plan!K62 | G98: =F98-E98 | H98: =Plan!I62 | I98: =Plan!O62
A99: 95 | B99: 4.16 | C99: =Plan!C90 | D99: 3 | E99: =Plan!J90 | F99: =Plan!K90 | G99: =F99-E99 | H99: =Plan!I90 | I99: =Plan!O90
A100: 96 | B100: 6.30 | C100: =Plan!C107 | D100: 1 | E100: =Plan!J107 | F100: =Plan!K107 | G100: =F100-E100 | H100: =Plan!I107 | I100: =Plan!O107
A101: 97 | B101: 5.11 | C101: =Plan!C84 | D101: 2 | E101: =Plan!J84 | F101: =Plan!K84 | G101: =F101-E101 | H101: =Plan!I84 | I101: =Plan!O84
...

Sheet Propuesta original
A1: Propuesta original (31-ago-2026) — plan por semanas
A2: Tal como se presentó: 6 fases en máximo 8 semanas, en secuencia. Sirve de referencia contra el plan optimizado.
A4: Fase | B4: Nombre | C4: Qué se realiza | D4: Semana inicio | E4: Semana fin | F4: 1 | G4: 2 | H4: 3 | I4: 4 | J4: 5 | K4: 6 | L4: 7 | M4: 8
A5: 1 | B5: Diseño y arquitectura | C5: Wireframes, modelo de datos y definición del stack (Next.js, Supabase, Resend). | D5: 1 | E5: 2
A6: 2 | B6: Landing y autenticación | C6: Página pública (misión, visión, servicios) y sistema de registro e inicio de sesión. | D6: 2 | E6: 3
A7: 3 | B7: Flujo de solicitud de crédito | C7: Formulario de solicitud (50 %/100 %, monto según tope), envío y notificación por correo. | D7: 3 | E7: 5
A8: 4 | B8: Panel de administración | C8: Dashboard de solicitudes y asociados, aprobación/rechazo y notificación automática de resultado. | D8: 5 | E8: 6
A9: 5 | B9: Convenios y pulido | C9: Sección de empresas aliadas y ajustes visuales, incluido el diseño responsive para celular. | D9: 6 | E9: 7
A10: 6 | B10: Pruebas y lanzamiento | C10: Pruebas con usuarios reales, corrección de errores, capacitación y despliegue en producción. | D10: 7 | E10: 8
A12: Qué cambia en el plan optimizado
A13: • Las 6 fases se partieron en actividades pequeñas (hoja Plan), cada una con un peso de 1 a 5.
A14: • En vez de ir fase por fase, dos filas de trabajo toman actividades de una cola común: lo que no depende de otra cosa avanza en paralelo.
A15: • Se agregaron actividades que surgieron en el desarrollo (Origen = «Agregado»): ingreso con código, afiliación, importación de asociados, política de datos.
A16: • Las fechas no se usan: el tiempo se mide en bloques y semanas relativas.

Sheet Pesos
A1: Escala de pesos (1 a 5)
A2: El peso mide el esfuerzo de una actividad y define su largo en el Gantt.
A4: Peso | B4: Nivel | C4: Bloques | D4: Equivale a | E4: Ejemplo del proyecto | F4: Actividades con este peso
A5: 1 | B5: Muy baja | C5: 1 | D5: Media jornada | E5: Borrar /login y /dashboard; capacitación | F5: =COUNTIF(Plan!$D$5:$D$129,A5)
A6: 2 | B6: Baja | C6: 2 | D6: 1 jornada | E6: SMTP con Resend; proteger /cuenta en proxy.ts | F6: =COUNTIF(Plan!$D$5:$D$129,A6)
A7: 3 | B7: Media | C7: 3 | D7: 1,5 jornadas | E7: Verificación del código OTP; /cuenta con datos reales | F7: =COUNTIF(Plan!$D$5:$D$129,A7)
A8: 4 | B8: Alta | C8: 4 | D8: 2 jornadas | E8: Panel /admin; afiliación con Resend; importar asociados | F8: =COUNTIF(Plan!$D$5:$D$129,A8)
A9: 5 | B9: Muy alta | C9: 5 | D9: 2,5 jornadas o más | E9: Reservado para trabajos que conviene partir en dos | F9: =COUNTIF(Plan!$D$5:$D$129,A9)
A11: Reglas de simultaneidad
A12: • Dos actividades pueden ir al mismo tiempo si ninguna depende (directa o indirectamente) de la otra.
A13: • Hay 2 filas de trabajo: como máximo 2 actividades a la vez. Las demás esperan en la cola, que no tiene límite.
A14: • «Simultánea: No» significa que la actividad ocupa las 2 filas (p. ej. el despliegue a producción).
A15: • La equivalencia en jornadas se ajusta en Resumen → Bloques por semana.

Sheet Bitácora
A1: Bitácora de avances
A2: Cada reporte de un agente que el supervisor aplicó al plan.
A4: Fecha | B4: Agente | C4: Actividades | D4: Cambio | E4: Detalle
A5: 2026-10-23 | B5: sesión principal | C5: 6.43 (P-144) | D5: PR #13 develop → main fusionado y desplegado en Vercel | E5: Sebas fusionó el PR #13; Vercel desplegó a producción (commit 10b8b8a, estado READY). La corrección de solicitudes de afiliación y el aviso por cambio de datos ya están en producción. Siguen pendientes pgTAP 35 y 36 (6.44, P-145) y la revisión de seguridad y QA (6.42) hasta que haya virtualización.
A6: 2026-10-23 | B6: sesión principal | C6: 2.17, 4.26, 4.27, 6.42, 6.44 (P-143, P-145) | D6: Selfie probada en celular real; dos funciones nuevas listas pendientes de migrar | E6: 2.17 y P-143 Hecho (Sebas probó la selfie en celular real). Nuevas En curso: 4.26 aviso al asociado por cambio de datos (migración 20261022000000, pgTAP 35) y 4.27 corregir datos de una solicitud de afiliación antes de aprobar (migración 20261023000000, pgTAP 36, pedido de Ricardo). Nueva 6.44 y P-145 (Sebas): aplicar ambas migraciones y correr pgTAP 35 y 36 cuando tenga Docker. 6.42 suma 4.26 y 4.27: falta su revisión de seguridad y QA. Verificación: vitest 778, tsc, lint y build en verde; entregables y PDF actualizados.
A7: 2026-10-22 | B7: sesión principal | C7: 4.23, 4.25, 6.41, 6.43, 2.17 (P-143, P-144) | D7: Migración 20261018100000 aplicada; 4.23, 4.25 y 6.41 Hecho; merge a develop; respaldos y logos.rar fuera del repo | E7: migration list --linked confirma 20261018100000 en producción. Commit e0cbe5a en avance-pendientes, merge en develop y push. Los respaldo-*.sql pasaron a ../backups/2026-10-02 y public/logos.rar (solo logos públicos) a la carpeta de la cooperativa. P-143 queda En curso solo con la selfie en celular real (2.17). Nueva actividad 6.43 y pendiente P-144 (Sebas): abrir y fusionar el PR develop → main para desplegar, porque gh no está instalado y la API quedó bloqueada por permisos.
A8: 2026-10-18 | B8: ga-verificador-qa | C8: 3.11, 2.16, 4.24, 4.25, 4.23, 2.17, 6.42 | D8: QA e2e: 395 en verde, spec r-cambios-18oct (19 pruebas), hallazgos F1 y F2 | E8: Sin regresiones (47 omitidas, 0 fallan). 3.11 pasa a Hecho. F1 (desplegable Entidad de Editar datos se reiniciaba) medio, corregido por la sesión principal con onSubmit+startTransition y spec en verde en escritorio y celular. F2 (URL en /cuenta durante la pausa) bajo, aceptado. La selfie con cámara real de celular no se pudo probar: 2.17 sigue En curso.
A9: 2026-10-18 | B9: sesión principal | C9: 2.16, 4.24, 4.25, 4.23, 6.41, 6.42, 3.11 (P-141, P-142, P-143) | D9: Migraciones 20261014000000 y 20261018000000 aplicadas; pgTAP 870 en verde; hallazgos de seguridad corregidos | E9: Sebas aplicó las dos migraciones. 2.16 y 4.24 pasan a Hecho. Se corrigieron RS-A1, M1, M2, M3, M4, B2 (B3 aceptado); nueva migración 20261018100000 (RPC admin_editar_datos_asociado, historial, trigger) y pgTAP 34 con 16 casos; vitest 773 y build en verde. 4.23 y 4.25 quedan En curso hasta aplicar 20261018100000. 6.41 ahora cubre tres migraciones y sigue En curso. P-141 y P-142 Hecho; nuevo P-143 (Sebas): aplicar la migración, sacar respaldo-*.sql y revisar public/logos.rar. Pendiente opcional: avisar por correo al asociado cuando cambian su correo institucional o nómina (ga-correos).
A10: 2026-10-18 | B10: ga-revisor-seguridad | C10: 6.42 | D10: Revisión de seguridad de los cambios sin commit: sin críticos | E10: 1 alto (respaldos con datos personales sin ignorar), 4 medios (pausa saltable, correo institucional sin aviso, regla propio/clientes solo en la app, logos.rar publicado) y 3 bajos. npm audit: 0 vulnerabilidades. Atendidos por la sesión principal.
A11: 2026-10-18 | B11: sesión principal | C11: 4.24, 4.25, 3.11, 2.17, 6.41, 6.42 (P-142) | D11: Pausa del ingreso, avisos, botón de WhatsApp y selfie con perfil propio: código listo, migración sin aplicar | E11: Nuevos 4.24 (pausa en /admin/plataforma, proxy.ts, /cuenta-pausada, historial), 4.25 (avisos una vez al entrar a /cuenta, con conteo y retiro), 3.11 (botón flotante de WhatsApp) y 2.17 (selfie con perfil propio y cámara HD; antes casi toda selfie salía dudosa por usar umbrales de la cédula). Migración 20261018000000 y pgTAP 33 (18 casos). vitest 773, tsc, lint y build en verde; entregables y PDF actualizados. Todas En curso. 6.41 ahora cubre ambas migraciones (20261014000000 y 20261018000000) y depende de 4.24 y 4.25; 6.42 (peso 2 a 3, razón: suma cuatro funciones nuevas) depende de todas. Nuevo P-142. Falta probar la selfie en un celular real.
A12: 2026-10-14 | B12: sesión principal | C12: 4.23, 2.16, 6.41, 6.42 (P-141) | D12: Editar datos del asociado y Afiliación sin repetidos: código listo, migración sin aplicar | E12: Nuevo 4.23: en /admin/asociados/[id], sección «Datos del asociado» con «Editar datos» (solo admin; no a uno mismo ni a sus clientes; 30 cambios por hora; el registro guarda los campos cambiados); 6 pruebas unitarias, vitest 769 en verde. Nuevo 2.16: migración 20261014000000 con trigger que rechaza (23505) afiliaciones con cédula o correo personal o institucional ya con cuenta o solicitud pendiente o contactada; el formulario responde igual que un envío exitoso (S-06); pgTAP 32 (10 casos); al aprobar, mensaje claro si el correo ya existe en Auth. Ambas En curso. Nuevo 6.41 (Sebas aplica la migración y se corre pgTAP; Docker no corría) y 6.42 (revisión de seguridad y QA). Nuevo P-141.
A13: 2026-10-09 | B13: sesión principal | C13: 6.12 (P-54) | D13: Alerta del límite de intentos resuelta desde el cron, no desde Vercel | E13: Vercel Pro sin Observability Plus no permite alertas por texto del log. El cron horario /api/cron/limpiar-fotos revisa el límite (lib/servidor/saludLimite.ts): LIMITE_HMAC_SECRET y conteo de intentos; si falla registra salud_limite_fallo y envía un correo diario a las 8 a. m. de Bogotá a ALERTA_TECNICA_CORREOS o soporte@greenallianceco.com. Documentado en documentacion-tecnica. 763 unitarias, tsc, lint y build en verde. Falta desplegar (Sebas); opcional crear ALERTA_TECNICA_CORREOS en Vercel.
A14: 2026-10-09 | B14: ga-supervisor-avances | C14: 5.4, 5.11, 6.1, 6.2, 6.3, 6.5, 6.15, 6.29, 6.7, 6.14, 6.6, 5.3 (P-37, P-42, P-58, P-70, P-81, P-106, P-108, P-111, P-118 a P-122, P-125, P-140) | D14: Limpieza del plan pedida por Sebas: se cierran tareas ya hechas | E14: Hecho: 5.4 (la página /politica-de-datos existe; la revisión del abogado sigue aparte en P-81), 5.11 (premios de asesores 50 y 100, migración 20261002100000), 6.1 (755 pruebas unitarias en verde), 6.2 (revisión de seguridad del 8-oct con hallazgos corregidos y en producción), 6.3 (e2e escritorio y celular 395 pasaron, 0 fallos), 6.5 (desplegado en www.greenallianceco.com), 6.15 (e2e al día) y 6.29 (entrega final, acta y último pago, cerrada por Sebas hoy). En curso: 6.7 (capacitación por Ricardo), 6.14 (celulares reales) y 6.6 (usuarios reales, sigue durante la garantía). 5.3 queda Bloqueada esperando a la cooperativa (fotos, cifras, testimonios, sedes); 6.12 sigue Pendiente (Sebas). Pendientes cerrados: P-37, P-42, P-58, P-106, P-108, P-111, P-118, P-119, P-120, P-121, P-122, P-125. P-70 y P-81 pasan a En curso. Nuevo P-140: cómo se desactiva o baja de rol a un administrador. Para poder cerrar 6.3 se quitó su dependencia de 5.3, porque el contenido real de la cooperativa no impide el QA.
A15: 2026-10-09 | B15: sesión principal | C15: 6.38, 6.39, 6.40 (P-137, P-138, P-139) | D15: SVM activado, migración 20261009000000 aplicada y código desplegado | E15: Verificado en producción: migración remota aplicada y landing sin números de convenios (6 convenios con whatsapp null; solo queda el WhatsApp de la cooperativa). Pruebas: pgTAP desde cero 32 archivos, 826 PASS; e2e escritorio y celular 395 pasaron, 47 omitidas a propósito por proyecto y 0 fallos (39,9 min); unitarias 755 en verde.
... A134: 2026-09-23 | B134: Claude (sesión principal) | C134: Todas | D134: Creación del Excel de avances | E134: Pendientes desde PENDIENTES.md, plan desde la propuesta (6 fases, 8 semanas) reorganizado en 2 filas con cola infinita y pesos 1–5.
